Workbook

Sheet Summary

Sheet 20260511 Invalid Data
A1: Data Domain | B1: Status March | C1: Status May | D1: KDE | E1: Key Data Element (Thai) | F1: Key Data Element (English) | G1: Src Database | H1: Src Schema | I1: Src Table | J1: Src Column | K1: Business DQ Rules | L1: Prod_ProfilingResult | M1: key | N1: ValidPercentage as of 20260511 | O1: Prod_ThresholdStatus May | P1: Status | Q1: Jobname | R1: Status Test | S1: RootCause | T1: Ticket
A2: Accounting | B2: Cannot be measured | C2: Cannot be measured | D2: KDE00571 | E2: ค่าบำเหน็จ | F2: Commission | G2: sales | H2: salesbenefit_pg | I2: submit_ctrl_detail | J2: amount_pension | K2: Validity | M2: KDE00571sales.salesbenefit_pg.submit_ctrl_detail.amount_pensionValidityAccounting | P2: Cannot be measured | R2: =VLOOKUP(M2,Sheet1!W:X,2,FALSE) -> NOT PASS
A3: Accounting | B3: Cannot be measured | C3: Cannot be measured | D3: KDE00572 | E3: ค่าพาหนะ | F3: Renewal Year Commission | G3: sales | H3: salesbenefit_pg | I3: submit_ctrl_detail | J3: amount_vehicle_fee | K3: Validity | M3: KDE00572sales.salesbenefit_pg.submit_ctrl_detail.amount_vehicle_feeValidityAccounting | P3: Cannot be measured | R3: =VLOOKUP(M3,Sheet1!W:X,2,FALSE) -> NOT PASS
A4: Accounting | B4: Pass | C4: Pass | D4: KDE00383 | E4: อากรสแตมป์ | F4: Revenue Stamp | G4: pos | H4: srvservice | I4: lnrqst | J4: duty | K4: Validity | M4: KDE00383pos.srvservice.lnrqst.dutyValidityAccounting | N4: 100 | O4: Pass | R4: =VLOOKUP(M4,Sheet1!W:X,2,FALSE) -> PASS
A5: Accounting | B5: Pass | C5: Pass | D5: KDE00571 | E5: ค่าบำเหน็จ | F5: Commission | G5: corebiz | H5: ovdebt | I5: debttrndet | J5: benefit | K5: Validity | M5: KDE00571corebiz.ovdebt.debttrndet.benefitValidityAccounting | N5: 100 | O5: Pass | R5: =VLOOKUP(M5,Sheet1!W:X,2,FALSE) -> PASS
A6: Accounting | B6: Pass | C6: Pass | D6: KDE00571 | E6: ค่าบำเหน็จ | F6: Commission | G6: sales | H6: salesbenefit_pg | I6: bank_benefit_detail | J6: amount_commission | K6: Validity | M6: KDE00571sales.salesbenefit_pg.bank_benefit_detail.amount_commissionValidityAccounting | N6: 100 | O6: Pass | R6: =VLOOKUP(M6,Sheet1!W:X,2,FALSE) -> PASS
A7: Accounting | B7: Pass | C7: Pass | D7: KDE00572 | E7: ค่าพาหนะ | F7: Renewal Year Commission | G7: sales | H7: salesbenefit_pg | I7: bank_benefit_detail | J7: amount_renew_commission | K7: Validity | M7: KDE00572sales.salesbenefit_pg.bank_benefit_detail.amount_renew_commissionValidityAccounting | N7: 100 | O7: Pass | R7: =VLOOKUP(M7,Sheet1!W:X,2,FALSE) -> PASS
A8: Accounting | B8: Pass | C8: Pass | D8: KDE00574 | E8: ค่าจัดงานภาค | F8: District Overriding | G8: sales | H8: salesbenefit_pg | I8: bank_benefit_detail | J8: amount_district_ov | K8: Validity | M8: KDE00574sales.salesbenefit_pg.bank_benefit_detail.amount_district_ovValidityAccounting | N8: 100 | O8: Pass | R8: =VLOOKUP(M8,Sheet1!W:X,2,FALSE) -> PASS
A9: Accounting | B9: Pass | C9: Pass | D9: KDE00576 | E9: ค่าจัดงานหน่วย | F9: Unit Overriding | G9: sales | H9: salesbenefit_pg | I9: bank_benefit_detail | J9: amount_unit_ov | K9: Validity | M9: KDE00576sales.salesbenefit_pg.bank_benefit_detail.amount_unit_ovValidityAccounting | N9: 100 | O9: Pass | R9: =VLOOKUP(M9,Sheet1!W:X,2,FALSE) -> PASS
A10: Accounting | B10: Pass | C10: Pass | D10: KDE00578 | E10: ค่าแยกทีมงานภาค | F10: District Spin Off | G10: sales | H10: salesbenefit_pg | I10: bank_benefit_detail | J10: amount_district_so | K10: Validity | M10: KDE00578sales.salesbenefit_pg.bank_benefit_detail.amount_district_soValidityAccounting | N10: 100 | O10: Pass | R10: =VLOOKUP(M10,Sheet1!W:X,2,FALSE) -> PASS
A11: Accounting | B11: Pass | C11: Pass | D11: KDE00579 | E11: ค่าแยกทีมงานศูนย์ | F11: Division Spin Off | G11: sales | H11: salesbenefit_pg | I11: bank_benefit_detail | J11: amount_division_so | K11: Validity | M11: KDE00579sales.salesbenefit_pg.bank_benefit_detail.amount_division_soValidityAccounting | N11: 100 | O11: Pass | R11: =VLOOKUP(M11,Sheet1!W:X,2,FALSE) -> PASS
A12: Accounting | B12: Pass | C12: Pass | D12: KDE00580 | E12: ค่าแยกทีมงานหน่วย | F12: Unit Spin Off | G12: sales | H12: salesbenefit_pg | I12: bank_benefit_detail | J12: amount_unit_so | K12: Validity | M12: KDE00580sales.salesbenefit_pg.bank_benefit_detail.amount_unit_soValidityAccounting | N12: 100 | O12: Pass | R12: =VLOOKUP(M12,Sheet1!W:X,2,FALSE) -> PASS
A13: Accounting | B13: Pass | C13: Pass | D13: KDE00581 | E13: ค่าบริหารเป้าหมายภาค | F13: District Target | G13: sales | H13: salesbenefit_pg | I13: bank_benefit_detail | J13: amount_district_target | K13: Validity | M13: KDE00581sales.salesbenefit_pg.bank_benefit_detail.amount_district_targetValidityAccounting | N13: 100 | O13: Pass | R13: =VLOOKUP(M13,Sheet1!W:X,2,FALSE) -> PASS
A14: Accounting | B14: Pass | C14: Pass | D14: KDE00661 | E14: เลขที่บัญชีธนาคารของตัวแทนในการจ่ายเงิน (payment) - Sales benefit | F14: Bank account number | G14: sales | H14: salesbenefit_pg | I14: master_account_agent | J14: account_no | K14: Completeness | M14: KDE00661sales.salesbenefit_pg.master_account_agent.account_noCompletenessAccounting | N14: 100 | O14: Pass | R14: =VLOOKUP(M14,Sheet1!W:X,2,FALSE) -> PASS
A15: Accounting | B15: Pass | C15: Pass | D15: KDE00661 | E15: เลขที่บัญชีธนาคารของตัวแทนในการจ่ายเงิน (payment) - Sales benefit | F15: Bank account number | G15: sales | H15: salesbenefit_pg | I15: master_account_agent | J15: account_no | K15: Validity | M15: KDE00661sales.salesbenefit_pg.master_account_agent.account_noValidityAccounting | N15: 100 | O15: Pass | R15: =VLOOKUP(M15,Sheet1!W:X,2,FALSE) -> PASS
A16: Claims | B16: Cannot be measured | C16: Cannot be measured | D16: KDE00122 | E16: เลขเรื่องสินไหมประกันชีวิตรายบุคคล | F16: Individual Claim Number | G16: claim | H16: cclaim | I16: claim | J16: orderno,sectioncode | K16: Completeness | M16: KDE00122claim.cclaim.claim.orderno,sectioncodeCompletenessClaims | P16: Sprint40 | R16: =VLOOKUP(M16,Sheet1!W:X,2,FALSE) -> PASS
A17: Claims | B17: Cannot be measured | C17: Cannot be measured | D17: KDE00122 | E17: เลขเรื่องสินไหมประกันชีวิตรายบุคคล | F17: Individual Claim Number | G17: claim | H17: cclaim | I17: claim | J17: orderno,sectioncode | K17: Validity | M17: KDE00122claim.cclaim.claim.orderno,sectioncodeValidityClaims | P17: Sprint40 | R17: =VLOOKUP(M17,Sheet1!W:X,2,FALSE) -> PASS
A18: Claims | B18: Cannot be measured | C18: Cannot be measured | D18: KDE00122 | E18: เลขเรื่องสินไหมประกันชีวิตรายบุคคล | F18: Individual Claim Number | G18: claim | H18: cclaim | I18: eclm | J18: orderno,sectioncode | K18: Validity | M18: KDE00122claim.cclaim.eclm.orderno,sectioncodeValidityClaims | P18: Sprint40 | R18: =VLOOKUP(M18,Sheet1!W:X,2,FALSE) -> PASS
A19: Claims | B19: Cannot be measured | C19: Cannot be measured | D19: KDE00122 | E19: เลขเรื่องสินไหมประกันชีวิตรายบุคคล | F19: Individual Claim Number | G19: claim | H19: cclaim | I19: excinsur | J19: orderno,sectioncode | K19: Validity | M19: KDE00122claim.cclaim.excinsur.orderno,sectioncodeValidityClaims | P19: Sprint40 | R19: =VLOOKUP(M19,Sheet1!W:X,2,FALSE) -> PASS
A20: Claims | B20: Cannot be measured | C20: Cannot be measured | D20: KDE00122 | E20: เลขเรื่องสินไหมประกันชีวิตรายบุคคล | F20: Individual Claim Number | G20: claim | H20: cmortgage | I20: mgclaim | J20: orderno,sectioncode | K20: Validity | M20: KDE00122claim.cmortgage.mgclaim.orderno,sectioncodeValidityClaims | P20: Cannot be measured | R20: =VLOOKUP(M20,Sheet1!W:X,2,FALSE) -> NOT PASS
A21: Claims | B21: Cannot be measured | C21: Cannot be measured | D21: KDE00122 | E21: เลขเรื่องสินไหมประกันชีวิตรายบุคคล | F21: Individual Claim Number | G21: claim | H21: cmortgage | I21: mgfinorder | J21: orderNo,sectionCode | K21: Validity | M21: KDE00122claim.cmortgage.mgfinorder.orderNo,sectionCodeValidityClaims | P21: Sprint40 | R21: =VLOOKUP(M21,Sheet1!W:X,2,FALSE) -> PASS
A22: Claims | B22: Cannot be measured | C22: Cannot be measured | D22: KDE00123 | E22: เลขที่สินไหมสำหรับลูกค้าประกันกลุ่ม | F22: Group Claim Number | G22: policy | H22: cbaac | I22: mclmtrn907 | J22: claimNo | K22: Completeness | M22: KDE00123policy.cbaac.mclmtrn907.claimNoCompletenessClaims | P22: Sprint40 | R22: =VLOOKUP(M22,Sheet1!W:X,2,FALSE) -> PASS
A23: Claims | B23: Cannot be measured | C23: Cannot be measured | D23: KDE00134 | E23: จำนวนเงินที่จ่ายสินไหม | F23: Claim Paid amount | G23: claim | H23: cclaim | I23: dth | J23: payLifeSum,payRiderSum | K23: Completeness | M23: KDE00134claim.cclaim.dth.payLifeSum,payRiderSumCompletenessClaims | P23: Sprint40 | R23: =VLOOKUP(M23,Sheet1!W:X,2,FALSE) -> PASS
A24: Claims | B24: Cannot be measured | C24: Cannot be measured | D24: KDE00134 | E24: จำนวนเงินที่จ่ายสินไหม | F24: Claim Paid amount | G24: policy | H24: mortgage | I24: cert | J24: amount1 | K24: Validity | M24: KDE00134policy.mortgage.cert.amount1ValidityClaims | P24: Sprint40 | R24: =VLOOKUP(M24,Sheet1!W:X,2,FALSE) -> PASS
A25: Claims | B25: Cannot be measured | C25: Cannot be measured | D25: KDE00134 | E25: จำนวนเงินที่จ่ายสินไหม | F25: Claim Paid amount | G25: claim | H25: cclaim | I25: dth | J25: payLifeSum,payRiderSum | K25: Validity | M25: KDE00134claim.cclaim.dth.payLifeSum,payRiderSumValidityClaims | P25: Sprint40 | R25: =VLOOKUP(M25,Sheet1!W:X,2,FALSE) -> PASS
A26: Claims | B26: Cannot be measured | C26: Cannot be measured | D26: KDE00138 | E26: วันที่เกิดเหตุ | F26: occurred date | G26: claim | H26: cclaim | I26: dth | J26: accidentdate | K26: Validity | M26: KDE00138claim.cclaim.dth.accidentdateValidityClaims | P26: Sprint40 | R26: =VLOOKUP(M26,Sheet1!W:X,2,FALSE) -> PASS
A27: Claims | B27: Cannot be measured | C27: Cannot be measured | D27: KDE00138 | E27: วันที่เกิดเหตุ | F27: occurred date | G27: claim | H27: cclaim | I27: iacm | J27: accidentdate | K27: Validity | M27: KDE00138claim.cclaim.iacm.accidentdateValidityClaims | P27: Sprint40 | R27: =VLOOKUP(M27,Sheet1!W:X,2,FALSE) -> PASS
A28: Claims | B28: Cannot be measured | C28: Cannot be measured | D28: KDE00138 | E28: วันที่เกิดเหตุ | F28: occurred date | G28: mbl_db | H28: dbo | I28: after_eclaim | J28: admitdate | K28: Validity | M28: KDE00138mbl_db.dbo.after_eclaim.admitdateValidityClaims | P28: Sprint40 | R28: =VLOOKUP(M28,Sheet1!W:X,2,FALSE) -> PASS
A29: Claims | B29: Cannot be measured | C29: Cannot be measured | D29: KDE00138 | E29: วันที่เกิดเหตุ | F29: occurred date | G29: policy | H29: mortgage | I29: cert | J29: deaddate | K29: Validity | M29: KDE00138policy.mortgage.cert.deaddateValidityClaims | P29: No Result @PROD | Q29: m_PersonDeadDate_Validity_DS403 | R29: =VLOOKUP(M29,Sheet1!W:X,2,FALSE) -> PASS | S29: Incorrect IDQ Mapping Configured | T29: https://tli-edg.atlassian.net/browse/KDEI-551
A30: Claims | B30: Cannot be measured | C30: Cannot be measured | D30: KDE00139 | E30: วันที่เข้ารับการรักษา | F30: Admission date | G30: claim | H30: cclaim | I30: mstwebclaim | J30: admitdate | K30: Completeness | M30: KDE00139claim.cclaim.mstwebclaim.admitdateCompletenessClaims | P30: Sprint40 | R30: =VLOOKUP(M30,Sheet1!W:X,2,FALSE) -> PASS
A31: Claims | B31: Cannot be measured | C31: Cannot be measured | D31: KDE00139 | E31: วันที่เข้ารับการรักษา | F31: Admission date | G31: group_life | H31: glife | I31: hclaim | J31: st_healdate | K31: Completeness | M31: KDE00139group_life.glife.hclaim.st_healdateCompletenessClaims | P31: Sprint40 | R31: =VLOOKUP(M31,Sheet1!W:X,2,FALSE) -> PASS
A32: Claims | B32: Cannot be measured | C32: Cannot be measured | D32: KDE00139 | E32: วันที่เข้ารับการรักษา | F32: Admission date | G32: claim | H32: cclaim | I32: mstwebclaim | J32: admitdate | K32: Validity | M32: KDE00139claim.cclaim.mstwebclaim.admitdateValidityClaims | P32: Sprint40 | R32: =VLOOKUP(M32,Sheet1!W:X,2,FALSE) -> PASS
A33: Claims | B33: Cannot be measured | C33: Cannot be measured | D33: KDE00141 | E33: วันที่อนุมัติสินไหม | F33: Claim Approved date | G33: claim | H33: cmortgage | I33: mgfinorder | J33: claimOkDate | K33: Completeness | M33: KDE00141claim.cmortgage.mgfinorder.claimOkDateCompletenessClaims | P33: Sprint40 | R33: =VLOOKUP(M33,Sheet1!W:X,2,FALSE) -> PASS
A34: Claims | B34: Cannot be measured | C34: Cannot be measured | D34: KDE00142 | E34: วันเดือนปีที่รับเอกสารเคลม | F34: Receive Document Date | G34: group_life | H34: glife | I34: claim | J34: recvdate | K34: Validity | M34: KDE00142group_life.glife.claim.recvdateValidityClaims | P34: Sprint40 | R34: =VLOOKUP(M34,Sheet1!W:X,2,FALSE) -> PASS
A35: Claims | B35: Cannot be measured | C35: Cannot be measured | D35: KDE00143 | E35: เลขที่รับเรื่องในการเรียกร้องสินไหมสำหรับลูกค้าประกันกลุ่ม | F35: Receive CLaim Number | G35: policy | H35: cbaac | I35: mclmrcv907 | J35: receiveNo | K35: Completeness | M35: KDE00143policy.cbaac.mclmrcv907.receiveNoCompletenessClaims | P35: Cannot be measured | R35: =VLOOKUP(M35,Sheet1!W:X,2,FALSE) -> NOT PASS
A36: Claims | B36: Invalid Data | C36: Invalid Data | D36: KDE00125 | E36: เหตุผลที่ปฏิเสธการจ่ายสินไหม | F36: Reject reason | G36: group_life | H36: glife | I36: rejclaim | J36: reject_cause | K36: Completeness | L36: Contact EDM | M36: KDE00125group_life.glife.rejclaim.reject_causeCompletenessClaims | N36: 99.95712 | O36: Fail - Invalid Data | P36: Sprint40 | R36: =VLOOKUP(M36,Sheet1!W:X,2,FALSE) -> PASS
A37: Claims | B37: Invalid Data | C37: Invalid Data | D37: KDE00133 | E37: ค่ารักษาพยาบาลตามใบเสร็จ | F37: Incurred amount | G37: group_life | H37: glife | I37: hclaimrcv | J37: amount | K37: Validity | L37: Contact EDM | M37: KDE00133group_life.glife.hclaimrcv.amountValidityClaims | N37: 99.999962 | O37: Fail - Invalid Data | P37: Sprint40 | R37: =VLOOKUP(M37,Sheet1!W:X,2,FALSE) -> PASS
A38: Claims | B38: Invalid Data | C38: Invalid Data | D38: KDE00138 | E38: วันที่เกิดเหตุ | F38: occurred date | G38: claim | H38: cclaim | I38: mstwebclaim | J38: accidentdate | K38: Validity | L38: Contact EDM | M38: KDE00138claim.cclaim.mstwebclaim.accidentdateValidityClaims | N38: 99.952532 | O38: Fail - Invalid Data | P38: Sprint40 | R38: =VLOOKUP(M38,Sheet1!W:X,2,FALSE) -> PASS
A39: Claims | B39: Invalid Data | C39: Invalid Data | D39: KDE00138 | E39: วันที่เกิดเหตุ | F39: occurred date | G39: claim | H39: cclaim | I39: oacm | J39: accidentdate | K39: Validity | L39: Contact EDM | M39: KDE00138claim.cclaim.oacm.accidentdateValidityClaims | N39: 99.998309 | O39: Fail - Invalid Data | P39: Sprint40 | R39: =VLOOKUP(M39,Sheet1!W:X,2,FALSE) -> PASS
A40: Claims | B40: Invalid Data | C40: Invalid Data | D40: KDE00139 | E40: วันที่เข้ารับการรักษา | F40: Admission date | G40: group_life | H40: glife | I40: hclaim | J40: st_healdate | K40: Validity | L40: Contact EDM | M40: KDE00139group_life.glife.hclaim.st_healdateValidityClaims | N40: 99.999709 | O40: Fail - Invalid Data | P40: Sprint40 | R40: =VLOOKUP(M40,Sheet1!W:X,2,FALSE) -> PASS
A41: Claims | B41: Invalid Data | C41: Invalid Data | D41: KDE00140 | E41: วันเดือนปีที่จ่ายเงินสินไหม | F41: Payment Date | G41: group_life | H41: glife | I41: claim | J41: paydate | K41: Completeness | L41: Contact EDM | M41: KDE00140group_life.glife.claim.paydateCompletenessClaims | N41: 99.870097 | O41: Fail - Invalid Data | P41: Sprint40 | R41: =VLOOKUP(M41,Sheet1!W:X,2,FALSE) -> PASS
A42: Claims | B42: Invalid Data | C42: Invalid Data | D42: KDE00140 | E42: วันเดือนปีที่จ่ายเงินสินไหม | F42: Payment Date | G42: group_life | H42: glife | I42: hclaim | J42: paydate | K42: Completeness | L42: Contact EDM | M42: KDE00140group_life.glife.hclaim.paydateCompletenessClaims | N42: 99.999977 | O42: Fail - Invalid Data | P42: Sprint40 | R42: =VLOOKUP(M42,Sheet1!W:X,2,FALSE) -> PASS
A43: Claims | B43: Invalid Data | C43: Invalid Data | D43: KDE00140 | E43: วันเดือนปีที่จ่ายเงินสินไหม | F43: Payment Date | G43: group_life | H43: glife | I43: medclaim | J43: paydate | K43: Completeness | L43: Contact EDM | M43: KDE00140group_life.glife.medclaim.paydateCompletenessClaims | N43: 99.976534 | O43: Fail - Invalid Data | P43: Sprint40 | R43: =VLOOKUP(M43,Sheet1!W:X,2,FALSE) -> PASS
A44: Claims | B44: Invalid Data | C44: Invalid Data | D44: KDE00140 | E44: วันเดือนปีที่จ่ายเงินสินไหม | F44: Payment Date | G44: group_life | H44: glife | I44: hclaim | J44: paydate | K44: Validity | L44: Contact EDM | M44: KDE00140group_life.glife.hclaim.paydateValidityClaims | N44: 99.99956 | O44: Fail - Invalid Data | P44: Sprint40 | R44: =VLOOKUP(M44,Sheet1!W:X,2,FALSE) -> PASS
A45: Claims | B45: Invalid Data | C45: Invalid Data | D45: KDE00140 | E45: วันเดือนปีที่จ่ายเงินสินไหม | F45: Payment Date | G45: group_life | H45: glife | I45: medclaim | J45: paydate | K45: Validity | L45: Contact EDM | M45: KDE00140group_life.glife.medclaim.paydateValidityClaims | N45: 99.99949 | O45: Fail - Invalid Data | P45: Sprint40 | R45: =VLOOKUP(M45,Sheet1!W:X,2,FALSE) -> PASS
A46: Claims | B46: Invalid Data | C46: Invalid Data | D46: KDE00142 | E46: วันเดือนปีที่รับเอกสารเคลม | F46: Receive Document Date | G46: group_life | H46: glife | I46: hclaim | J46: recvdate | K46: Completeness | L46: Contact EDM | M46: KDE00142group_life.glife.hclaim.recvdateCompletenessClaims | N46: 99.999664 | O46: Fail - Invalid Data | P46: Sprint40 | R46: =VLOOKUP(M46,Sheet1!W:X,2,FALSE) -> PASS
A47: Claims | B47: Invalid Data | C47: Invalid Data | D47: KDE00142 | E47: วันเดือนปีที่รับเอกสารเคลม | F47: Receive Document Date | G47: group_life | H47: glife | I47: hclaim | J47: recvdate | K47: Validity | L47: Contact EDM | M47: KDE00142group_life.glife.hclaim.recvdateValidityClaims | N47: 99.997851 | O47: Fail - Invalid Data | P47: Sprint40 | R47: =VLOOKUP(M47,Sheet1!W:X,2,FALSE) -> PASS
A48: Claims | B48: Invalid Data | C48: Invalid Data | D48: KDE00142 | E48: วันเดือนปีที่รับเอกสารเคลม | F48: Receive Document Date | G48: group_life | H48: glife | I48: medclaim | J48: recvdate | K48: Validity | L48: Contact EDM | M48: KDE00142group_life.glife.medclaim.recvdateValidityClaims | N48: 99.99852 | O48: Fail - Invalid Data | P48: Sprint40 | R48: =VLOOKUP(M48,Sheet1!W:X,2,FALSE) -> PASS
A49: Claims | B49: Pass | C49: Pass | D49: KDE00128 | E49: ช่องการเรียกร้องสินไหม | F49: channel of summit claim | G49: claim | H49: claimonline | I49: registeronline | J49: systemtype | K49: Completeness | M49: KDE00128claim.claimonline.registeronline.systemtypeCompletenessClaims | N49: 100 | O49: Pass | P49: Sprint40 | R49: =VLOOKUP(M49,Sheet1!W:X,2,FALSE) -> Pass with Condition
A50: Claims | B50: Pass | C50: Pass | D50: KDE00128 | E50: ช่องการเรียกร้องสินไหม | F50: channel of summit claim | G50: claim | H50: claimonline | I50: registeronline | J50: systemtype | K50: Integrity | M50: KDE00128claim.claimonline.registeronline.systemtypeIntegrityClaims | N50: 100 | O50: Pass | P50: Sprint40 | R50: =VLOOKUP(M50,Sheet1!W:X,2,FALSE) -> PASS
A51: Claims | B51: Pass | C51: Pass | D51: KDE00132 | E51: ประเภทผลประโยชน์การจ่ายสินไหม | F51: Benefit Type of paid | G51: group_life | H51: glife | I51: claimrcv | J51: claim_type | K51: Integrity | M51: KDE00132group_life.glife.claimrcv.claim_typeIntegrityClaims | N51: 100 | O51: Pass | P51: Sprint40 | R51: =VLOOKUP(M51,Sheet1!W:X,2,FALSE) -> PASS
A52: Claims | B52: Pass | C52: Pass | D52: KDE00132 | E52: ประเภทผลประโยชน์การจ่ายสินไหม | F52: Benefit Type of paid | G52: group_life | H52: glife | I52: hclaimrcv | J52: claim_type | K52: Integrity | M52: KDE00132group_life.glife.hclaimrcv.claim_typeIntegrityClaims | N52: 100 | O52: Pass | P52: Sprint40 | R52: =VLOOKUP(M52,Sheet1!W:X,2,FALSE) -> PASS
A53: Claims | B53: Pass | C53: Pass | D53: KDE00133 | E53: ค่ารักษาพยาบาลตามใบเสร็จ | F53: Incurred amount | G53: group_life | H53: glife | I53: hclaimrcv | J53: amount | K53: Completeness | M53: KDE00133group_life.glife.hclaimrcv.amountCompletenessClaims | N53: 100 | O53: Pass | P53: Sprint40 | R53: =VLOOKUP(M53,Sheet1!W:X,2,FALSE) -> PASS
A54: Claims | B54: Pass | C54: Pass | D54: KDE00138 | E54: วันที่เกิดเหตุ | F54: occurred date | G54: claim | H54: cclaim | I54: dth | J54: accidentdate | K54: Completeness | M54: KDE00138claim.cclaim.dth.accidentdateCompletenessClaims | N54: 100 | O54: Pass | P54: No Result @PROD | Q54: m_AccidentOccurredDate_Completeness_DS68 | R54: =VLOOKUP(M54,Sheet1!W:X,2,FALSE) -> PASS
A55: Claims | B55: Pass | C55: Pass | D55: KDE00138 | E55: วันที่เกิดเหตุ | F55: occurred date | G55: claim | H55: cclaim | I55: iacm | J55: accidentdate | K55: Completeness | M55: KDE00138claim.cclaim.iacm.accidentdateCompletenessClaims | N55: 100 | O55: Pass | P55: Sprint40 | R55: =VLOOKUP(M55,Sheet1!W:X,2,FALSE) -> PASS
A56: Claims | B56: Pass | C56: Pass | D56: KDE00138 | E56: วันที่เกิดเหตุ | F56: occurred date | G56: claim | H56: cclaim | I56: mstwebclaim | J56: accidentdate | K56: Completeness | M56: KDE00138claim.cclaim.mstwebclaim.accidentdateCompletenessClaims | N56: 100 | O56: Pass | P56: Sprint40 | R56: =VLOOKUP(M56,Sheet1!W:X,2,FALSE) -> PASS
A57: Claims | B57: Pass | C57: Pass | D57: KDE00138 | E57: วันที่เกิดเหตุ | F57: occurred date | G57: claim | H57: cclaim | I57: oacm | J57: accidentdate | K57: Completeness | M57: KDE00138claim.cclaim.oacm.accidentdateCompletenessClaims | N57: 100 | O57: Pass | P57: Sprint40 | R57: =VLOOKUP(M57,Sheet1!W:X,2,FALSE) -> PASS
A58: Claims | B58: Pass | C58: Pass | D58: KDE00138 | E58: วันที่เกิดเหตุ | F58: occurred date | G58: mbl_db | H58: dbo | I58: after_eclaim | J58: admitdate | K58: Completeness | M58: KDE00138mbl_db.dbo.after_eclaim.admitdateCompletenessClaims | N58: 100 | O58: Pass | P58: Sprint40 | R58: =VLOOKUP(M58,Sheet1!W:X,2,FALSE) -> PASS
A59: Claims | B59: Pass | C59: Pass | D59: KDE00140 | E59: วันเดือนปีที่จ่ายเงินสินไหม | F59: Payment Date | G59: group_life | H59: glife | I59: claim | J59: paydate | K59: Validity | M59: KDE00140group_life.glife.claim.paydateValidityClaims | N59: 100 | O59: Pass | P59: Sprint40 | R59: =VLOOKUP(M59,Sheet1!W:X,2,FALSE) -> PASS
A60: Claims | B60: Pass | C60: Pass | D60: KDE00141 | E60: วันที่อนุมัติสินไหม | F60: Claim Approved date | G60: claim | H60: claimbook | I60: claimpayment | J60: claimokdate | K60: Completeness | M60: KDE00141claim.claimbook.claimpayment.claimokdateCompletenessClaims | N60: 100 | O60: Pass | P60: Sprint40 | R60: =VLOOKUP(M60,Sheet1!W:X,2,FALSE) -> PASS
A61: Claims | B61: Pass | C61: Pass | D61: KDE00141 | E61: วันที่อนุมัติสินไหม | F61: Claim Approved date | G61: claim | H61: claimbook | I61: claimpayment | J61: claimokdate | K61: Validity | M61: KDE00141claim.claimbook.claimpayment.claimokdateValidityClaims | N61: 100 | O61: Pass | P61: Sprint40 | R61: =VLOOKUP(M61,Sheet1!W:X,2,FALSE) -> PASS
A62: Claims | B62: Pass | C62: Pass | D62: KDE00142 | E62: วันเดือนปีที่รับเอกสารเคลม | F62: Receive Document Date | G62: group_life | H62: glife | I62: claim | J62: recvdate | K62: Completeness | M62: KDE00142group_life.glife.claim.recvdateCompletenessClaims | N62: 100 | O62: Pass | P62: Sprint40 | R62: =VLOOKUP(M62,Sheet1!W:X,2,FALSE) -> PASS
A63: Claims | B63: Pass | C63: Pass | D63: KDE00142 | E63: วันเดือนปีที่รับเอกสารเคลม | F63: Receive Document Date | G63: group_life | H63: glife | I63: medclaim | J63: recvdate | K63: Completeness | M63: KDE00142group_life.glife.medclaim.recvdateCompletenessClaims | N63: 100 | O63: Pass | P63: Sprint40 | R63: =VLOOKUP(M63,Sheet1!W:X,2,FALSE) -> PASS
A64: Claims | B64: Pass | C64: Pass | D64: KDE00143 | E64: เลขที่รับเรื่องในการเรียกร้องสินไหมสำหรับลูกค้าประกันกลุ่ม | F64: Receive CLaim Number | G64: group_life | H64: glife | I64: claim | J64: recvno | K64: Completeness | M64: KDE00143group_life.glife.claim.recvnoCompletenessClaims | N64: 100 | O64: Pass | P64: Sprint40 | R64: =VLOOKUP(M64,Sheet1!W:X,2,FALSE) -> PASS
A65: Claims | B65: Pass | C65: Pass | D65: KDE00143 | E65: เลขที่รับเรื่องในการเรียกร้องสินไหมสำหรับลูกค้าประกันกลุ่ม | F65: Receive CLaim Number | G65: group_life | H65: glife | I65: hclaim | J65: recvno | K65: Completeness | M65: KDE00143group_life.glife.hclaim.recvnoCompletenessClaims | N65: 100 | O65: Pass | P65: Sprint40 | R65: =VLOOKUP(M65,Sheet1!W:X,2,FALSE) -> PASS
A66: Claims | B66: Pass | C66: Pass | D66: KDE00143 | E66: เลขที่รับเรื่องในการเรียกร้องสินไหมสำหรับลูกค้าประกันกลุ่ม | F66: Receive CLaim Number | G66: group_life | H66: glife | I66: medclaim | J66: recvno | K66: Completeness | M66: KDE00143group_life.glife.medclaim.recvnoCompletenessClaims | N66: 100 | O66: Pass | P66: Sprint40 | R66: =VLOOKUP(M66,Sheet1!W:X,2,FALSE) -> PASS
... A75: Claims | B75: Pass | C75: Pass | D75: KDE00434 | E75: สถานะการพิจารณา | F75: Claim status | G75: claim | H75: claimbook | I75: claimpayment | J75: remarkno | K75: Integrity | M75: KDE00434claim.claimbook.claimpayment.remarknoIntegrityClaims | N75: 100 | O75: Pass | P75: Sprint40 | R75: =VLOOKUP(M75,Sheet1!W:X,2,FALSE) -> PASS
A76: Customer | B76: Cannot be measured | C76: Cannot be measured | D76: KDE00001 | E76: หมายเลขโทรศัพท์มือถือของผู้เอาประกัน | F76: Policyholder Mobile Phone Number | G76: underwrite | H76: cunderwrite | I76: phone | J76: phoneno | K76: Validity | M76: KDE00001underwrite.cunderwrite.phone.phonenoValidityCustomer | O76: No Data Found | P76: No Result @PROD | Q76: m_MobilePhoneNumber_Validity_DS797 | R76: =VLOOKUP(M76,Sheet1!W:X,2,FALSE) -> PASS | S76: Check data in partioned tables: cunderwrite.phoneYYMM
A77: Customer | B77: Cannot be measured | C77: Invalid Data | D77: KDE00002 | E77: หมายเลขโทรศัพท์สถานทีทำงานของผู้เอาประกัน | F77: Policyholder Work address_Phone No | G77: tlprompt | H77: public | I77: address | J77: telno | K77: Validity | L77: Contact EDM | M77: KDE00002tlprompt.public.address.mobilenoValidityCustomer | N77: 99.896829 | O77: Fail - Invalid Data | R77: =VLOOKUP(M77,Sheet1!W:X,2,FALSE) -> PASS
A78: Customer | B78: Cannot be measured | C78: Invalid Data | D78: KDE00002 | E78: หมายเลขโทรศัพท์สถานทีทำงานของผู้เอาประกัน | F78: Policyholder Work address_Phone No | G78: tlprompt | H78: public | I78: address | J78: mobileno | K78: Validity | L78: Contact EDM | M78: KDE00002tlprompt.public.address.mobilenoValidityCustomer | N78: 99.896829 | O78: Fail - Invalid Data | R78: =VLOOKUP(M78,Sheet1!W:X,2,FALSE) -> PASS
A79: Customer | B79: Cannot be measured | C79: Cannot be measured | D79: KDE00005 | E79: เลขที่บัตรประชาชนของผู้รับมอบสิทธิ | F79: Assignee Identity Number | G79: pos | H79: srvservice | I79: delegatemast | J79: referenceid | K79: Completeness | M79: KDE00005pos.srvservice.delegatemast.referenceidCompletenessCustomer | P79: Cannot be measured | R79: =VLOOKUP(M79,Sheet1!W:X,2,FALSE) -> FIXED
A80: Customer | B80: Cannot be measured | C80: Cannot be measured | D80: KDE00005 | E80: เลขประจำตัวประชาชนของผู้ปกครอง คบ. | F80: KB's Identification Number | G80: tlprompt | H80: public | I80: kb | J80: identifyid | K80: Completeness | M80: KDE00005tlprompt.public.kb.identifyidCompletenessCustomer | P80: Cannot be measured | R80: =VLOOKUP(M80,Sheet1!W:X,2,FALSE) -> FIXED
A81: Customer | B81: Cannot be measured | C81: Cannot be measured | D81: KDE00005 | E81: เลขประจำตัวประชาชนของผู้เอาประกันภัย | F81: Policyholder Identification Number | G81: claim | H81: cclaim | I81: eclaimform | J81: citizenid | K81: Completeness | M81: KDE00005claim.cclaim.eclaimform.citizenidCompletenessCustomer | P81: Cannot be measured | R81: =VLOOKUP(M81,Sheet1!W:X,2,FALSE) -> FIXED
A82: Customer | B82: Cannot be measured | C82: Cannot be measured | D82: KDE00005 | E82: เลขประจำตัวประชาชนของผู้เอาประกันภัย | F82: Policyholder Identification Number | G82: common_db | H82: dbo | I82: tb_prospect | J82: citizen_id | K82: Completeness | M82: KDE00005common_db.dbo.tb_prospect.citizen_idCompletenessCustomer | P82: Cannot be measured | R82: =VLOOKUP(M82,Sheet1!W:X,2,FALSE) -> FIXED
A83: Customer | B83: Cannot be measured | C83: Cannot be measured | D83: KDE00005 | E83: เลขประจำตัวประชาชนของผู้เอาประกันภัย | F83: Policyholder Identification Number | G83: customer | H83: party | I83: party | J83: govt_id | K83: Completeness | M83: KDE00005customer.party.party.govt_idCompletenessCustomer | P83: Cannot be measured | R83: =VLOOKUP(M83,Sheet1!W:X,2,FALSE) -> FIXED
A84: Customer | B84: Cannot be measured | C84: Cannot be measured | D84: KDE00005 | E84: เลขประจำตัวประชาชนของผู้เอาประกันภัย | F84: Policyholder Identification Number | G84: dfl | H84: dfl | I84: mcaapplications | J84: identifyid | K84: Completeness | M84: KDE00005dfl.dfl.mcaapplications.identifyidCompletenessCustomer | P84: Cannot be measured | R84: =VLOOKUP(M84,Sheet1!W:X,2,FALSE) -> FIXED
A85: Customer | B85: Cannot be measured | C85: Cannot be measured | D85: KDE00005 | E85: เลขประจำตัวประชาชนของผู้เอาประกันภัย | F85: Policyholder Identification Number | G85: group_life | H85: glife | I85: citizenid | J85: referenceid | K85: Completeness | M85: KDE00005group_life.glife.citizenid.referenceidCompletenessCustomer | P85: Cannot be measured | R85: =VLOOKUP(M85,Sheet1!W:X,2,FALSE) -> FIXED
A86: Customer | B86: Cannot be measured | C86: Cannot be measured | D86: KDE00005 | E86: เลขประจำตัวประชาชนของผู้เอาประกันภัย | F86: Policyholder Identification Number | G86: policy | H86: mstperson | I86: person | J86: referenceid | K86: Completeness | M86: KDE00005policy.mstperson.person.referenceidCompletenessCustomer | P86: Cannot be measured | R86: =VLOOKUP(M86,Sheet1!W:X,2,FALSE) -> FIXED
A87: Customer | B87: Cannot be measured | C87: Cannot be measured | D87: KDE00005 | E87: เลขประจำตัวประชาชนของผู้เอาประกันภัย | F87: Policyholder Identification Number | G87: policy | H87: universal | I87: partialwithdraw | J87: referenceid | K87: Completeness | M87: KDE00005policy.universal.partialwithdraw.referenceidCompletenessCustomer | P87: Cannot be measured | R87: =VLOOKUP(M87,Sheet1!W:X,2,FALSE) -> FIXED
A88: Customer | B88: Cannot be measured | C88: Cannot be measured | D88: KDE00005 | E88: เลขประจำตัวประชาชนของผู้เอาประกันภัย | F88: Policyholder Identification Number | G88: pos | H88: srvservice | I88: dvtran | J88: referenceid | K88: Completeness | M88: KDE00005pos.srvservice.dvtran.referenceidCompletenessCustomer | P88: Cannot be measured | R88: =VLOOKUP(M88,Sheet1!W:X,2,FALSE) -> FIXED
A89: Customer | B89: Cannot be measured | C89: Cannot be measured | D89: KDE00005 | E89: เลขประจำตัวประชาชนของผู้เอาประกันภัย | F89: Policyholder Identification Number | G89: tlprompt | H89: public | I89: mcaapplications | J89: identifyid | K89: Completeness | M89: KDE00005tlprompt.public.mcaapplications.identifyidCompletenessCustomer | P89: Cannot be measured | R89: =VLOOKUP(M89,Sheet1!W:X,2,FALSE) -> FIXED
A90: Customer | B90: Cannot be measured | C90: Cannot be measured | D90: KDE00005 | E90: เลขประจำตัวประชาชนของผู้เอาประกันภัย | F90: Policyholder Identification Number | G90: underwrite | H90: cunderwrite | I90: appln | J90: idno | K90: Completeness | M90: KDE00005underwrite.cunderwrite.appln.idnoCompletenessCustomer | P90: Cannot be measured | R90: =VLOOKUP(M90,Sheet1!W:X,2,FALSE) -> FIXED
... A113: Customer | B113: Cannot be measured | C113: Cannot be measured | D113: KDE00007 | E113: เลขประจำตัวผู้เสียภาษีอากร | F113: Taxpayer identification number | G113: group_life | H113: glife | I113: engcompany | J113: regisnumber | K113: Completeness | M113: KDE00007group_life.glife.engcompany.regisnumberCompletenessCustomer | P113: Cannot be measured | R113: =VLOOKUP(M113,Sheet1!W:X,2,FALSE) -> FIXED
A114: Customer | B114: Cannot be measured | C114: Cannot be measured | D114: KDE00007 | E114: เลขประจำตัวผู้เสียภาษีอากร | F114: Taxpayer identification number | G114: tlprompt | H114: public | I114: payment | J114: personidtax | K114: Completeness | M114: KDE00007tlprompt.public.payment.personidtaxCompletenessCustomer | N114: 0.30818099 | O114: Fail - Invalid Rules | R114: =VLOOKUP(M114,Sheet1!W:X,2,FALSE) -> PASS
A115: Customer | B115: Cannot be measured | C115: Cannot be measured | D115: KDE00007 | E115: เลขประจำตัวผู้เสียภาษีอากร | F115: Taxpayer identification number | G115: group_life | H115: glife | I115: engcompany | J115: regisnumber | K115: Validity | M115: KDE00007group_life.glife.engcompany.regisnumberValidityCustomer | P115: Cannot be measured | R115: =VLOOKUP(M115,Sheet1!W:X,2,FALSE) -> FIXED
A116: Customer | B116: Cannot be measured | C116: Cannot be measured | D116: KDE00007 | E116: เลขประจำตัวผู้เสียภาษีอากร | F116: Taxpayer identification number | G116: policy | H116: cbranch | I116: nbnewappfield | J116: taxid | K116: Validity | M116: KDE00007policy.cbranch.nbnewappfield.taxidValidityCustomer | P116: Cannot be measured | R116: =VLOOKUP(M116,Sheet1!W:X,2,FALSE) -> NOT PASS
A117: Customer | B117: Cannot be measured | C117: Cannot be measured | D117: KDE00007 | E117: เลขประจำตัวผู้เสียภาษีอากร | F117: Taxpayer identification number | G117: pos | H117: newservice | I117: consent | J117: referenceid | K117: Validity | M117: KDE00007pos.newservice.consent.referenceidValidityCustomer | P117: Cannot be measured | R117: =VLOOKUP(M117,Sheet1!W:X,2,FALSE) -> NOT PASS
A118: Customer | B118: Cannot be measured | C118: Cannot be measured | D118: KDE00007 | E118: เลขประจำตัวผู้เสียภาษีอากร | F118: Taxpayer identification number | G118: tlprompt | H118: public | I118: payment | J118: personidtax | K118: Validity | M118: KDE00007tlprompt.public.payment.personidtaxValidityCustomer | P118: Cannot be measured | R118: =VLOOKUP(M118,Sheet1!W:X,2,FALSE) -> FIXED
A119: Customer | B119: Cannot be measured | C119: Pass | D119: KDE00008 | E119: เลขที่หนังสือเดินทางของผู้ขอเอาประกัน | F119: Policyholder Passport No. | G119: group_life | H119: glife | I119: passportid | J119: passportid | K119: Completeness | M119: KDE00008group_life.glife.passportid.passportidCompletenessCustomer | N119: 100 | O119: Pass | R119: =VLOOKUP(M119,Sheet1!W:X,2,FALSE) -> PASS
A120: Customer | B120: Cannot be measured | C120: Cannot be measured | D120: KDE00008 | E120: เลขที่หนังสือเดินทางของผู้ขอเอาประกัน | F120: Policyholder Passport No. | G120: tlprompt | H120: public | I120: prospect | J120: passport | K120: Completeness | M120: KDE00008tlprompt.public.prospect.passportCompletenessCustomer | N120: 0.59179662 | O120: Fail - Invalid Rules | R120: =VLOOKUP(M120,Sheet1!W:X,2,FALSE) -> PASS
A121: Customer | B121: Cannot be measured | C121: Cannot be measured | D121: KDE00014 | E121: คำนำหน้าชื่อของผู้ขอเอาประกัน | F121: Applicant's Title | G121: policy | H121: mstperson | I121: name | J121: prename | K121: Integrity | M121: KDE00014policy.mstperson.name.prenameIntegrityCustomer | P121: Cannot be measured | R121: =VLOOKUP(M121,Sheet1!W:X,2,FALSE) -> NOT PASS
A122: Customer | B122: Cannot be measured | C122: Invalid Data | D122: KDE00016 | E122: ชื่อ-นามสกุล ของผู้ขอเอาประกัน | F122: Applicant Name-Surname | G122: group_life | H122: glife | I122: g | J122: fname,lname | K122: Completeness | L122: Contact EDM | M122: KDE00016group_life.glife.g.PersonNameCompletenessCustomer | N122: 99.947261 | O122: Fail - Invalid Data | R122: =VLOOKUP(M122,Sheet1!W:X,2,FALSE) -> PASS
A123: Customer | B123: Cannot be measured | C123: Cannot be measured | D123: KDE00016 | E123: ชื่อ-นามสกุล ของผู้เอาประกัน | F123: Policyholder Name-Surname | G123: dm_db | H123: dbo | I123: l_serv_master | J123: first_name,last_name | K123: Completeness | M123: KDE00016dm_db.dbo.l_serv_master.firstnameCompletenessCustomer | O123: No Data Found | P123: No Result @PROD | Q123: m_PersonName_Completeness_ENT904 | R123: =VLOOKUP(M123,Sheet1!W:X,2,FALSE) -> Pass with Condition | S123: Check data in source table dm_db.dbo.l_serv_master
A124: Customer | B124: Cannot be measured | C124: Cannot be measured | D124: KDE00016 | E124: ชื่อ-นามสกุล ของผู้เอาประกัน | F124: Policyholder Name-Surname | G124: dm_db | H124: dbo | I124: tb_dmmast | J124: firstname,lastname | K124: Completeness | M124: KDE00016dm_db.dbo.tb_dmmast.firstnameCompletenessCustomer | O124: No Data Found | P124: No Result @PROD | Q124: m_PersonName_Completeness_ENT1159 | R124: =VLOOKUP(M124,Sheet1!W:X,2,FALSE) -> Pass with Condition | S124: Check data in source table dm_db.dbo.tb_dmmast
A125: Customer | B125: Cannot be measured | C125: Pass | D125: KDE00016 | E125: ชื่อ-นามสกุล ของผู้เอาประกัน | F125: Policyholder Name-Surname | G125: underwrite | H125: cunderwrite | I125: dmapplication | J125: firstname,lastname | K125: Completeness | M125: KDE00016underwrite.cunderwrite.dmapplication.CustomerNameCompletenessCustomer | N125: 100 | O125: Pass | R125: =VLOOKUP(M125,Sheet1!W:X,2,FALSE) -> Pass with Condition
A126: Customer | B126: Cannot be measured | C126: Cannot be measured | D126: KDE00016 | E126: ชื่อ-นามสกุล ของผู้ขอเอาประกัน | F126: Applicant Name-Surname | G126: customer | H126: common_refund | I126: customers_refund | J126: firstname,lastname | K126: Validity | M126: KDE00016customer.common_refund.customers_refund.PersonNameValidityCustomer | R126: =VLOOKUP(M126,Sheet1!W:X,2,FALSE) -> FIXED
A127: Customer | B127: Cannot be measured | C127: Cannot be measured | D127: KDE00016 | E127: ชื่อ-นามสกุล ของผู้ขอเอาประกัน | F127: Applicant Name-Surname | G127: customer | H127: party | I127: person | J127: fname_th,lname_th | K127: Validity | M127: KDE00016customer.party.person.fname_thValidityCustomer | R127: =VLOOKUP(M127,Sheet1!W:X,2,FALSE) -> NOT PASS
A128: Customer | B128: Cannot be measured | C128: Cannot be measured | D128: KDE00016 | E128: ชื่อ-นามสกุล ของผู้ขอเอาประกัน | F128: Applicant Name-Surname | G128: dfl | H128: dfl | I128: mcaapplications | J128: name,lastname | K128: Validity | M128: KDE00016dfl.dfl.mcaapplications.PersonNameValidityCustomer | R128: =VLOOKUP(M128,Sheet1!W:X,2,FALSE) -> NOT PASS
A129: Customer | B129: Cannot be measured | C129: Cannot be measured | D129: KDE00016 | E129: ชื่อ-นามสกุล ของผู้ขอเอาประกัน | F129: Applicant Name-Surname | G129: finance_acc | H129: accountbranch | I129: paymentmst | J129: firstname,lastname | K129: Validity | M129: KDE00016finance_acc.accountbranch.paymentmst.PersonNameValidityCustomer | R129: =VLOOKUP(M129,Sheet1!W:X,2,FALSE) -> FIXED
A130: Customer | B130: Cannot be measured | C130: Cannot be measured | D130: KDE00016 | E130: ชื่อ-นามสกุล ของผู้ขอเอาประกัน | F130: Applicant Name-Surname | G130: group_life | H130: glife | I130: g | J130: fname,lname | K130: Validity | M130: KDE00016group_life.glife.g.PersonNameValidityCustomer | R130: =VLOOKUP(M130,Sheet1!W:X,2,FALSE) -> NOT PASS
...

Sheet 20260316 Invalid Data
A1: Data Domain | B1: Status | C1: KDE | D1: Key Data Element (Thai) | E1: Key Data Element (English) | F1: Src Database | G1: Src Schema | H1: Src Table | I1: Src Column | J1: Business DQ Rules | K1: Prod_ProfilingResult | L1: IssueCategory | M1: IssueSubCategory | N1: ValidPercentage | O1: Prod_ThresholdStatus
A2: Accounting | B2: Cannot be measured | C2: KDE00571 | D2: ค่าบำเหน็จ | E2: Commission | F2: sales | G2: salesbenefit_pg | H2: submit_ctrl_detail | I2: amount_pension | J2: Validity
A3: Accounting | B3: Cannot be measured | C3: KDE00572 | D3: ค่าพาหนะ | E3: Renewal Year Commission | F3: sales | G3: salesbenefit_pg | H3: submit_ctrl_detail | I3: amount_vehicle_fee | J3: Validity
A4: Accounting | B4: Pass | C4: KDE00383 | D4: อากรสแตมป์ | E4: Revenue Stamp | F4: pos | G4: srvservice | H4: lnrqst | I4: duty | J4: Validity | K4: DS629_StampDutyAmount_Validity_prf | O4: Pass
A5: Accounting | B5: Pass | C5: KDE00571 | D5: ค่าบำเหน็จ | E5: Commission | F5: corebiz | G5: ovdebt | H5: debttrndet | I5: benefit | J5: Validity | K5: DS146_CommissionAmount_Validity_prf | O5: Pass
A6: Accounting | B6: Pass | C6: KDE00571 | D6: ค่าบำเหน็จ | E6: Commission | F6: sales | G6: salesbenefit_pg | H6: bank_benefit_detail | I6: amount_commission | J6: Validity | K6: DS1165_CommissionAmount_Validity_prf | O6: Pass
A7: Accounting | B7: Pass | C7: KDE00572 | D7: ค่าพาหนะ | E7: Renewal Year Commission | F7: sales | G7: salesbenefit_pg | H7: bank_benefit_detail | I7: amount_renew_commission | J7: Validity | K7: DS1166_RenewalYearCommissionAmount_Validity_prf | O7: Pass
A8: Accounting | B8: Pass | C8: KDE00574 | D8: ค่าจัดงานภาค | E8: District Overriding | F8: sales | G8: salesbenefit_pg | H8: bank_benefit_detail | I8: amount_district_ov | J8: Validity | K8: DS1168_DistrictOverridingAmount_Validity_prf | O8: Pass
A9: Accounting | B9: Pass | C9: KDE00576 | D9: ค่าจัดงานหน่วย | E9: Unit Overriding | F9: sales | G9: salesbenefit_pg | H9: bank_benefit_detail | I9: amount_unit_ov | J9: Validity | K9: DS1170_UnitOverridingAmount_Validity_prf | O9: Pass
A10: Accounting | B10: Pass | C10: KDE00578 | D10: ค่าแยกทีมงานภาค | E10: District Spin Off | F10: sales | G10: salesbenefit_pg | H10: bank_benefit_detail | I10: amount_district_so | J10: Validity | K10: DS1171_DistrictSpinOffAmount_Validity_prf | O10: Pass
A11: Accounting | B11: Pass | C11: KDE00579 | D11: ค่าแยกทีมงานศูนย์ | E11: Division Spin Off | F11: sales | G11: salesbenefit_pg | H11: bank_benefit_detail | I11: amount_division_so | J11: Validity | K11: DS1172_DivisionSpinOffAmount_Validity_prf | O11: Pass
A12: Accounting | B12: Pass | C12: KDE00580 | D12: ค่าแยกทีมงานหน่วย | E12: Unit Spin Off | F12: sales | G12: salesbenefit_pg | H12: bank_benefit_detail | I12: amount_unit_so | J12: Validity | K12: DS1173_UnitSpinOffAmount_Validity_prf | O12: Pass
A13: Accounting | B13: Pass | C13: KDE00581 | D13: ค่าบริหารเป้าหมายภาค | E13: District Target | F13: sales | G13: salesbenefit_pg | H13: bank_benefit_detail | I13: amount_district_target | J13: Validity | K13: DS1174_DistrictTargetAmount_Validity_prf | O13: Pass
A14: Accounting | B14: Pass | C14: KDE00661 | D14: เลขที่บัญชีธนาคารของตัวแทนในการจ่ายเงิน (payment) - Sales benefit | E14: Bank account number | F14: sales | G14: salesbenefit_pg | H14: master_account_agent | I14: account_no | J14: Completeness | K14: DS709_BankAccountNumber_Completeness_prf | O14: Pass
A15: Accounting | B15: Pass | C15: KDE00661 | D15: เลขที่บัญชีธนาคารของตัวแทนในการจ่ายเงิน (payment) - Sales benefit | E15: Bank account number | F15: sales | G15: salesbenefit_pg | H15: master_account_agent | I15: account_no | J15: Validity | K15: DS709_BankAccountNumber_Validity_prf | O15: Pass
A16: Claims | B16: Cannot be measured | C16: KDE00122 | D16: เลขเรื่องสินไหมประกันชีวิตรายบุคคล | E16: Individual Claim Number | F16: claim | G16: cclaim | H16: claim | I16: orderno,sectioncode | J16: Completeness
A17: Claims | B17: Cannot be measured | C17: KDE00122 | D17: เลขเรื่องสินไหมประกันชีวิตรายบุคคล | E17: Individual Claim Number | F17: claim | G17: cclaim | H17: claim | I17: orderno,sectioncode | J17: Validity
A18: Claims | B18: Cannot be measured | C18: KDE00122 | D18: เลขเรื่องสินไหมประกันชีวิตรายบุคคล | E18: Individual Claim Number | F18: claim | G18: cclaim | H18: eclm | I18: orderno,sectioncode | J18: Validity
A19: Claims | B19: Cannot be measured | C19: KDE00122 | D19: เลขเรื่องสินไหมประกันชีวิตรายบุคคล | E19: Individual Claim Number | F19: claim | G19: cclaim | H19: excinsur | I19: orderno,sectioncode | J19: Validity
A20: Claims | B20: Cannot be measured | C20: KDE00122 | D20: เลขเรื่องสินไหมประกันชีวิตรายบุคคล | E20: Individual Claim Number | F20: claim | G20: cmortgage | H20: mgclaim | I20: orderno,sectioncode | J20: Validity
A21: Claims | B21: Cannot be measured | C21: KDE00122 | D21: เลขเรื่องสินไหมประกันชีวิตรายบุคคล | E21: Individual Claim Number | F21: claim | G21: cmortgage | H21: mgfinorder | I21: orderNo,sectionCode | J21: Validity
A22: Claims | B22: Cannot be measured | C22: KDE00123 | D22: เลขที่สินไหมสำหรับลูกค้าประกันกลุ่ม | E22: Group Claim Number | F22: policy | G22: cbaac | H22: mclmtrn907 | I22: claimNo | J22: Completeness | K22: DS402_GroupClaimNumber_Completeness_prf | O22: No Data Found
A23: Claims | B23: Cannot be measured | C23: KDE00134 | D23: จำนวนเงินที่จ่ายสินไหม | E23: Claim Paid amount | F23: claim | G23: cclaim | H23: dth | I23: payLifeSum,payRiderSum | J23: Completeness
A24: Claims | B24: Cannot be measured | C24: KDE00134 | D24: จำนวนเงินที่จ่ายสินไหม | E24: Claim Paid amount | F24: policy | G24: mortgage | H24: cert | I24: amount1 | J24: Validity
A25: Claims | B25: Cannot be measured | C25: KDE00134 | D25: จำนวนเงินที่จ่ายสินไหม | E25: Claim Paid amount | F25: claim | G25: cclaim | H25: dth | I25: payLifeSum,payRiderSum | J25: Validity
A26: Claims | B26: Cannot be measured | C26: KDE00138 | D26: วันที่เกิดเหตุ | E26: occurred date | F26: claim | G26: cclaim | H26: dth | I26: accidentdate | J26: Validity
A27: Claims | B27: Cannot be measured | C27: KDE00138 | D27: วันที่เกิดเหตุ | E27: occurred date | F27: claim | G27: cclaim | H27: iacm | I27: accidentdate | J27: Validity
A28: Claims | B28: Cannot be measured | C28: KDE00138 | D28: วันที่เกิดเหตุ | E28: occurred date | F28: mbl_db | G28: dbo | H28: after_eclaim | I28: admitdate | J28: Validity
A29: Claims | B29: Cannot be measured | C29: KDE00138 | D29: วันที่เกิดเหตุ | E29: occurred date | F29: policy | G29: mortgage | H29: cert | I29: deaddate | J29: Validity
A30: Claims | B30: Cannot be measured | C30: KDE00139 | D30: วันที่เข้ารับการรักษา | E30: Admission date | F30: claim | G30: cclaim | H30: mstwebclaim | I30: admitdate | J30: Completeness
A31: Claims | B31: Cannot be measured | C31: KDE00139 | D31: วันที่เข้ารับการรักษา | E31: Admission date | F31: group_life | G31: glife | H31: hclaim | I31: st_healdate | J31: Completeness
A32: Claims | B32: Cannot be measured | C32: KDE00139 | D32: วันที่เข้ารับการรักษา | E32: Admission date | F32: claim | G32: cclaim | H32: mstwebclaim | I32: admitdate | J32: Validity
A33: Claims | B33: Cannot be measured | C33: KDE00141 | D33: วันที่อนุมัติสินไหม | E33: Claim Approved date | F33: claim | G33: cmortgage | H33: mgfinorder | I33: claimOkDate | J33: Completeness | K33: DS74_ClaimApprovalDate_Completeness_prf | O33: No Data Found
A34: Claims | B34: Cannot be measured | C34: KDE00142 | D34: วันเดือนปีที่รับเอกสารเคลม | E34: Receive Document Date | F34: group_life | G34: glife | H34: claim | I34: recvdate | J34: Validity
A35: Claims | B35: Cannot be measured | C35: KDE00143 | D35: เลขที่รับเรื่องในการเรียกร้องสินไหมสำหรับลูกค้าประกันกลุ่ม | E35: Receive CLaim Number | F35: policy | G35: cbaac | H35: mclmrcv907 | I35: receiveNo | J35: Completeness
A36: Claims | B36: Invalid Data | C36: KDE00125 | D36: เหตุผลที่ปฏิเสธการจ่ายสินไหม | E36: Reject reason | F36: group_life | G36: glife | H36: rejclaim | I36: reject_cause | J36: Completeness | K36: DS300_ClaimRejectReason_Completeness_prf | L36: Completeness | M36: Missing required fields | N36: 99.95712 | O36: Fail - Invalid Data
A37: Claims | B37: Invalid Data | C37: KDE00133 | D37: ค่ารักษาพยาบาลตามใบเสร็จ | E37: Incurred amount | F37: group_life | G37: glife | H37: hclaimrcv | I37: amount | J37: Validity | K37: DS306_IncurredAmount_Validity_prf | L37: Validity | M37: Out‑of‑range numerical values | N37: 99.999962 | O37: Fail - Invalid Data
A38: Claims | B38: Invalid Data | C38: KDE00138 | D38: วันที่เกิดเหตุ | E38: occurred date | F38: claim | G38: cclaim | H38: mstwebclaim | I38: accidentdate | J38: Validity | K38: DS70_AccidentOccurredDate_Validity_prf | L38: Validity | M38: Invalid data format | N38: 99.952532 | O38: Fail - Invalid Data
A39: Claims | B39: Invalid Data | C39: KDE00138 | D39: วันที่เกิดเหตุ | E39: occurred date | F39: claim | G39: cclaim | H39: oacm | I39: accidentdate | J39: Validity | K39: DS71_AccidentOccurredDate_Validity_prf | L39: Validity | M39: Invalid data format | N39: 99.998309 | O39: Fail - Invalid Data
A40: Claims | B40: Invalid Data | C40: KDE00139 | D40: วันที่เข้ารับการรักษา | E40: Admission date | F40: group_life | G40: glife | H40: hclaim | I40: st_healdate | J40: Validity | K40: DS308_AdmissionDate_Validity_prf | L40: Validity | M40: Invalid data format | N40: 99.999709 | O40: Fail - Invalid Data
A41: Claims | B41: Invalid Data | C41: KDE00140 | D41: วันเดือนปีที่จ่ายเงินสินไหม | E41: Payment Date | F41: group_life | G41: glife | H41: claim | I41: paydate | J41: Completeness | K41: DS309_ClaimPaymentDate_Completeness_prf | L41: Completeness | M41: Missing required fields | N41: 99.870097 | O41: Fail - Invalid Data
A42: Claims | B42: Invalid Data | C42: KDE00140 | D42: วันเดือนปีที่จ่ายเงินสินไหม | E42: Payment Date | F42: group_life | G42: glife | H42: hclaim | I42: paydate | J42: Completeness | K42: DS310_ClaimPaymentDate_Completeness_prf | L42: Completeness | M42: Missing required fields | N42: 99.999977 | O42: Fail - Invalid Data
A43: Claims | B43: Invalid Data | C43: KDE00140 | D43: วันเดือนปีที่จ่ายเงินสินไหม | E43: Payment Date | F43: group_life | G43: glife | H43: medclaim | I43: paydate | J43: Completeness | K43: DS311_ClaimPaymentDate_Completeness_prf | L43: Completeness | M43: Missing required fields | N43: 99.976534 | O43: Fail - Invalid Data
A44: Claims | B44: Invalid Data | C44: KDE00140 | D44: วันเดือนปีที่จ่ายเงินสินไหม | E44: Payment Date | F44: group_life | G44: glife | H44: hclaim | I44: paydate | J44: Validity | K44: DS310_ClaimPaymentDate_Validity_prf | L44: Validity | M44: Invalid data format | N44: 99.99956 | O44: Fail - Invalid Data
A45: Claims | B45: Invalid Data | C45: KDE00140 | D45: วันเดือนปีที่จ่ายเงินสินไหม | E45: Payment Date | F45: group_life | G45: glife | H45: medclaim | I45: paydate | J45: Validity | K45: DS311_ClaimPaymentDate_Validity_prf | L45: Validity | M45: Invalid data format | N45: 99.99949 | O45: Fail - Invalid Data
A46: Claims | B46: Invalid Data | C46: KDE00142 | D46: วันเดือนปีที่รับเอกสารเคลม | E46: Receive Document Date | F46: group_life | G46: glife | H46: hclaim | I46: recvdate | J46: Completeness | K46: DS313_ClaimReceivedDate_Completeness_prf | L46: Completeness | M46: Missing required fields | N46: 99.999664 | O46: Fail - Invalid Data
A47: Claims | B47: Invalid Data | C47: KDE00142 | D47: วันเดือนปีที่รับเอกสารเคลม | E47: Receive Document Date | F47: group_life | G47: glife | H47: hclaim | I47: recvdate | J47: Validity | K47: DS313_ClaimReceivedDate_Validity_prf | L47: Validity | M47: Invalid data format | N47: 99.997851 | O47: Fail - Invalid Data
A48: Claims | B48: Invalid Data | C48: KDE00142 | D48: วันเดือนปีที่รับเอกสารเคลม | E48: Receive Document Date | F48: group_life | G48: glife | H48: medclaim | I48: recvdate | J48: Validity | K48: DS314_ClaimReceivedDate_Validity_prf | L48: Validity | M48: Invalid data format | N48: 99.99852 | O48: Fail - Invalid Data
A49: Claims | B49: Pass | C49: KDE00128 | D49: ช่องการเรียกร้องสินไหม | E49: channel of summit claim | F49: claim | G49: claimonline | H49: registeronline | I49: systemtype | J49: Completeness | K49: DS67_ClaimSubmitChannelCode_Completeness_prf | O49: Pass
A50: Claims | B50: Pass | C50: KDE00128 | D50: ช่องการเรียกร้องสินไหม | E50: channel of summit claim | F50: claim | G50: claimonline | H50: registeronline | I50: systemtype | J50: Integrity | K50: DS67_ClaimSubmitChannelCode_Integrity_prf | O50: Pass
A51: Claims | B51: Pass | C51: KDE00132 | D51: ประเภทผลประโยชน์การจ่ายสินไหม | E51: Benefit Type of paid | F51: group_life | G51: glife | H51: claimrcv | I51: claim_type | J51: Integrity | K51: DS303_BenefitTypeOfPaid_Integrity_prf | O51: Pass
A52: Claims | B52: Pass | C52: KDE00132 | D52: ประเภทผลประโยชน์การจ่ายสินไหม | E52: Benefit Type of paid | F52: group_life | G52: glife | H52: hclaimrcv | I52: claim_type | J52: Integrity | K52: DS304_BenefitTypeOfPaid_Integrity_prf | O52: Pass
A53: Claims | B53: Pass | C53: KDE00133 | D53: ค่ารักษาพยาบาลตามใบเสร็จ | E53: Incurred amount | F53: group_life | G53: glife | H53: hclaimrcv | I53: amount | J53: Completeness | K53: DS306_IncurredAmount_Completeness_prf | O53: Pass
A54: Claims | B54: Pass | C54: KDE00138 | D54: วันที่เกิดเหตุ | E54: occurred date | F54: claim | G54: cclaim | H54: dth | I54: accidentdate | J54: Completeness | K54: DS68_AccidentOccurredDate_Completeness_prf | O54: Pass
A55: Claims | B55: Pass | C55: KDE00138 | D55: วันที่เกิดเหตุ | E55: occurred date | F55: claim | G55: cclaim | H55: iacm | I55: accidentdate | J55: Completeness | K55: DS69_AccidentOccurredDate_Completeness_prf | O55: Pass
A56: Claims | B56: Pass | C56: KDE00138 | D56: วันที่เกิดเหตุ | E56: occurred date | F56: claim | G56: cclaim | H56: mstwebclaim | I56: accidentdate | J56: Completeness | K56: DS70_AccidentOccurredDate_Completeness_prf | O56: Pass
A57: Claims | B57: Pass | C57: KDE00138 | D57: วันที่เกิดเหตุ | E57: occurred date | F57: claim | G57: cclaim | H57: oacm | I57: accidentdate | J57: Completeness | K57: DS71_AccidentOccurredDate_Completeness_prf | O57: Pass
A58: Claims | B58: Pass | C58: KDE00138 | D58: วันที่เกิดเหตุ | E58: occurred date | F58: mbl_db | G58: dbo | H58: after_eclaim | I58: admitdate | J58: Completeness | K58: DS346_AccidentOccurredDate_Completeness_prf | O58: Pass
A59: Claims | B59: Pass | C59: KDE00140 | D59: วันเดือนปีที่จ่ายเงินสินไหม | E59: Payment Date | F59: group_life | G59: glife | H59: claim | I59: paydate | J59: Validity | K59: DS309_ClaimPaymentDate_Validity_prf | O59: Pass
A60: Claims | B60: Pass | C60: KDE00141 | D60: วันที่อนุมัติสินไหม | E60: Claim Approved date | F60: claim | G60: claimbook | H60: claimpayment | I60: claimokdate | J60: Completeness | K60: DS73_ClaimApprovalDate_Completeness_prf | O60: Pass
... A76: Customer | B76: Cannot be measured | C76: KDE00001 | D76: หมายเลขโทรศัพท์มือถือของผู้เอาประกัน | E76: Policyholder Mobile Phone Number | F76: underwrite | G76: cunderwrite | H76: phone | I76: phoneno | J76: Validity | K76: DS797_MobilePhoneNumber_Validity_prf | O76: No Data Found
A77: Customer | B77: Cannot be measured | C77: KDE00002 | D77: หมายเลขโทรศัพท์สถานทีทำงานของผู้เอาประกัน | E77: Policyholder Work address_Phone No | F77: tlprompt | G77: public | H77: address | I77: telno | J77: Validity
A78: Customer | B78: Cannot be measured | C78: KDE00002 | D78: หมายเลขโทรศัพท์สถานทีทำงานของผู้เอาประกัน | E78: Policyholder Work address_Phone No | F78: tlprompt | G78: public | H78: address | I78: mobileno | J78: Validity
A79: Customer | B79: Cannot be measured | C79: KDE00005 | D79: เลขที่บัตรประชาชนของผู้รับมอบสิทธิ | E79: Assignee Identity Number | F79: pos | G79: srvservice | H79: delegatemast | I79: referenceid | J79: Completeness
A80: Customer | B80: Cannot be measured | C80: KDE00005 | D80: เลขประจำตัวประชาชนของผู้ปกครอง คบ. | E80: KB's Identification Number | F80: tlprompt | G80: public | H80: kb | I80: identifyid | J80: Completeness
A81: Customer | B81: Cannot be measured | C81: KDE00005 | D81: เลขประจำตัวประชาชนของผู้เอาประกันภัย | E81: Policyholder Identification Number | F81: claim | G81: cclaim | H81: eclaimform | I81: citizenid | J81: Completeness
A82: Customer | B82: Cannot be measured | C82: KDE00005 | D82: เลขประจำตัวประชาชนของผู้เอาประกันภัย | E82: Policyholder Identification Number | F82: common_db | G82: dbo | H82: tb_prospect | I82: citizen_id | J82: Completeness
A83: Customer | B83: Cannot be measured | C83: KDE00005 | D83: เลขประจำตัวประชาชนของผู้เอาประกันภัย | E83: Policyholder Identification Number | F83: customer | G83: party | H83: party | I83: govt_id | J83: Completeness
A84: Customer | B84: Cannot be measured | C84: KDE00005 | D84: เลขประจำตัวประชาชนของผู้เอาประกันภัย | E84: Policyholder Identification Number | F84: dfl | G84: dfl | H84: mcaapplications | I84: identifyid | J84: Completeness
A85: Customer | B85: Cannot be measured | C85: KDE00005 | D85: เลขประจำตัวประชาชนของผู้เอาประกันภัย | E85: Policyholder Identification Number | F85: group_life | G85: glife | H85: citizenid | I85: referenceid | J85: Completeness
A86: Customer | B86: Cannot be measured | C86: KDE00005 | D86: เลขประจำตัวประชาชนของผู้เอาประกันภัย | E86: Policyholder Identification Number | F86: policy | G86: mstperson | H86: person | I86: referenceid | J86: Completeness
A87: Customer | B87: Cannot be measured | C87: KDE00005 | D87: เลขประจำตัวประชาชนของผู้เอาประกันภัย | E87: Policyholder Identification Number | F87: policy | G87: universal | H87: partialwithdraw | I87: referenceid | J87: Completeness
A88: Customer | B88: Cannot be measured | C88: KDE00005 | D88: เลขประจำตัวประชาชนของผู้เอาประกันภัย | E88: Policyholder Identification Number | F88: pos | G88: srvservice | H88: dvtran | I88: referenceid | J88: Completeness
... A113: Customer | B113: Cannot be measured | C113: KDE00007 | D113: เลขประจำตัวผู้เสียภาษีอากร | E113: Taxpayer identification number | F113: group_life | G113: glife | H113: engcompany | I113: regisnumber | J113: Completeness
A114: Customer | B114: Cannot be measured | C114: KDE00007 | D114: เลขประจำตัวผู้เสียภาษีอากร | E114: Taxpayer identification number | F114: tlprompt | G114: public | H114: payment | I114: personidtax | J114: Completeness | K114: DS720_TaxPayerIDNumber_Completeness_prf | L114: Completeness | M114: Missing required fields | N114: 0.31432315 | O114: Fail - Invalid Rules
A115: Customer | B115: Cannot be measured | C115: KDE00007 | D115: เลขประจำตัวผู้เสียภาษีอากร | E115: Taxpayer identification number | F115: group_life | G115: glife | H115: engcompany | I115: regisnumber | J115: Validity
A116: Customer | B116: Cannot be measured | C116: KDE00007 | D116: เลขประจำตัวผู้เสียภาษีอากร | E116: Taxpayer identification number | F116: policy | G116: cbranch | H116: nbnewappfield | I116: taxid | J116: Validity
A117: Customer | B117: Cannot be measured | C117: KDE00007 | D117: เลขประจำตัวผู้เสียภาษีอากร | E117: Taxpayer identification number | F117: pos | G117: newservice | H117: consent | I117: referenceid | J117: Validity
A118: Customer | B118: Cannot be measured | C118: KDE00007 | D118: เลขประจำตัวผู้เสียภาษีอากร | E118: Taxpayer identification number | F118: tlprompt | G118: public | H118: payment | I118: personidtax | J118: Validity
A119: Customer | B119: Cannot be measured | C119: KDE00008 | D119: เลขที่หนังสือเดินทางของผู้ขอเอาประกัน | E119: Policyholder Passport No. | F119: group_life | G119: glife | H119: passportid | I119: passportid | J119: Completeness
A120: Customer | B120: Cannot be measured | C120: KDE00008 | D120: เลขที่หนังสือเดินทางของผู้ขอเอาประกัน | E120: Policyholder Passport No. | F120: tlprompt | G120: public | H120: prospect | I120: passport | J120: Completeness | K120: DS721_PassportNumber_Completeness_prf | L120: Completeness | M120: Missing required fields | N120: 0.56189386 | O120: Fail - Invalid Rules
A121: Customer | B121: Cannot be measured | C121: KDE00014 | D121: คำนำหน้าชื่อของผู้ขอเอาประกัน | E121: Applicant's Title | F121: policy | G121: mstperson | H121: name | I121: prename | J121: Integrity
A122: Customer | B122: Cannot be measured | C122: KDE00016 | D122: ชื่อ-นามสกุล ของผู้ขอเอาประกัน | E122: Applicant Name-Surname | F122: group_life | G122: glife | H122: g | I122: fname,lname | J122: Completeness
A123: Customer | B123: Cannot be measured | C123: KDE00016 | D123: ชื่อ-นามสกุล ของผู้เอาประกัน | E123: Policyholder Name-Surname | F123: dm_db | G123: dbo | H123: l_serv_master | I123: first_name,last_name | J123: Completeness | K123: ENT904_PersonName_Completeness_prf | O123: No Data Found
A124: Customer | B124: Cannot be measured | C124: KDE00016 | D124: ชื่อ-นามสกุล ของผู้เอาประกัน | E124: Policyholder Name-Surname | F124: dm_db | G124: dbo | H124: tb_dmmast | I124: firstname,lastname | J124: Completeness | K124: ENT1159_PersonName_Completeness_prf | O124: No Data Found
A125: Customer | B125: Cannot be measured | C125: KDE00016 | D125: ชื่อ-นามสกุล ของผู้เอาประกัน | E125: Policyholder Name-Surname | F125: underwrite | G125: cunderwrite | H125: dmapplication | I125: firstname,lastname | J125: Completeness
A126: Customer | B126: Cannot be measured | C126: KDE00016 | D126: ชื่อ-นามสกุล ของผู้ขอเอาประกัน | E126: Applicant Name-Surname | F126: customer | G126: common_refund | H126: customers_refund | I126: firstname,lastname | J126: Validity
A127: Customer | B127: Cannot be measured | C127: KDE00016 | D127: ชื่อ-นามสกุล ของผู้ขอเอาประกัน | E127: Applicant Name-Surname | F127: customer | G127: party | H127: person | I127: fname_th,lname_th | J127: Validity
A128: Customer | B128: Cannot be measured | C128: KDE00016 | D128: ชื่อ-นามสกุล ของผู้ขอเอาประกัน | E128: Applicant Name-Surname | F128: dfl | G128: dfl | H128: mcaapplications | I128: name,lastname | J128: Validity
A129: Customer | B129: Cannot be measured | C129: KDE00016 | D129: ชื่อ-นามสกุล ของผู้ขอเอาประกัน | E129: Applicant Name-Surname | F129: finance_acc | G129: accountbranch | H129: paymentmst | I129: firstname,lastname | J129: Validity
A130: Customer | B130: Cannot be measured | C130: KDE00016 | D130: ชื่อ-นามสกุล ของผู้ขอเอาประกัน | E130: Applicant Name-Surname | F130: group_life | G130: glife | H130: g | I130: fname,lname | J130: Validity
A131: Customer | B131: Cannot be measured | C131: KDE00016 | D131: ชื่อ-นามสกุล ของผู้ขอเอาประกัน | E131: Applicant Name-Surname | F131: policy | G131: mstperson | H131: name | I131: firstname,lastname | J131: Validity
A132: Customer | B132: Cannot be measured | C132: KDE00016 | D132: ชื่อ-นามสกุล ของผู้ขอเอาประกัน | E132: Applicant Name-Surname | F132: tlprompt | G132: public | H132: mcaapplications | I132: name,lastname | J132: Validity
A133: Customer | B133: Cannot be measured | C133: KDE00016 | D133: ชื่อ-นามสกุล ของผู้ขอเอาประกัน | E133: Applicant Name-Surname | F133: underwrite | G133: cunderwrite | H133: appln | I133: firstname,lastname | J133: Validity
A134: Customer | B134: Cannot be measured | C134: KDE00016 | D134: ชื่อ-นามสกุล ของผู้เอาประกัน | E134: Policyholder Name-Surname | F134: claim | G134: cclaim | H134: namindi | I134: firstname,lastname | J134: Validity
A135: Customer | B135: Cannot be measured | C135: KDE00016 | D135: ชื่อ-นามสกุล ของผู้เอาประกัน | E135: Policyholder Name-Surname | F135: claim | G135: cclaim | H135: namordo | I135: firstname,lastname | J135: Validity
A136: Customer | B136: Cannot be measured | C136: KDE00016 | D136: ชื่อ-นามสกุล ของผู้เอาประกัน | E136: Policyholder Name-Surname | F136: claim | G136: claimback | H136: extendage | I136: firstname,lastname | J136: Validity
... A140: Customer | B140: Cannot be measured | C140: KDE00016 | D140: ชื่อ-นามสกุล ของผู้มอบอำนาจ | E140: Authorized Person Name-Surname | F140: group_life | G140: glife | H140: policy_peopleref | I140: tfirstname,tlastname | J140: Validity
A141: Customer | B141: Cannot be measured | C141: KDE00016 | D141: ชื่อ-นามสกุล ของผู้มอบอำนาจ | E141: Authorized Person Name-Surname | F141: group_life | G141: glife | H141: policy_peopleref | I141: tfirstname,tlastname | J141: Completeness | K141: ENT293_PersonName_Completeness_prf | L141: Completeness | M141: Missing required fields | N141: 46.003447 | O141: Fail - Further Investigation
A142: Customer | B142: Cannot be measured | C142: KDE00016 | D142: ชื่อ-นามสกุล ของผู้เอาประกัน | E142: Policyholder Name-Surname | F142: claim | G142: cclaim | H142: eclaimform | I142: firstname,lastname | J142: Validity
...

Sheet Sheet3
A3: Status May | B3: Count of KDE | C3: countIF | E3: Status May | F3: KDE | G3: Count of KDE
A4: Cannot be measured | B4: 215 | C4: 75 | E4: Cannot be measured | F4: KDE00001 | G4: 1
A5: Invalid Data | B5: 163 | C5: 75 | F5: KDE00005 | G5: 34
A6: Pass | B6: 491 | C6: 137 | F6: KDE00007 | G6: 6 | J6: Status Test | K6: CountIf of KDE
A7: (blank) | B7: 1 | C7: 1 | F7: KDE00008 | G7: 1 | J7: FIXED | K7: 12
A8: Grand Total | B8: 870 | F8: KDE00014 | G8: 1 | J8: NOT PASS | K8: 39
F9: KDE00016 | G9: 21 | J9: PASS | K9: 172
C10: =SUM(C4:C9) -> 288 | F10: KDE00025 | G10: 1 | J10: Pass with Condition | K10: 19
F11: KDE00058 | G11: 1 | J11: Ready | K11: 5
F12: KDE00063 | G12: 2 | J12: (blank) | K12: 1
F13: KDE00093 | G13: 1 | J13: Grand Total | K13: =SUM(K7:K12) -> 248
F14: KDE00104 | G14: 1
F15: KDE00121 | G15: 2
F16: KDE00122 | G16: 6
F17: KDE00123 | G17: 1
F18: KDE00134 | G18: 3
F19: KDE00136 | G19: 1
F20: KDE00138 | G20: 4
F21: KDE00139 | G21: 3
F22: KDE00141 | G22: 1
F23: KDE00142 | G23: 1
F24: KDE00143 | G24: 1
F25: KDE00152 | G25: 1
... F78: KDE00802 | G78: 2
E79: Cannot be measured Total | G79: 215
E80: Invalid Data | G80: 163
E81: Pass | G81: 491
E82: (blank) | F82: KDE00514 | G82: 1
F83: (blank)
E84: (blank) Total | G84: 1
E85: Grand Total | G85: 870

Sheet xxx
A1: Data Domain | B1: Status March | C1: Status May | D1: Status Jun | E1: xxx | F1: KDE | G1: Key Data Element (Thai) | H1: Key Data Element (English) | I1: Src Database | J1: Src Schema | K1: Src Table | L1: Src Column | M1: Business DQ Rules | N1: Prod_ProfilingResult | O1: key | P1: ValidPercentage as of 20260601 | R1: Prod_ThresholdStatus Jun | S1: Status | T1: Jobname | U1: Status Test | V1: RootCause | W1: Ticket
A2: Accounting | B2: Cannot be measured | C2: Cannot be measured | D2: Cannot be measured | F2: KDE00571 | G2: ค่าบำเหน็จ | H2: Commission | I2: sales | J2: salesbenefit_pg | K2: submit_ctrl_detail | L2: amount_pension | M2: Validity | O2: KDE00571sales.salesbenefit_pg.submit_ctrl_detail.amount_pensionValidityAccounting | P2: =VLOOKUP(O2,Sheet6!K:L,2,FALSE) -> #N/A | S2: Cannot be measured | U2: =VLOOKUP(O2,Sheet1!W:X,2,FALSE) -> NOT PASS | V2: Check data in partioned tables: cunderwrite.phoneYYMM
A3: Accounting | B3: Cannot be measured | C3: Cannot be measured | D3: Cannot be measured | F3: KDE00572 | G3: ค่าพาหนะ | H3: Renewal Year Commission | I3: sales | J3: salesbenefit_pg | K3: submit_ctrl_detail | L3: amount_vehicle_fee | M3: Validity | O3: KDE00572sales.salesbenefit_pg.submit_ctrl_detail.amount_vehicle_feeValidityAccounting | P3: =VLOOKUP(O3,Sheet6!K:L,2,FALSE) -> #N/A | S3: Cannot be measured | U3: =VLOOKUP(O3,Sheet1!W:X,2,FALSE) -> NOT PASS
A4: Accounting | B4: Pass | C4: Pass | D4: Pass | F4: KDE00383 | G4: อากรสแตมป์ | H4: Revenue Stamp | I4: pos | J4: srvservice | K4: lnrqst | L4: duty | M4: Validity | O4: KDE00383pos.srvservice.lnrqst.dutyValidityAccounting | P4: =VLOOKUP(O4,Sheet6!K:L,2,FALSE) -> 100 | Q4: Pass | R4: Pass | U4: =VLOOKUP(O4,Sheet1!W:X,2,FALSE) -> PASS
A5: Accounting | B5: Pass | C5: Pass | D5: Pass | F5: KDE00571 | G5: ค่าบำเหน็จ | H5: Commission | I5: corebiz | J5: ovdebt | K5: debttrndet | L5: benefit | M5: Validity | O5: KDE00571corebiz.ovdebt.debttrndet.benefitValidityAccounting | P5: =VLOOKUP(O5,Sheet6!K:L,2,FALSE) -> 100 | R5: Pass | U5: =VLOOKUP(O5,Sheet1!W:X,2,FALSE) -> PASS
A6: Accounting | B6: Pass | C6: Pass | D6: Pass | F6: KDE00571 | G6: ค่าบำเหน็จ | H6: Commission | I6: sales | J6: salesbenefit_pg | K6: bank_benefit_detail | L6: amount_commission | M6: Validity | O6: KDE00571sales.salesbenefit_pg.bank_benefit_detail.amount_commissionValidityAccounting | P6: =VLOOKUP(O6,Sheet6!K:L,2,FALSE) -> 100 | R6: Pass | U6: =VLOOKUP(O6,Sheet1!W:X,2,FALSE) -> PASS
A7: Accounting | B7: Pass | C7: Pass | D7: Pass | F7: KDE00572 | G7: ค่าพาหนะ | H7: Renewal Year Commission | I7: sales | J7: salesbenefit_pg | K7: bank_benefit_detail | L7: amount_renew_commission | M7: Validity | O7: KDE00572sales.salesbenefit_pg.bank_benefit_detail.amount_renew_commissionValidityAccounting | P7: =VLOOKUP(O7,Sheet6!K:L,2,FALSE) -> 100 | R7: Pass | U7: =VLOOKUP(O7,Sheet1!W:X,2,FALSE) -> PASS
A8: Accounting | B8: Pass | C8: Pass | D8: Pass | F8: KDE00574 | G8: ค่าจัดงานภาค | H8: District Overriding | I8: sales | J8: salesbenefit_pg | K8: bank_benefit_detail | L8: amount_district_ov | M8: Validity | O8: KDE00574sales.salesbenefit_pg.bank_benefit_detail.amount_district_ovValidityAccounting | P8: =VLOOKUP(O8,Sheet6!K:L,2,FALSE) -> 100 | R8: Pass | U8: =VLOOKUP(O8,Sheet1!W:X,2,FALSE) -> PASS
A9: Accounting | B9: Pass | C9: Pass | D9: Pass | F9: KDE00576 | G9: ค่าจัดงานหน่วย | H9: Unit Overriding | I9: sales | J9: salesbenefit_pg | K9: bank_benefit_detail | L9: amount_unit_ov | M9: Validity | O9: KDE00576sales.salesbenefit_pg.bank_benefit_detail.amount_unit_ovValidityAccounting | P9: =VLOOKUP(O9,Sheet6!K:L,2,FALSE) -> 100 | R9: Pass | U9: =VLOOKUP(O9,Sheet1!W:X,2,FALSE) -> PASS
A10: Accounting | B10: Pass | C10: Pass | D10: Pass | F10: KDE00578 | G10: ค่าแยกทีมงานภาค | H10: District Spin Off | I10: sales | J10: salesbenefit_pg | K10: bank_benefit_detail | L10: amount_district_so | M10: Validity | O10: KDE00578sales.salesbenefit_pg.bank_benefit_detail.amount_district_soValidityAccounting | P10: =VLOOKUP(O10,Sheet6!K:L,2,FALSE) -> 100 | R10: Pass | U10: =VLOOKUP(O10,Sheet1!W:X,2,FALSE) -> PASS
A11: Accounting | B11: Pass | C11: Pass | D11: Pass | F11: KDE00579 | G11: ค่าแยกทีมงานศูนย์ | H11: Division Spin Off | I11: sales | J11: salesbenefit_pg | K11: bank_benefit_detail | L11: amount_division_so | M11: Validity | O11: KDE00579sales.salesbenefit_pg.bank_benefit_detail.amount_division_soValidityAccounting | P11: =VLOOKUP(O11,Sheet6!K:L,2,FALSE) -> 100 | R11: Pass | U11: =VLOOKUP(O11,Sheet1!W:X,2,FALSE) -> PASS
A12: Accounting | B12: Pass | C12: Pass | D12: Pass | F12: KDE00580 | G12: ค่าแยกทีมงานหน่วย | H12: Unit Spin Off | I12: sales | J12: salesbenefit_pg | K12: bank_benefit_detail | L12: amount_unit_so | M12: Validity | O12: KDE00580sales.salesbenefit_pg.bank_benefit_detail.amount_unit_soValidityAccounting | P12: =VLOOKUP(O12,Sheet6!K:L,2,FALSE) -> 100 | R12: Pass | U12: =VLOOKUP(O12,Sheet1!W:X,2,FALSE) -> PASS
A13: Accounting | B13: Pass | C13: Pass | D13: Pass | F13: KDE00581 | G13: ค่าบริหารเป้าหมายภาค | H13: District Target | I13: sales | J13: salesbenefit_pg | K13: bank_benefit_detail | L13: amount_district_target | M13: Validity | O13: KDE00581sales.salesbenefit_pg.bank_benefit_detail.amount_district_targetValidityAccounting | P13: =VLOOKUP(O13,Sheet6!K:L,2,FALSE) -> 100 | R13: Pass | U13: =VLOOKUP(O13,Sheet1!W:X,2,FALSE) -> PASS
A14: Accounting | B14: Pass | C14: Pass | D14: Pass | F14: KDE00661 | G14: เลขที่บัญชีธนาคารของตัวแทนในการจ่ายเงิน (payment) - Sales benefit | H14: Bank account number | I14: sales | J14: salesbenefit_pg | K14: master_account_agent | L14: account_no | M14: Completeness | O14: KDE00661sales.salesbenefit_pg.master_account_agent.account_noCompletenessAccounting | P14: =VLOOKUP(O14,Sheet6!K:L,2,FALSE) -> 100 | R14: Pass | U14: =VLOOKUP(O14,Sheet1!W:X,2,FALSE) -> PASS
A15: Accounting | B15: Pass | C15: Pass | D15: Pass | F15: KDE00661 | G15: เลขที่บัญชีธนาคารของตัวแทนในการจ่ายเงิน (payment) - Sales benefit | H15: Bank account number | I15: sales | J15: salesbenefit_pg | K15: master_account_agent | L15: account_no | M15: Validity | O15: KDE00661sales.salesbenefit_pg.master_account_agent.account_noValidityAccounting | P15: =VLOOKUP(O15,Sheet6!K:L,2,FALSE) -> 100 | R15: Pass | U15: =VLOOKUP(O15,Sheet1!W:X,2,FALSE) -> PASS
A16: Claims | B16: Cannot be measured | C16: Cannot be measured | D16: Cannot be measured | F16: KDE00122 | G16: เลขเรื่องสินไหมประกันชีวิตรายบุคคล | H16: Individual Claim Number | I16: claim | J16: cmortgage | K16: mgclaim | L16: orderno,sectioncode | M16: Validity | O16: KDE00122claim.cmortgage.mgclaim.orderno,sectioncodeValidityClaims | P16: =VLOOKUP(O16,Sheet6!K:L,2,FALSE) -> #N/A | S16: Cannot be measured | U16: =VLOOKUP(O16,Sheet1!W:X,2,FALSE) -> NOT PASS
A17: Claims | B17: Cannot be measured | C17: Cannot be measured | D17: Cannot be measured | F17: KDE00122 | G17: เลขเรื่องสินไหมประกันชีวิตรายบุคคล | H17: Individual Claim Number | I17: claim | J17: cmortgage | K17: mgfinorder | L17: orderNo,sectionCode | M17: Validity | O17: KDE00122claim.cmortgage.mgfinorder.ClaimNumberValidityClaims | P17: =VLOOKUP(O17,Sheet6!K:L,2,FALSE) -> #N/A | S17: Sprint40 | U17: PASS
A18: Claims | B18: Cannot be measured | C18: Cannot be measured | D18: Cannot be measured | F18: KDE00123 | G18: เลขที่สินไหมสำหรับลูกค้าประกันกลุ่ม | H18: Group Claim Number | I18: policy | J18: cbaac | K18: mclmtrn907 | L18: claimNo | M18: Completeness | O18: KDE00123policy.cbaac.mclmtrn907.claimNoCompletenessClaims | P18: =VLOOKUP(O18,Sheet6!K:L,2,FALSE) -> #N/A | S18: Sprint40 | U18: =VLOOKUP(O18,Sheet1!W:X,2,FALSE) -> PASS
A19: Claims | B19: Cannot be measured | C19: Cannot be measured | D19: Cannot be measured | F19: KDE00134 | G19: จำนวนเงินที่จ่ายสินไหม | H19: Claim Paid amount | I19: claim | J19: cclaim | K19: dth | L19: payLifeSum,payRiderSum | M19: Validity | O19: KDE00134claim.cclaim.dth.ClaimPaidAmountValidityClaims | P19: =VLOOKUP(O19,Sheet6!K:L,2,FALSE) -> #N/A | S19: Sprint40 No Result @PROD | U19: PASS
A20: Claims | B20: Cannot be measured | C20: Cannot be measured | D20: Cannot be measured | F20: KDE00138 | G20: วันที่เกิดเหตุ | H20: occurred date | I20: policy | J20: mortgage | K20: cert | L20: deaddate | M20: Validity | O20: KDE00138policy.mortgage.cert.deaddateValidityClaims | P20: =VLOOKUP(O20,Sheet6!K:L,2,FALSE) -> #N/A | S20: No Result @PROD | T20: m_PersonDeadDate_Validity_DS403 | U20: =VLOOKUP(O20,Sheet1!W:X,2,FALSE) -> PASS
A21: Claims | B21: Cannot be measured | C21: Cannot be measured | D21: Cannot be measured | F21: KDE00141 | G21: วันที่อนุมัติสินไหม | H21: Claim Approved date | I21: claim | J21: cmortgage | K21: mgfinorder | L21: claimOkDate | M21: Completeness | O21: KDE00141claim.cmortgage.mgfinorder.claimOkDateCompletenessClaims | P21: =VLOOKUP(O21,Sheet6!K:L,2,FALSE) -> #N/A | S21: Sprint40 | U21: =VLOOKUP(O21,Sheet1!W:X,2,FALSE) -> PASS
A22: Claims | B22: Cannot be measured | C22: Cannot be measured | D22: Cannot be measured | F22: KDE00143 | G22: เลขที่รับเรื่องในการเรียกร้องสินไหมสำหรับลูกค้าประกันกลุ่ม | H22: Receive CLaim Number | I22: policy | J22: cbaac | K22: mclmrcv907 | L22: receiveNo | M22: Completeness | O22: KDE00143policy.cbaac.mclmrcv907.receiveNoCompletenessClaims | P22: =VLOOKUP(O22,Sheet6!K:L,2,FALSE) -> #N/A | S22: Cannot be measured | U22: =VLOOKUP(O22,Sheet1!W:X,2,FALSE) -> NOT PASS
A23: Claims | B23: Cannot be measured | C23: Cannot be measured | D23: Invalid Data | F23: KDE00122 | G23: เลขเรื่องสินไหมประกันชีวิตรายบุคคล | H23: Individual Claim Number | I23: claim | J23: cclaim | K23: claim | L23: orderno,sectioncode | M23: Completeness | N23: DQ Measurement Result - Claims.xlsx | O23: KDE00122claim.cclaim.claim.ClaimNumberCompletenessClaims | P23: =VLOOKUP(O23,Sheet6!K:L,2,FALSE) -> 99.999936 | R23: Fail - Invalid Data | S23: Sprint40 | U23: PASS
A24: Claims | B24: Cannot be measured | C24: Cannot be measured | D24: Invalid Data | F24: KDE00122 | G24: เลขเรื่องสินไหมประกันชีวิตรายบุคคล | H24: Individual Claim Number | I24: claim | J24: cclaim | K24: claim | L24: orderno,sectioncode | M24: Validity | N24: DQ Measurement Result - Claims.xlsx | O24: KDE00122claim.cclaim.claim.ClaimNumberValidityClaims | P24: =VLOOKUP(O24,Sheet6!K:L,2,FALSE) -> 99.999743 | R24: Fail - Invalid Data | S24: Sprint40 | U24: PASS
A25: Claims | B25: Cannot be measured | C25: Cannot be measured | D25: Invalid Data | F25: KDE00122 | G25: เลขเรื่องสินไหมประกันชีวิตรายบุคคล | H25: Individual Claim Number | I25: claim | J25: cclaim | K25: excinsur | L25: orderno,sectioncode | M25: Validity | N25: DQ Measurement Result - Claims.xlsx | O25: KDE00122claim.cclaim.excinsur.ClaimNumberValidityClaims | P25: =VLOOKUP(O25,Sheet6!K:L,2,FALSE) -> 99.993299 | R25: Fail - Invalid Data | S25: Sprint40 | U25: PASS
A26: Claims | B26: Invalid Data | C26: Invalid Data | D26: Invalid Data | F26: KDE00125 | G26: เหตุผลที่ปฏิเสธการจ่ายสินไหม | H26: Reject reason | I26: group_life | J26: glife | K26: rejclaim | L26: reject_cause | M26: Completeness | N26: DQ Measurement Result - Claims.xlsx | O26: KDE00125group_life.glife.rejclaim.reject_causeCompletenessClaims | P26: =VLOOKUP(O26,Sheet6!K:L,2,FALSE) -> 99.957348 | R26: Fail - Invalid Data | S26: Sprint40 | U26: =VLOOKUP(O26,Sheet1!W:X,2,FALSE) -> PASS
A27: Claims | B27: Invalid Data | C27: Invalid Data | D27: Invalid Data | F27: KDE00133 | G27: ค่ารักษาพยาบาลตามใบเสร็จ | H27: Incurred amount | I27: group_life | J27: glife | K27: hclaimrcv | L27: amount | M27: Validity | N27: DQ Measurement Result - Claims.xlsx | O27: KDE00133group_life.glife.hclaimrcv.amountValidityClaims | P27: =VLOOKUP(O27,Sheet6!K:L,2,FALSE) -> 99.999963 | R27: Fail - Invalid Data | S27: Sprint40 | U27: =VLOOKUP(O27,Sheet1!W:X,2,FALSE) -> PASS
A28: Claims | B28: Cannot be measured | C28: Cannot be measured | D28: Invalid Data | F28: KDE00134 | G28: จำนวนเงินที่จ่ายสินไหม | H28: Claim Paid amount | I28: claim | J28: cclaim | K28: dth | L28: payLifeSum,payRiderSum | M28: Completeness | N28: DQ Measurement Result - Claims.xlsx | O28: KDE00134claim.cclaim.dth.ClaimPaidAmountCompletenessClaims | P28: =VLOOKUP(O28,Sheet6!K:L,2,FALSE) -> 99.997295 | R28: Fail - Invalid Data | S28: Sprint40 | U28: PASS
A29: Claims | B29: Cannot be measured | C29: Cannot be measured | D29: Invalid Data | F29: KDE00138 | G29: วันที่เกิดเหตุ | H29: occurred date | I29: claim | J29: cclaim | K29: iacm | L29: accidentdate | M29: Validity | N29: DQ Measurement Result - Claims.xlsx | O29: KDE00138claim.cclaim.iacm.accidentdateValidityClaims | P29: =VLOOKUP(O29,Sheet6!K:L,2,FALSE) -> 99.991083 | R29: Fail - Invalid Data | S29: Sprint40 | U29: =VLOOKUP(O29,Sheet1!W:X,2,FALSE) -> PASS
A30: Claims | B30: Cannot be measured | C30: Cannot be measured | D30: Invalid Data | F30: KDE00138 | G30: วันที่เกิดเหตุ | H30: occurred date | I30: mbl_db | J30: dbo | K30: after_eclaim | L30: admitdate | M30: Validity | N30: DQ Measurement Result - Claims.xlsx | O30: KDE00138mbl_db.dbo.after_eclaim.admitdateValidityClaims | P30: =VLOOKUP(O30,Sheet6!K:L,2,FALSE) -> 99.962999 | R30: Fail - Invalid Data | S30: Sprint40 | U30: =VLOOKUP(O30,Sheet1!W:X,2,FALSE) -> PASS
A31: Claims | B31: Invalid Data | C31: Invalid Data | D31: Invalid Data | F31: KDE00138 | G31: วันที่เกิดเหตุ | H31: occurred date | I31: claim | J31: cclaim | K31: mstwebclaim | L31: accidentdate | M31: Validity | N31: DQ Measurement Result - Claims.xlsx | O31: KDE00138claim.cclaim.mstwebclaim.accidentdateValidityClaims | P31: =VLOOKUP(O31,Sheet6!K:L,2,FALSE) -> 99.954311 | R31: Fail - Invalid Data | S31: Sprint40 | U31: =VLOOKUP(O31,Sheet1!W:X,2,FALSE) -> PASS
A32: Claims | B32: Invalid Data | C32: Invalid Data | D32: Invalid Data | F32: KDE00138 | G32: วันที่เกิดเหตุ | H32: occurred date | I32: claim | J32: cclaim | K32: oacm | L32: accidentdate | M32: Validity | N32: DQ Measurement Result - Claims.xlsx | O32: KDE00138claim.cclaim.oacm.accidentdateValidityClaims | P32: =VLOOKUP(O32,Sheet6!K:L,2,FALSE) -> 99.998286 | R32: Fail - Invalid Data | S32: Sprint40 | U32: =VLOOKUP(O32,Sheet1!W:X,2,FALSE) -> PASS
A33: Claims | B33: Cannot be measured | C33: Cannot be measured | D33: Invalid Data | F33: KDE00139 | G33: วันที่เข้ารับการรักษา | H33: Admission date | I33: claim | J33: cclaim | K33: mstwebclaim | L33: admitdate | M33: Completeness | N33: DQ Measurement Result - Claims.xlsx | O33: KDE00139claim.cclaim.mstwebclaim.admitdateCompletenessClaims | P33: =VLOOKUP(O33,Sheet6!K:L,2,FALSE) -> 92.642859 | R33: Fail - Invalid Data | S33: Sprint40 | U33: =VLOOKUP(O33,Sheet1!W:X,2,FALSE) -> PASS
A34: Claims | B34: Cannot be measured | C34: Cannot be measured | D34: Invalid Data | F34: KDE00139 | G34: วันที่เข้ารับการรักษา | H34: Admission date | I34: group_life | J34: glife | K34: hclaim | L34: st_healdate | M34: Completeness | N34: DQ Measurement Result - Claims.xlsx | O34: KDE00139group_life.glife.hclaim.st_healdateCompletenessClaims | P34: =VLOOKUP(O34,Sheet6!K:L,2,FALSE) -> 99.999278 | R34: Fail - Invalid Data | S34: Sprint40 | U34: =VLOOKUP(O34,Sheet1!W:X,2,FALSE) -> PASS
A35: Claims | B35: Cannot be measured | C35: Cannot be measured | D35: Invalid Data | F35: KDE00139 | G35: วันที่เข้ารับการรักษา | H35: Admission date | I35: claim | J35: cclaim | K35: mstwebclaim | L35: admitdate | M35: Validity | N35: DQ Measurement Result - Claims.xlsx | O35: KDE00139claim.cclaim.mstwebclaim.admitdateValidityClaims | P35: =VLOOKUP(O35,Sheet6!K:L,2,FALSE) -> 99.999199 | R35: Fail - Invalid Data | S35: Sprint40 | U35: =VLOOKUP(O35,Sheet1!W:X,2,FALSE) -> PASS
A36: Claims | B36: Invalid Data | C36: Invalid Data | D36: Invalid Data | F36: KDE00139 | G36: วันที่เข้ารับการรักษา | H36: Admission date | I36: group_life | J36: glife | K36: hclaim | L36: st_healdate | M36: Validity | N36: DQ Measurement Result - Claims.xlsx | O36: KDE00139group_life.glife.hclaim.st_healdateValidityClaims | P36: =VLOOKUP(O36,Sheet6!K:L,2,FALSE) -> 99.999716 | R36: Fail - Invalid Data | S36: Sprint40 | U36: =VLOOKUP(O36,Sheet1!W:X,2,FALSE) -> PASS
A37: Claims | B37: Invalid Data | C37: Invalid Data | D37: Invalid Data | F37: KDE00140 | G37: วันเดือนปีที่จ่ายเงินสินไหม | H37: Payment Date | I37: group_life | J37: glife | K37: claim | L37: paydate | M37: Completeness | N37: DQ Measurement Result - Claims.xlsx | O37: KDE00140group_life.glife.claim.paydateCompletenessClaims | P37: =VLOOKUP(O37,Sheet6!K:L,2,FALSE) -> 99.871195 | R37: Fail - Invalid Data | S37: Sprint40 | U37: =VLOOKUP(O37,Sheet1!W:X,2,FALSE) -> PASS
A38: Claims | B38: Invalid Data | C38: Invalid Data | D38: Invalid Data | F38: KDE00140 | G38: วันเดือนปีที่จ่ายเงินสินไหม | H38: Payment Date | I38: group_life | J38: glife | K38: hclaim | L38: paydate | M38: Completeness | N38: DQ Measurement Result - Claims.xlsx | O38: KDE00140group_life.glife.hclaim.paydateCompletenessClaims | P38: =VLOOKUP(O38,Sheet6!K:L,2,FALSE) -> 99.999977 | R38: Fail - Invalid Data | S38: Sprint40 | U38: =VLOOKUP(O38,Sheet1!W:X,2,FALSE) -> PASS
A39: Claims | B39: Invalid Data | C39: Invalid Data | D39: Invalid Data | F39: KDE00140 | G39: วันเดือนปีที่จ่ายเงินสินไหม | H39: Payment Date | I39: group_life | J39: glife | K39: medclaim | L39: paydate | M39: Completeness | N39: DQ Measurement Result - Claims.xlsx | O39: KDE00140group_life.glife.medclaim.paydateCompletenessClaims | P39: =VLOOKUP(O39,Sheet6!K:L,2,FALSE) -> 99.977093 | R39: Fail - Invalid Data | S39: Sprint40 | U39: =VLOOKUP(O39,Sheet1!W:X,2,FALSE) -> PASS
A40: Claims | B40: Invalid Data | C40: Invalid Data | D40: Invalid Data | F40: KDE00140 | G40: วันเดือนปีที่จ่ายเงินสินไหม | H40: Payment Date | I40: group_life | J40: glife | K40: hclaim | L40: paydate | M40: Validity | N40: DQ Measurement Result - Claims.xlsx | O40: KDE00140group_life.glife.hclaim.paydateValidityClaims | P40: =VLOOKUP(O40,Sheet6!K:L,2,FALSE) -> 99.999571 | R40: Fail - Invalid Data | S40: Sprint40 | U40: =VLOOKUP(O40,Sheet1!W:X,2,FALSE) -> PASS
... A44: Claims | B44: Invalid Data | C44: Invalid Data | D44: Invalid Data | F44: KDE00142 | G44: วันเดือนปีที่รับเอกสารเคลม | H44: Receive Document Date | I44: group_life | J44: glife | K44: medclaim | L44: recvdate | M44: Validity | N44: DQ Measurement Result - Claims.xlsx | O44: KDE00142group_life.glife.medclaim.recvdateValidityClaims | P44: =VLOOKUP(O44,Sheet6!K:L,2,FALSE) -> 99.998555 | R44: Fail - Invalid Data | S44: Sprint40 | U44: =VLOOKUP(O44,Sheet1!W:X,2,FALSE) -> PASS
A45: Claims | B45: Cannot be measured | C45: Cannot be measured | D45: Pass | F45: KDE00122 | G45: เลขเรื่องสินไหมประกันชีวิตรายบุคคล | H45: Individual Claim Number | I45: claim | J45: cclaim | K45: eclm | L45: orderno,sectioncode | M45: Validity | O45: KDE00122claim.cclaim.eclm.ClaimNumberValidityClaims | P45: =VLOOKUP(O45,Sheet6!K:L,2,FALSE) -> 100 | R45: Pass | S45: Sprint40 | U45: PASS | V45: Check data in source table dm_db.dbo.l_serv_master
A46: Claims | B46: Pass | C46: Pass | D46: Pass | F46: KDE00128 | G46: ช่องการเรียกร้องสินไหม | H46: channel of summit claim | I46: claim | J46: claimonline | K46: registeronline | L46: systemtype | M46: Completeness | O46: KDE00128claim.claimonline.registeronline.systemtypeCompletenessClaims | P46: =VLOOKUP(O46,Sheet6!K:L,2,FALSE) -> 100 | R46: Pass | S46: Sprint40 | U46: =VLOOKUP(O46,Sheet1!W:X,2,FALSE) -> Pass with Condition | V46: Check data in source table dm_db.dbo.tb_dmmast
A47: Claims | B47: Pass | C47: Pass | D47: Pass | F47: KDE00128 | G47: ช่องการเรียกร้องสินไหม | H47: channel of summit claim | I47: claim | J47: claimonline | K47: registeronline | L47: systemtype | M47: Integrity | O47: KDE00128claim.claimonline.registeronline.systemtypeIntegrityClaims | P47: =VLOOKUP(O47,Sheet6!K:L,2,FALSE) -> 100 | R47: Pass | S47: Sprint40 | U47: =VLOOKUP(O47,Sheet1!W:X,2,FALSE) -> PASS
A48: Claims | B48: Pass | C48: Pass | D48: Pass | F48: KDE00132 | G48: ประเภทผลประโยชน์การจ่ายสินไหม | H48: Benefit Type of paid | I48: group_life | J48: glife | K48: claimrcv | L48: claim_type | M48: Integrity | O48: KDE00132group_life.glife.claimrcv.claim_typeIntegrityClaims | P48: =VLOOKUP(O48,Sheet6!K:L,2,FALSE) -> 100 | R48: Pass | S48: Sprint40 | U48: =VLOOKUP(O48,Sheet1!W:X,2,FALSE) -> PASS
A49: Claims | B49: Pass | C49: Pass | D49: Pass | F49: KDE00132 | G49: ประเภทผลประโยชน์การจ่ายสินไหม | H49: Benefit Type of paid | I49: group_life | J49: glife | K49: hclaimrcv | L49: claim_type | M49: Integrity | O49: KDE00132group_life.glife.hclaimrcv.claim_typeIntegrityClaims | P49: =VLOOKUP(O49,Sheet6!K:L,2,FALSE) -> 100 | R49: Pass | S49: Sprint40 | U49: =VLOOKUP(O49,Sheet1!W:X,2,FALSE) -> PASS
A50: Claims | B50: Pass | C50: Pass | D50: Pass | F50: KDE00133 | G50: ค่ารักษาพยาบาลตามใบเสร็จ | H50: Incurred amount | I50: group_life | J50: glife | K50: hclaimrcv | L50: amount | M50: Completeness | O50: KDE00133group_life.glife.hclaimrcv.amountCompletenessClaims | P50: =VLOOKUP(O50,Sheet6!K:L,2,FALSE) -> 100 | R50: Pass | S50: Sprint40 | U50: =VLOOKUP(O50,Sheet1!W:X,2,FALSE) -> PASS
A51: Claims | B51: Cannot be measured | C51: Cannot be measured | D51: Pass | F51: KDE00134 | G51: จำนวนเงินที่จ่ายสินไหม | H51: Claim Paid amount | I51: policy | J51: mortgage | K51: cert | L51: amount1 | M51: Validity | O51: KDE00134policy.mortgage.cert.amount1ValidityClaims | P51: =VLOOKUP(O51,Sheet6!K:L,2,FALSE) -> 100 | R51: Pass | S51: Sprint40 | U51: =VLOOKUP(O51,Sheet1!W:X,2,FALSE) -> PASS
A52: Claims | B52: Cannot be measured | C52: Cannot be measured | D52: Pass | F52: KDE00138 | G52: วันที่เกิดเหตุ | H52: occurred date | I52: claim | J52: cclaim | K52: dth | L52: accidentdate | M52: Validity | O52: KDE00138claim.cclaim.dth.accidentdateValidityClaims | P52: =VLOOKUP(O52,Sheet6!K:L,2,FALSE) -> 100 | R52: Pass | S52: Sprint40 | U52: =VLOOKUP(O52,Sheet1!W:X,2,FALSE) -> PASS
A53: Claims | B53: Pass | C53: Pass | D53: Pass | F53: KDE00138 | G53: วันที่เกิดเหตุ | H53: occurred date | I53: claim | J53: cclaim | K53: dth | L53: accidentdate | M53: Completeness | O53: KDE00138claim.cclaim.dth.accidentdateCompletenessClaims | P53: =VLOOKUP(O53,Sheet6!K:L,2,FALSE) -> #N/A | R53: Pass | S53: No Result @PROD | T53: m_AccidentOccurredDate_Completeness_DS68 | U53: =VLOOKUP(O53,Sheet1!W:X,2,FALSE) -> PASS
A54: Claims | B54: Pass | C54: Pass | D54: Pass | F54: KDE00138 | G54: วันที่เกิดเหตุ | H54: occurred date | I54: claim | J54: cclaim | K54: iacm | L54: accidentdate | M54: Completeness | O54: KDE00138claim.cclaim.iacm.accidentdateCompletenessClaims | P54: =VLOOKUP(O54,Sheet6!K:L,2,FALSE) -> 100 | R54: Pass | S54: Sprint40 | U54: =VLOOKUP(O54,Sheet1!W:X,2,FALSE) -> PASS
A55: Claims | B55: Pass | C55: Pass | D55: Pass | F55: KDE00138 | G55: วันที่เกิดเหตุ | H55: occurred date | I55: claim | J55: cclaim | K55: mstwebclaim | L55: accidentdate | M55: Completeness | O55: KDE00138claim.cclaim.mstwebclaim.accidentdateCompletenessClaims | P55: =VLOOKUP(O55,Sheet6!K:L,2,FALSE) -> 100 | R55: Pass | S55: Sprint40 | U55: =VLOOKUP(O55,Sheet1!W:X,2,FALSE) -> PASS
A56: Claims | B56: Pass | C56: Pass | D56: Pass | F56: KDE00138 | G56: วันที่เกิดเหตุ | H56: occurred date | I56: claim | J56: cclaim | K56: oacm | L56: accidentdate | M56: Completeness | O56: KDE00138claim.cclaim.oacm.accidentdateCompletenessClaims | P56: =VLOOKUP(O56,Sheet6!K:L,2,FALSE) -> 100 | R56: Pass | S56: Sprint40 | U56: =VLOOKUP(O56,Sheet1!W:X,2,FALSE) -> PASS
A57: Claims | B57: Pass | C57: Pass | D57: Pass | F57: KDE00138 | G57: วันที่เกิดเหตุ | H57: occurred date | I57: mbl_db | J57: dbo | K57: after_eclaim | L57: admitdate | M57: Completeness | O57: KDE00138mbl_db.dbo.after_eclaim.admitdateCompletenessClaims | P57: =VLOOKUP(O57,Sheet6!K:L,2,FALSE) -> 100 | R57: Pass | S57: Sprint40 | U57: =VLOOKUP(O57,Sheet1!W:X,2,FALSE) -> PASS
A58: Claims | B58: Pass | C58: Pass | D58: Pass | F58: KDE00140 | G58: วันเดือนปีที่จ่ายเงินสินไหม | H58: Payment Date | I58: group_life | J58: glife | K58: claim | L58: paydate | M58: Validity | O58: KDE00140group_life.glife.claim.paydateValidityClaims | P58: =VLOOKUP(O58,Sheet6!K:L,2,FALSE) -> 100 | R58: Pass | S58: Sprint40 | U58: =VLOOKUP(O58,Sheet1!W:X,2,FALSE) -> PASS
A59: Claims | B59: Pass | C59: Pass | D59: Pass | F59: KDE00141 | G59: วันที่อนุมัติสินไหม | H59: Claim Approved date | I59: claim | J59: claimbook | K59: claimpayment | L59: claimokdate | M59: Completeness | O59: KDE00141claim.claimbook.claimpayment.claimokdateCompletenessClaims | P59: =VLOOKUP(O59,Sheet6!K:L,2,FALSE) -> #N/A | R59: Pass | S59: Sprint40 No Result @PROD | U59: =VLOOKUP(O59,Sheet1!W:X,2,FALSE) -> PASS
A60: Claims | B60: Pass | C60: Pass | D60: Pass | F60: KDE00141 | G60: วันที่อนุมัติสินไหม | H60: Claim Approved date | I60: claim | J60: claimbook | K60: claimpayment | L60: claimokdate | M60: Validity | O60: KDE00141claim.claimbook.claimpayment.claimokdateValidityClaims | P60: =VLOOKUP(O60,Sheet6!K:L,2,FALSE) -> #N/A | R60: Pass | S60: Sprint40 No Result @PROD | U60: =VLOOKUP(O60,Sheet1!W:X,2,FALSE) -> PASS
A61: Claims | B61: Cannot be measured | C61: Cannot be measured | D61: Pass | F61: KDE00142 | G61: วันเดือนปีที่รับเอกสารเคลม | H61: Receive Document Date | I61: group_life | J61: glife | K61: claim | L61: recvdate | M61: Validity | O61: KDE00142group_life.glife.claim.recvdateValidityClaims | P61: =VLOOKUP(O61,Sheet6!K:L,2,FALSE) -> 100 | R61: Pass | S61: Sprint40 | U61: =VLOOKUP(O61,Sheet1!W:X,2,FALSE) -> PASS
A62: Claims | B62: Pass | C62: Pass | D62: Pass | F62: KDE00142 | G62: วันเดือนปีที่รับเอกสารเคลม | H62: Receive Document Date | I62: group_life | J62: glife | K62: claim | L62: recvdate | M62: Completeness | O62: KDE00142group_life.glife.claim.recvdateCompletenessClaims | P62: =VLOOKUP(O62,Sheet6!K:L,2,FALSE) -> 100 | R62: Pass | S62: Sprint40 | U62: =VLOOKUP(O62,Sheet1!W:X,2,FALSE) -> PASS
A63: Claims | B63: Pass | C63: Pass | D63: Pass | F63: KDE00142 | G63: วันเดือนปีที่รับเอกสารเคลม | H63: Receive Document Date | I63: group_life | J63: glife | K63: medclaim | L63: recvdate | M63: Completeness | O63: KDE00142group_life.glife.medclaim.recvdateCompletenessClaims | P63: =VLOOKUP(O63,Sheet6!K:L,2,FALSE) -> 100 | R63: Pass | S63: Sprint40 | U63: =VLOOKUP(O63,Sheet1!W:X,2,FALSE) -> PASS
A64: Claims | B64: Pass | C64: Pass | D64: Pass | F64: KDE00143 | G64: เลขที่รับเรื่องในการเรียกร้องสินไหมสำหรับลูกค้าประกันกลุ่ม | H64: Receive CLaim Number | I64: group_life | J64: glife | K64: claim | L64: recvno | M64: Completeness | O64: KDE00143group_life.glife.claim.recvnoCompletenessClaims | P64: =VLOOKUP(O64,Sheet6!K:L,2,FALSE) -> 100 | R64: Pass | S64: Sprint40 | U64: =VLOOKUP(O64,Sheet1!W:X,2,FALSE) -> PASS
A65: Claims | B65: Pass | C65: Pass | D65: Pass | F65: KDE00143 | G65: เลขที่รับเรื่องในการเรียกร้องสินไหมสำหรับลูกค้าประกันกลุ่ม | H65: Receive CLaim Number | I65: group_life | J65: glife | K65: hclaim | L65: recvno | M65: Completeness | O65: KDE00143group_life.glife.hclaim.recvnoCompletenessClaims | P65: =VLOOKUP(O65,Sheet6!K:L,2,FALSE) -> 100 | R65: Pass | S65: Sprint40 | U65: =VLOOKUP(O65,Sheet1!W:X,2,FALSE) -> PASS
... A75: Claims | B75: Pass | C75: Pass | D75: Pass | F75: KDE00434 | G75: สถานะการพิจารณา | H75: Claim status | I75: claim | J75: claimbook | K75: claimpayment | L75: remarkno | M75: Integrity | O75: KDE00434claim.claimbook.claimpayment.remarknoIntegrityClaims | P75: =VLOOKUP(O75,Sheet6!K:L,2,FALSE) -> 100 | R75: Pass | S75: Sprint40 | U75: =VLOOKUP(O75,Sheet1!W:X,2,FALSE) -> PASS
A76: Customer | B76: Cannot be measured | C76: Cannot be measured | D76: Cannot be measured | F76: KDE00001 | G76: หมายเลขโทรศัพท์มือถือของผู้เอาประกัน | H76: Policyholder Mobile Phone Number | I76: underwrite | J76: cunderwrite | K76: phone | L76: phoneno | M76: Validity | O76: KDE00001underwrite.cunderwrite.phone.phonenoValidityCustomer | P76: =VLOOKUP(O76,Sheet6!K:L,2,FALSE) -> #N/A | R76: No Data Found | S76: No Result @PROD | T76: m_MobilePhoneNumber_Validity_DS797 | U76: =VLOOKUP(O76,Sheet1!W:X,2,FALSE) -> PASS
A77: Customer | B77: Cannot be measured | C77: Cannot be measured | D77: Cannot be measured | F77: KDE00005 | G77: เลขที่บัตรประชาชนของผู้รับมอบสิทธิ | H77: Assignee Identity Number | I77: pos | J77: srvservice | K77: delegatemast | L77: referenceid | M77: Completeness | O77: KDE00005pos.srvservice.delegatemast.referenceidCompletenessCustomer | P77: =VLOOKUP(O77,Sheet6!K:L,2,FALSE) -> 100 | S77: Cannot be measured | U77: =VLOOKUP(O77,Sheet1!W:X,2,FALSE) -> FIXED
A78: Customer | B78: Cannot be measured | C78: Cannot be measured | D78: Cannot be measured | F78: KDE00005 | G78: เลขประจำตัวประชาชนของผู้ปกครอง คบ. | H78: KB's Identification Number | I78: tlprompt | J78: public | K78: kb | L78: identifyid | M78: Completeness | O78: KDE00005tlprompt.public.kb.identifyidCompletenessCustomer | P78: =VLOOKUP(O78,Sheet6!K:L,2,FALSE) -> 98.767902 | S78: Cannot be measured | U78: =VLOOKUP(O78,Sheet1!W:X,2,FALSE) -> FIXED | V78: Incorrect IDQ Mapping Configured | W78: https://tli-edg.atlassian.net/browse/KDEI-551
A79: Customer | B79: Cannot be measured | C79: Cannot be measured | D79: Cannot be measured | F79: KDE00005 | G79: เลขประจำตัวประชาชนของผู้เอาประกันภัย | H79: Policyholder Identification Number | I79: claim | J79: cclaim | K79: eclaimform | L79: citizenid | M79: Completeness | O79: KDE00005claim.cclaim.eclaimform.citizenidCompletenessCustomer | P79: =VLOOKUP(O79,Sheet6!K:L,2,FALSE) -> 100 | S79: Cannot be measured | U79: =VLOOKUP(O79,Sheet1!W:X,2,FALSE) -> FIXED
A80: Customer | B80: Cannot be measured | C80: Cannot be measured | D80: Cannot be measured | F80: KDE00005 | G80: เลขประจำตัวประชาชนของผู้เอาประกันภัย | H80: Policyholder Identification Number | I80: common_db | J80: dbo | K80: tb_prospect | L80: citizen_id | M80: Completeness | O80: KDE00005common_db.dbo.tb_prospect.citizen_idCompletenessCustomer | P80: =VLOOKUP(O80,Sheet6!K:L,2,FALSE) -> 25.857275 | S80: Cannot be measured | U80: =VLOOKUP(O80,Sheet1!W:X,2,FALSE) -> FIXED
A81: Customer | B81: Cannot be measured | C81: Cannot be measured | D81: Cannot be measured | F81: KDE00005 | G81: เลขประจำตัวประชาชนของผู้เอาประกันภัย | H81: Policyholder Identification Number | I81: customer | J81: party | K81: party | L81: govt_id | M81: Completeness | O81: KDE00005customer.party.party.govt_idCompletenessCustomer | P81: =VLOOKUP(O81,Sheet6!K:L,2,FALSE) -> 98.209838 | S81: Cannot be measured | U81: =VLOOKUP(O81,Sheet1!W:X,2,FALSE) -> FIXED
A82: Customer | B82: Cannot be measured | C82: Cannot be measured | D82: Cannot be measured | F82: KDE00005 | G82: เลขประจำตัวประชาชนของผู้เอาประกันภัย | H82: Policyholder Identification Number | I82: dfl | J82: dfl | K82: mcaapplications | L82: identifyid | M82: Completeness | O82: KDE00005dfl.dfl.mcaapplications.identifyidCompletenessCustomer | P82: =VLOOKUP(O82,Sheet6!K:L,2,FALSE) -> #N/A | S82: Cannot be measured | U82: =VLOOKUP(O82,Sheet1!W:X,2,FALSE) -> FIXED
A83: Customer | B83: Cannot be measured | C83: Cannot be measured | D83: Cannot be measured | F83: KDE00005 | G83: เลขประจำตัวประชาชนของผู้เอาประกันภัย | H83: Policyholder Identification Number | I83: group_life | J83: glife | K83: citizenid | L83: referenceid | M83: Completeness | O83: KDE00005group_life.glife.citizenid.referenceidCompletenessCustomer | P83: =VLOOKUP(O83,Sheet6!K:L,2,FALSE) -> 99.958397 | S83: Cannot be measured | U83: =VLOOKUP(O83,Sheet1!W:X,2,FALSE) -> FIXED
A84: Customer | B84: Cannot be measured | C84: Cannot be measured | D84: Cannot be measured | F84: KDE00005 | G84: เลขประจำตัวประชาชนของผู้เอาประกันภัย | H84: Policyholder Identification Number | I84: policy | J84: mstperson | K84: person | L84: referenceid | M84: Completeness | O84: KDE00005policy.mstperson.person.referenceidCompletenessCustomer | P84: =VLOOKUP(O84,Sheet6!K:L,2,FALSE) -> 99.999881 | S84: Cannot be measured | U84: =VLOOKUP(O84,Sheet1!W:X,2,FALSE) -> FIXED
A85: Customer | B85: Cannot be measured | C85: Cannot be measured | D85: Cannot be measured | F85: KDE00005 | G85: เลขประจำตัวประชาชนของผู้เอาประกันภัย | H85: Policyholder Identification Number | I85: policy | J85: universal | K85: partialwithdraw | L85: referenceid | M85: Completeness | O85: KDE00005policy.universal.partialwithdraw.referenceidCompletenessCustomer | P85: =VLOOKUP(O85,Sheet6!K:L,2,FALSE) -> 100 | S85: Cannot be measured | U85: =VLOOKUP(O85,Sheet1!W:X,2,FALSE) -> FIXED
A86: Customer | B86: Cannot be measured | C86: Cannot be measured | D86: Cannot be measured | F86: KDE00005 | G86: เลขประจำตัวประชาชนของผู้เอาประกันภัย | H86: Policyholder Identification Number | I86: pos | J86: srvservice | K86: dvtran | L86: referenceid | M86: Completeness | O86: KDE00005pos.srvservice.dvtran.referenceidCompletenessCustomer | P86: =VLOOKUP(O86,Sheet6!K:L,2,FALSE) -> 99.99627 | S86: Cannot be measured | U86: =VLOOKUP(O86,Sheet1!W:X,2,FALSE) -> FIXED
A87: Customer | B87: Cannot be measured | C87: Cannot be measured | D87: Cannot be measured | F87: KDE00005 | G87: เลขประจำตัวประชาชนของผู้เอาประกันภัย | H87: Policyholder Identification Number | I87: tlprompt | J87: public | K87: mcaapplications | L87: identifyid | M87: Completeness | O87: KDE00005tlprompt.public.mcaapplications.identifyidCompletenessCustomer | P87: =VLOOKUP(O87,Sheet6!K:L,2,FALSE) -> 100 | S87: Cannot be measured | U87: =VLOOKUP(O87,Sheet1!W:X,2,FALSE) -> FIXED
A88: Customer | B88: Cannot be measured | C88: Cannot be measured | D88: Cannot be measured | F88: KDE00005 | G88: เลขประจำตัวประชาชนของผู้เอาประกันภัย | H88: Policyholder Identification Number | I88: underwrite | J88: cunderwrite | K88: appln | L88: idno | M88: Completeness | O88: KDE00005underwrite.cunderwrite.appln.idnoCompletenessCustomer | P88: =VLOOKUP(O88,Sheet6!K:L,2,FALSE) -> 100 | S88: Cannot be measured | U88: =VLOOKUP(O88,Sheet1!W:X,2,FALSE) -> FIXED
A89: Customer | B89: Cannot be measured | C89: Cannot be measured | D89: Cannot be measured | F89: KDE00005 | G89: เลขประจำตัวประชาชนของผู้เอาประกันภัย | H89: Policyholder Identification Number | I89: underwrite | J89: cunderwrite | K89: dmapplication | L89: idno | M89: Completeness | O89: KDE00005underwrite.cunderwrite.dmapplication.idnoCompletenessCustomer | P89: =VLOOKUP(O89,Sheet6!K:L,2,FALSE) -> 100 | S89: Cannot be measured | U89: =VLOOKUP(O89,Sheet1!W:X,2,FALSE) -> FIXED
A90: Customer | B90: Cannot be measured | C90: Cannot be measured | D90: Cannot be measured | F90: KDE00005 | G90: เลขที่บัตรประชาชนของผู้รับมอบสิทธิ | H90: Assignee Identity Number | I90: pos | J90: srvservice | K90: delegatemast | L90: referenceid | M90: Validity | O90: KDE00005pos.srvservice.delegatemast.referenceidValidityCustomer | P90: =VLOOKUP(O90,Sheet6!K:L,2,FALSE) -> 99.977162 | S90: Cannot be measured | U90: =VLOOKUP(O90,Sheet1!W:X,2,FALSE) -> NOT PASS
... A104: Customer | B104: Cannot be measured | C104: Cannot be measured | D104: Cannot be measured | F104: KDE00005 | G104: เลขประจำตัวประชาชนของผู้เอาประกันภัย | H104: Policyholder Identification Number | I104: pos | J104: srvservice | K104: mttranpermit | L104: referenceid | M104: Validity | O104: KDE00005pos.srvservice.mttranpermit.referenceidValidityCustomer | P104: =VLOOKUP(O104,Sheet6!K:L,2,FALSE) -> 100 | S104: Cannot be measured | U104: =VLOOKUP(O104,Sheet1!W:X,2,FALSE) -> NOT PASS
A105: Customer | B105: Cannot be measured | C105: Cannot be measured | D105: Cannot be measured | F105: KDE00005 | G105: เลขประจำตัวประชาชนของผู้เอาประกันภัย | H105: Policyholder Identification Number | I105: pos | J105: srvservice | K105: pctran | L105: referenceid | M105: Validity | P105: =VLOOKUP(O105,Sheet6!K:L,2,FALSE) -> #N/A | S105: Cannot be measured | U105: =VLOOKUP(O105,Sheet1!W:X,2,FALSE) -> #N/A
A106: Customer | B106: Cannot be measured | C106: Cannot be measured | D106: Cannot be measured | F106: KDE00005 | G106: เลขประจำตัวประชาชนของผู้เอาประกันภัย | H106: Policyholder Identification Number | I106: pos | J106: srvservice | K106: pstran | L106: referenceid | M106: Validity | O106: KDE00005pos.srvservice.pstran.referenceidValidityCustomer | P106: =VLOOKUP(O106,Sheet6!K:L,2,FALSE) -> 99.960032 | S106: Cannot be measured | U106: =VLOOKUP(O106,Sheet1!W:X,2,FALSE) -> NOT PASS
A107: Customer | B107: Cannot be measured | C107: Cannot be measured | D107: Cannot be measured | F107: KDE00005 | G107: เลขประจำตัวประชาชนของผู้เอาประกันภัย | H107: Policyholder Identification Number | I107: pos | J107: srvservice | K107: srtrano | L107: referenceid | M107: Validity | O107: KDE00005pos.srvservice.srtrano.referenceidValidityCustomer | P107: =VLOOKUP(O107,Sheet6!K:L,2,FALSE) -> 99.930303 | S107: Cannot be measured | U107: =VLOOKUP(O107,Sheet1!W:X,2,FALSE) -> NOT PASS
A108: Customer | B108: Cannot be measured | C108: Cannot be measured | D108: Cannot be measured | F108: KDE00005 | G108: เลขประจำตัวประชาชนของผู้เอาประกันภัย | H108: Policyholder Identification Number | I108: tlprompt | J108: public | K108: mcaapplications | L108: identifyid | M108: Validity | O108: KDE00005tlprompt.public.mcaapplications.identifyidValidityCustomer | P108: =VLOOKUP(O108,Sheet6!K:L,2,FALSE) -> 100 | S108: Cannot be measured | U108: =VLOOKUP(O108,Sheet1!W:X,2,FALSE) -> NOT PASS
A109: Customer | B109: Cannot be measured | C109: Cannot be measured | D109: Cannot be measured | F109: KDE00005 | G109: เลขประจำตัวประชาชนของผู้เอาประกันภัย | H109: Policyholder Identification Number | I109: underwrite | J109: cunderwrite | K109: appln | L109: idno | M109: Validity | O109: KDE00005underwrite.cunderwrite.appln.idnoValidityCustomer | P109: =VLOOKUP(O109,Sheet6!K:L,2,FALSE) -> 99.996334 | S109: Cannot be measured | U109: =VLOOKUP(O109,Sheet1!W:X,2,FALSE) -> FIXED
A110: Customer | B110: Cannot be measured | C110: Cannot be measured | D110: Cannot be measured | F110: KDE00005 | G110: เลขประจำตัวประชาชนของผู้เอาประกันภัย | H110: Policyholder Identification Number | I110: underwrite | J110: cunderwrite | K110: dmapplication | L110: idno | M110: Validity | O110: KDE00005underwrite.cunderwrite.dmapplication.idnoValidityCustomer | P110: =VLOOKUP(O110,Sheet6!K:L,2,FALSE) -> 100 | S110: Cannot be measured | U110: =VLOOKUP(O110,Sheet1!W:X,2,FALSE) -> NOT PASS
A111: Customer | B111: Cannot be measured | C111: Cannot be measured | D111: Cannot be measured | F111: KDE00007 | G111: เลขประจำตัวผู้เสียภาษีอากร | H111: Taxpayer identification number | I111: group_life | J111: glife | K111: engcompany | L111: regisnumber | M111: Completeness | O111: KDE00007group_life.glife.engcompany.regisnumberCompletenessCustomer | P111: =VLOOKUP(O111,Sheet6!K:L,2,FALSE) -> 92.051691 | S111: Cannot be measured | U111: =VLOOKUP(O111,Sheet1!W:X,2,FALSE) -> FIXED
A112: Customer | B112: Cannot be measured | C112: Cannot be measured | D112: Cannot be measured | F112: KDE00007 | G112: เลขประจำตัวผู้เสียภาษีอากร | H112: Taxpayer identification number | I112: tlprompt | J112: public | K112: payment | L112: personidtax | M112: Completeness | O112: KDE00007tlprompt.public.payment.personidtaxCompletenessCustomer | P112: =VLOOKUP(O112,Sheet6!K:L,2,FALSE) -> 0.30683312 | R112: Fail - Invalid Rules | U112: =VLOOKUP(O112,Sheet1!W:X,2,FALSE) -> PASS
A113: Customer | B113: Cannot be measured | C113: Cannot be measured | D113: Cannot be measured | F113: KDE00007 | G113: เลขประจำตัวผู้เสียภาษีอากร | H113: Taxpayer identification number | I113: group_life | J113: glife | K113: engcompany | L113: regisnumber | M113: Validity | O113: KDE00007group_life.glife.engcompany.regisnumberValidityCustomer | P113: =VLOOKUP(O113,Sheet6!K:L,2,FALSE) -> 99.788462 | S113: Cannot be measured | U113: =VLOOKUP(O113,Sheet1!W:X,2,FALSE) -> FIXED
A114: Customer | B114: Cannot be measured | C114: Cannot be measured | D114: Cannot be measured | F114: KDE00007 | G114: เลขประจำตัวผู้เสียภาษีอากร | H114: Taxpayer identification number | I114: policy | J114: cbranch | K114: nbnewappfield | L114: taxid | M114: Validity | O114: KDE00007policy.cbranch.nbnewappfield.taxidValidityCustomer | P114: =VLOOKUP(O114,Sheet6!K:L,2,FALSE) -> 99.787374 | S114: Cannot be measured | U114: =VLOOKUP(O114,Sheet1!W:X,2,FALSE) -> NOT PASS
A115: Customer | B115: Cannot be measured | C115: Cannot be measured | D115: Cannot be measured | F115: KDE00007 | G115: เลขประจำตัวผู้เสียภาษีอากร | H115: Taxpayer identification number | I115: pos | J115: newservice | K115: consent | L115: referenceid | M115: Validity | O115: KDE00007pos.newservice.consent.referenceidValidityCustomer | P115: =VLOOKUP(O115,Sheet6!K:L,2,FALSE) -> 99.637714 | S115: Cannot be measured | U115: =VLOOKUP(O115,Sheet1!W:X,2,FALSE) -> NOT PASS
A116: Customer | B116: Cannot be measured | C116: Cannot be measured | D116: Cannot be measured | F116: KDE00007 | G116: เลขประจำตัวผู้เสียภาษีอากร | H116: Taxpayer identification number | I116: tlprompt | J116: public | K116: payment | L116: personidtax | M116: Validity | O116: KDE00007tlprompt.public.payment.personidtaxValidityCustomer | P116: =VLOOKUP(O116,Sheet6!K:L,2,FALSE) -> #N/A | S116: Cannot be measured | U116: =VLOOKUP(O116,Sheet1!W:X,2,FALSE) -> FIXED
A117: Customer | B117: Cannot be measured | C117: Cannot be measured | D117: Cannot be measured | F117: KDE00008 | G117: เลขที่หนังสือเดินทางของผู้ขอเอาประกัน | H117: Policyholder Passport No. | I117: tlprompt | J117: public | K117: prospect | L117: passport | M117: Completeness | O117: KDE00008tlprompt.public.prospect.passportCompletenessCustomer | P117: =VLOOKUP(O117,Sheet6!K:L,2,FALSE) -> 0.60288425 | R117: Fail - Invalid Rules | U117: =VLOOKUP(O117,Sheet1!W:X,2,FALSE) -> PASS
A118: Customer | B118: Cannot be measured | C118: Cannot be measured | D118: Cannot be measured | F118: KDE00014 | G118: คำนำหน้าชื่อของผู้ขอเอาประกัน | H118: Applicant's Title | I118: policy | J118: mstperson | K118: name | L118: prename | M118: Integrity | O118: KDE00014policy.mstperson.name.prenameIntegrityCustomer | P118: =VLOOKUP(O118,Sheet6!K:L,2,FALSE) -> 96.266196 | S118: Cannot be measured | U118: =VLOOKUP(O118,Sheet1!W:X,2,FALSE) -> NOT PASS
A119: Customer | B119: Cannot be measured | C119: Cannot be measured | D119: Cannot be measured | F119: KDE00016 | G119: ชื่อ-นามสกุล ของผู้เอาประกัน | H119: Policyholder Name-Surname | I119: dm_db | J119: dbo | K119: l_serv_master | L119: first_name,last_name | M119: Completeness | O119: KDE00016dm_db.dbo.l_serv_master.firstnameCompletenessCustomer | P119: =VLOOKUP(O119,Sheet6!K:L,2,FALSE) -> #N/A | S119: No Result @PROD | T119: m_PersonName_Completeness_ENT904 | U119: =VLOOKUP(O119,Sheet1!W:X,2,FALSE) -> Pass with Condition
A120: Customer | B120: Cannot be measured | C120: Cannot be measured | D120: Cannot be measured | F120: KDE00016 | G120: ชื่อ-นามสกุล ของผู้เอาประกัน | H120: Policyholder Name-Surname | I120: dm_db | J120: dbo | K120: tb_dmmast | L120: firstname,lastname | M120: Completeness | O120: KDE00016dm_db.dbo.tb_dmmast.firstnameCompletenessCustomer | P120: =VLOOKUP(O120,Sheet6!K:L,2,FALSE) -> #N/A | R120: No Data Found | S120: No Result @PROD | T120: m_PersonName_Completeness_ENT1159 | U120: =VLOOKUP(O120,Sheet1!W:X,2,FALSE) -> Pass with Condition
A121: Customer | B121: Cannot be measured | C121: Cannot be measured | D121: Cannot be measured | F121: KDE00016 | G121: ชื่อ-นามสกุล ของผู้ขอเอาประกัน | H121: Applicant Name-Surname | I121: customer | J121: common_refund | K121: customers_refund | L121: firstname,lastname | M121: Validity | O121: KDE00016customer.common_refund.customers_refund.PersonNameValidityCustomer | P121: =VLOOKUP(O121,Sheet6!K:L,2,FALSE) -> 99.949685 | U121: =VLOOKUP(O121,Sheet1!W:X,2,FALSE) -> FIXED
A122: Customer | B122: Cannot be measured | C122: Cannot be measured | D122: Cannot be measured | F122: KDE00016 | G122: ชื่อ-นามสกุล ของผู้ขอเอาประกัน | H122: Applicant Name-Surname | I122: customer | J122: party | K122: person | L122: fname_th,lname_th | M122: Validity | O122: KDE00016customer.party.person.fname_thValidityCustomer | P122: =VLOOKUP(O122,Sheet6!K:L,2,FALSE) -> 99.994072 | U122: =VLOOKUP(O122,Sheet1!W:X,2,FALSE) -> NOT PASS
A123: Customer | B123: Cannot be measured | C123: Cannot be measured | D123: Cannot be measured | F123: KDE00016 | G123: ชื่อ-นามสกุล ของผู้ขอเอาประกัน | H123: Applicant Name-Surname | I123: dfl | J123: dfl | K123: mcaapplications | L123: name,lastname | M123: Validity | O123: KDE00016dfl.dfl.mcaapplications.PersonNameValidityCustomer | P123: =VLOOKUP(O123,Sheet6!K:L,2,FALSE) -> 99.990208 | U123: =VLOOKUP(O123,Sheet1!W:X,2,FALSE) -> NOT PASS
A124: Customer | B124: Cannot be measured | C124: Cannot be measured | D124: Cannot be measured | F124: KDE00016 | G124: ชื่อ-นามสกุล ของผู้ขอเอาประกัน | H124: Applicant Name-Surname | I124: finance_acc | J124: accountbranch | K124: paymentmst | L124: firstname,lastname | M124: Validity | O124: KDE00016finance_acc.accountbranch.paymentmst.PersonNameValidityCustomer | P124: =VLOOKUP(O124,Sheet6!K:L,2,FALSE) -> 99.963047 | U124: =VLOOKUP(O124,Sheet1!W:X,2,FALSE) -> FIXED
A125: Customer | B125: Cannot be measured | C125: Cannot be measured | D125: Cannot be measured | F125: KDE00016 | G125: ชื่อ-นามสกุล ของผู้ขอเอาประกัน | H125: Applicant Name-Surname | I125: group_life | J125: glife | K125: g | L125: fname,lname | M125: Validity | O125: KDE00016group_life.glife.g.PersonNameValidityCustomer | P125: =VLOOKUP(O125,Sheet6!K:L,2,FALSE) -> 99.906076 | U125: =VLOOKUP(O125,Sheet1!W:X,2,FALSE) -> NOT PASS
...

Sheet Sheet6
A1: KDENumber | B1: DataDomain | C1: Dimension | D1: DataField | E1: TestedRows | F1: AnomalyRows | G1: ValidRows | H1: ValidPercentage | I1: Threshold | J1: ThresholdStatus | K1: key
A2: KDE00734 | B2: Customer | C2: Validity | D2: dfl.dfl.beneficiary.identifyid | E2: 5 | F2: 5 | G2: 0 | H2: 0 | I2: 100 | J2: Fail | K2: =A2&D2&C2&B2 -> KDE00734dfl.dfl.beneficiary.identifyidValidityCustomer | L2: =H2 -> 0
A3: KDE00409 | B3: Customer | C3: Completeness | D3: dfl.dfl.mcaapplications.fatcaagree | E3: 40851 | F3: 40851 | G3: 0 | H3: 0 | I3: 100 | J3: Fail | K3: =A3&D3&C3&B3 -> KDE00409dfl.dfl.mcaapplications.fatcaagreeCompletenessCustomer | L3: =H3 -> 0
A4: KDE00413 | B4: Customer | C4: Validity | D4: pos.collection.gwcollection.card_number | E4: 1 | F4: 1 | G4: 0 | H4: 0 | I4: 100 | J4: Fail | K4: =A4&D4&C4&B4 -> KDE00413pos.collection.gwcollection.card_numberValidityCustomer | L4: =H4 -> 0
A5: KDE00223 | B5: Insurance/Policy | C5: Completeness | D5: tlprompt.public.quotation.savingpremium | E5: 4748538 | F5: 4746250 | G5: 2288 | H5: 0.048183251 | I5: 100 | J5: Fail | K5: =A5&D5&C5&B5 -> KDE00223tlprompt.public.quotation.savingpremiumCompletenessInsurance/Policy | L5: =H5 -> 0.048183251
A6: KDE00007 | B6: Customer | C6: Completeness | D6: tlprompt.public.payment.personidtax | E6: 1192179 | F6: 1188521 | G6: 3658 | H6: 0.30683312 | I6: 100 | J6: Fail | K6: =A6&D6&C6&B6 -> KDE00007tlprompt.public.payment.personidtaxCompletenessCustomer | L6: =H6 -> 0.30683312
A7: KDE00092 | B7: Customer | C7: Validity | D7: policy.mstpolicy.whlmast.occupationtype | E7: 4811 | F7: 4789 | G7: 22 | H7: 0.45728539 | I7: 100 | J7: Fail | K7: =A7&D7&C7&B7 -> KDE00092policy.mstpolicy.whlmast.occupationtypeValidityCustomer | L7: =H7 -> 0.45728539
A8: KDE00008 | B8: Customer | C8: Completeness | D8: tlprompt.public.prospect.passport | E8: 788211 | F8: 783459 | G8: 4752 | H8: 0.60288425 | I8: 100 | J8: Fail | K8: =A8&D8&C8&B8 -> KDE00008tlprompt.public.prospect.passportCompletenessCustomer | L8: =H8 -> 0.60288425
A9: KDE00256 | B9: Insurance/Policy | C9: Completeness | D9: policy.mortgage.cert.certno | E9: 1214344 | F9: 1199520 | G9: 14824 | H9: 1.2207414 | I9: 100 | J9: Fail | K9: =A9&D9&C9&B9 -> KDE00256policy.mortgage.cert.certnoCompletenessInsurance/Policy | L9: =H9 -> 1.2207414
A10: KDE00228 | B10: Insurance/Policy | C10: Completeness | D10: tlprompt.public.quotation.topuppremium | E10: 4748538 | F10: 4470238 | G10: 278300 | H10: 5.8607512 | I10: 100 | J10: Fail | K10: =A10&D10&C10&B10 -> KDE00228tlprompt.public.quotation.topuppremiumCompletenessInsurance/Policy | L10: =H10 -> 5.8607512
A11: KDE00005 | B11: Customer | C11: Completeness | D11: common_db.dbo.tb_prospect.citizen_id | E11: 1079 | F11: 800 | G11: 279 | H11: 25.857275 | I11: 100 | J11: Fail | K11: =A11&D11&C11&B11 -> KDE00005common_db.dbo.tb_prospect.citizen_idCompletenessCustomer | L11: =H11 -> 25.857275
A12: KDE00802 | B12: Customer | C12: Validity | D12: claim.claimbook.claimpaymentreceiver.citizenid | E12: 4507795 | F12: 3212059 | G12: 1295736 | H12: 28.744342 | I12: 100 | J12: Fail | K12: =A12&D12&C12&B12 -> KDE00802claim.claimbook.claimpaymentreceiver.citizenidValidityCustomer | L12: =H12 -> 28.744342
A13: KDE00005 | B13: Customer | C13: Validity | D13: pos.newservice.fatca.referenceid | E13: 60 | F13: 41 | G13: 19 | H13: 31.666667 | I13: 100 | J13: Fail | K13: =A13&D13&C13&B13 -> KDE00005pos.newservice.fatca.referenceidValidityCustomer | L13: =H13 -> 31.666667
... A796: KDE00363 | B796: Finance | C796: Validity | D796: underwrite.cunderwrite.job.psreceivedate | E796: 29510 | F796: 0 | G796: 29510 | H796: 100 | I796: 100 | J796: Pass | K796: =A796&D796&C796&B796 -> KDE00363underwrite.cunderwrite.job.psreceivedateValidityFinance | L796: =H796 -> 100

Sheet 20260601 Invalid Data
A1: Data Domain | B1: Status March | C1: Status May | D1: Status Jun | E1: KDE | F1: Key Data Element (Thai) | G1: Key Data Element (English) | H1: Src Database | I1: Src Schema | J1: Src Table | K1: Src Column | L1: Business DQ Rules | M1: Prod_ProfilingResult | N1: key | O1: ValidPercentage as of 20260601 | Q1: Prod_ThresholdStatus Jun | R1: Status | S1: Jobname | T1: Status Test | U1: RootCause | V1: Ticket
A2: Accounting | B2: Cannot be measured | C2: Cannot be measured | D2: Cannot be measured | E2: KDE00571 | F2: ค่าบำเหน็จ | G2: Commission | H2: sales | I2: salesbenefit_pg | J2: submit_ctrl_detail | K2: amount_pension | L2: Validity | N2: KDE00571sales.salesbenefit_pg.submit_ctrl_detail.amount_pensionValidityAccounting | R2: Cannot be measured | T2: =VLOOKUP(N2,Sheet1!W:X,2,FALSE) -> NOT PASS | U2: Check data in partioned tables: cunderwrite.phoneYYMM
A3: Accounting | B3: Cannot be measured | C3: Cannot be measured | D3: Cannot be measured | E3: KDE00572 | F3: ค่าพาหนะ | G3: Renewal Year Commission | H3: sales | I3: salesbenefit_pg | J3: submit_ctrl_detail | K3: amount_vehicle_fee | L3: Validity | N3: KDE00572sales.salesbenefit_pg.submit_ctrl_detail.amount_vehicle_feeValidityAccounting | R3: Cannot be measured | T3: =VLOOKUP(N3,Sheet1!W:X,2,FALSE) -> NOT PASS
A4: Accounting | B4: Pass | C4: Pass | D4: Pass | E4: KDE00383 | F4: อากรสแตมป์ | G4: Revenue Stamp | H4: pos | I4: srvservice | J4: lnrqst | K4: duty | L4: Validity | N4: KDE00383pos.srvservice.lnrqst.dutyValidityAccounting | O4: 100 | Q4: Pass | T4: =VLOOKUP(N4,Sheet1!W:X,2,FALSE) -> PASS
A5: Accounting | B5: Pass | C5: Pass | D5: Pass | E5: KDE00571 | F5: ค่าบำเหน็จ | G5: Commission | H5: corebiz | I5: ovdebt | J5: debttrndet | K5: benefit | L5: Validity | N5: KDE00571corebiz.ovdebt.debttrndet.benefitValidityAccounting | O5: 100 | Q5: Pass | T5: =VLOOKUP(N5,Sheet1!W:X,2,FALSE) -> PASS
A6: Accounting | B6: Pass | C6: Pass | D6: Pass | E6: KDE00571 | F6: ค่าบำเหน็จ | G6: Commission | H6: sales | I6: salesbenefit_pg | J6: bank_benefit_detail | K6: amount_commission | L6: Validity | N6: KDE00571sales.salesbenefit_pg.bank_benefit_detail.amount_commissionValidityAccounting | O6: 100 | Q6: Pass | T6: =VLOOKUP(N6,Sheet1!W:X,2,FALSE) -> PASS
A7: Accounting | B7: Pass | C7: Pass | D7: Pass | E7: KDE00572 | F7: ค่าพาหนะ | G7: Renewal Year Commission | H7: sales | I7: salesbenefit_pg | J7: bank_benefit_detail | K7: amount_renew_commission | L7: Validity | N7: KDE00572sales.salesbenefit_pg.bank_benefit_detail.amount_renew_commissionValidityAccounting | O7: 100 | Q7: Pass | T7: =VLOOKUP(N7,Sheet1!W:X,2,FALSE) -> PASS
A8: Accounting | B8: Pass | C8: Pass | D8: Pass | E8: KDE00574 | F8: ค่าจัดงานภาค | G8: District Overriding | H8: sales | I8: salesbenefit_pg | J8: bank_benefit_detail | K8: amount_district_ov | L8: Validity | N8: KDE00574sales.salesbenefit_pg.bank_benefit_detail.amount_district_ovValidityAccounting | O8: 100 | Q8: Pass | T8: =VLOOKUP(N8,Sheet1!W:X,2,FALSE) -> PASS
A9: Accounting | B9: Pass | C9: Pass | D9: Pass | E9: KDE00576 | F9: ค่าจัดงานหน่วย | G9: Unit Overriding | H9: sales | I9: salesbenefit_pg | J9: bank_benefit_detail | K9: amount_unit_ov | L9: Validity | N9: KDE00576sales.salesbenefit_pg.bank_benefit_detail.amount_unit_ovValidityAccounting | O9: 100 | Q9: Pass | T9: =VLOOKUP(N9,Sheet1!W:X,2,FALSE) -> PASS
A10: Accounting | B10: Pass | C10: Pass | D10: Pass | E10: KDE00578 | F10: ค่าแยกทีมงานภาค | G10: District Spin Off | H10: sales | I10: salesbenefit_pg | J10: bank_benefit_detail | K10: amount_district_so | L10: Validity | N10: KDE00578sales.salesbenefit_pg.bank_benefit_detail.amount_district_soValidityAccounting | O10: 100 | Q10: Pass | T10: =VLOOKUP(N10,Sheet1!W:X,2,FALSE) -> PASS
A11: Accounting | B11: Pass | C11: Pass | D11: Pass | E11: KDE00579 | F11: ค่าแยกทีมงานศูนย์ | G11: Division Spin Off | H11: sales | I11: salesbenefit_pg | J11: bank_benefit_detail | K11: amount_division_so | L11: Validity | N11: KDE00579sales.salesbenefit_pg.bank_benefit_detail.amount_division_soValidityAccounting | O11: 100 | Q11: Pass | T11: =VLOOKUP(N11,Sheet1!W:X,2,FALSE) -> PASS
A12: Accounting | B12: Pass | C12: Pass | D12: Pass | E12: KDE00580 | F12: ค่าแยกทีมงานหน่วย | G12: Unit Spin Off | H12: sales | I12: salesbenefit_pg | J12: bank_benefit_detail | K12: amount_unit_so | L12: Validity | N12: KDE00580sales.salesbenefit_pg.bank_benefit_detail.amount_unit_soValidityAccounting | O12: 100 | Q12: Pass | T12: =VLOOKUP(N12,Sheet1!W:X,2,FALSE) -> PASS
A13: Accounting | B13: Pass | C13: Pass | D13: Pass | E13: KDE00581 | F13: ค่าบริหารเป้าหมายภาค | G13: District Target | H13: sales | I13: salesbenefit_pg | J13: bank_benefit_detail | K13: amount_district_target | L13: Validity | N13: KDE00581sales.salesbenefit_pg.bank_benefit_detail.amount_district_targetValidityAccounting | O13: 100 | Q13: Pass | T13: =VLOOKUP(N13,Sheet1!W:X,2,FALSE) -> PASS
A14: Accounting | B14: Pass | C14: Pass | D14: Pass | E14: KDE00661 | F14: เลขที่บัญชีธนาคารของตัวแทนในการจ่ายเงิน (payment) - Sales benefit | G14: Bank account number | H14: sales | I14: salesbenefit_pg | J14: master_account_agent | K14: account_no | L14: Completeness | N14: KDE00661sales.salesbenefit_pg.master_account_agent.account_noCompletenessAccounting | O14: 100 | Q14: Pass | T14: =VLOOKUP(N14,Sheet1!W:X,2,FALSE) -> PASS
A15: Accounting | B15: Pass | C15: Pass | D15: Pass | E15: KDE00661 | F15: เลขที่บัญชีธนาคารของตัวแทนในการจ่ายเงิน (payment) - Sales benefit | G15: Bank account number | H15: sales | I15: salesbenefit_pg | J15: master_account_agent | K15: account_no | L15: Validity | N15: KDE00661sales.salesbenefit_pg.master_account_agent.account_noValidityAccounting | O15: 100 | Q15: Pass | T15: =VLOOKUP(N15,Sheet1!W:X,2,FALSE) -> PASS
A16: Claims | B16: Cannot be measured | C16: Cannot be measured | D16: Cannot be measured | E16: KDE00122 | F16: เลขเรื่องสินไหมประกันชีวิตรายบุคคล | G16: Individual Claim Number | H16: claim | I16: cmortgage | J16: mgclaim | K16: orderno,sectioncode | L16: Validity | N16: KDE00122claim.cmortgage.mgclaim.orderno,sectioncodeValidityClaims | R16: Cannot be measured | T16: =VLOOKUP(N16,Sheet1!W:X,2,FALSE) -> NOT PASS
A17: Claims | B17: Cannot be measured | C17: Cannot be measured | D17: Cannot be measured | E17: KDE00122 | F17: เลขเรื่องสินไหมประกันชีวิตรายบุคคล | G17: Individual Claim Number | H17: claim | I17: cmortgage | J17: mgfinorder | K17: orderNo,sectionCode | L17: Validity | N17: KDE00122claim.cmortgage.mgfinorder.ClaimNumberValidityClaims | R17: Sprint40 | T17: PASS
A18: Claims | B18: Cannot be measured | C18: Cannot be measured | D18: Cannot be measured | E18: KDE00123 | F18: เลขที่สินไหมสำหรับลูกค้าประกันกลุ่ม | G18: Group Claim Number | H18: policy | I18: cbaac | J18: mclmtrn907 | K18: claimNo | L18: Completeness | N18: KDE00123policy.cbaac.mclmtrn907.claimNoCompletenessClaims | R18: Sprint40 | T18: =VLOOKUP(N18,Sheet1!W:X,2,FALSE) -> PASS
A19: Claims | B19: Cannot be measured | C19: Cannot be measured | D19: Cannot be measured | E19: KDE00134 | F19: จำนวนเงินที่จ่ายสินไหม | G19: Claim Paid amount | H19: claim | I19: cclaim | J19: dth | K19: payLifeSum,payRiderSum | L19: Validity | N19: KDE00134claim.cclaim.dth.ClaimPaidAmountValidityClaims | R19: Sprint40 No Result @PROD | T19: PASS
A20: Claims | B20: Cannot be measured | C20: Cannot be measured | D20: Cannot be measured | E20: KDE00138 | F20: วันที่เกิดเหตุ | G20: occurred date | H20: policy | I20: mortgage | J20: cert | K20: deaddate | L20: Validity | N20: KDE00138policy.mortgage.cert.deaddateValidityClaims | R20: No Result @PROD | S20: m_PersonDeadDate_Validity_DS403 | T20: =VLOOKUP(N20,Sheet1!W:X,2,FALSE) -> PASS
A21: Claims | B21: Cannot be measured | C21: Cannot be measured | D21: Cannot be measured | E21: KDE00141 | F21: วันที่อนุมัติสินไหม | G21: Claim Approved date | H21: claim | I21: cmortgage | J21: mgfinorder | K21: claimOkDate | L21: Completeness | N21: KDE00141claim.cmortgage.mgfinorder.claimOkDateCompletenessClaims | R21: Sprint40 | T21: =VLOOKUP(N21,Sheet1!W:X,2,FALSE) -> PASS
A22: Claims | B22: Cannot be measured | C22: Cannot be measured | D22: Cannot be measured | E22: KDE00143 | F22: เลขที่รับเรื่องในการเรียกร้องสินไหมสำหรับลูกค้าประกันกลุ่ม | G22: Receive CLaim Number | H22: policy | I22: cbaac | J22: mclmrcv907 | K22: receiveNo | L22: Completeness | N22: KDE00143policy.cbaac.mclmrcv907.receiveNoCompletenessClaims | R22: Cannot be measured | T22: =VLOOKUP(N22,Sheet1!W:X,2,FALSE) -> NOT PASS
A23: Claims | B23: Cannot be measured | C23: Cannot be measured | D23: Invalid Data | E23: KDE00122 | F23: เลขเรื่องสินไหมประกันชีวิตรายบุคคล | G23: Individual Claim Number | H23: claim | I23: cclaim | J23: claim | K23: orderno,sectioncode | L23: Completeness | M23: DQ Measurement Result - Claims.xlsx | N23: KDE00122claim.cclaim.claim.ClaimNumberCompletenessClaims | O23: 99.999936 | Q23: Fail - Invalid Data | R23: Sprint40 | T23: PASS
A24: Claims | B24: Cannot be measured | C24: Cannot be measured | D24: Invalid Data | E24: KDE00122 | F24: เลขเรื่องสินไหมประกันชีวิตรายบุคคล | G24: Individual Claim Number | H24: claim | I24: cclaim | J24: claim | K24: orderno,sectioncode | L24: Validity | M24: DQ Measurement Result - Claims.xlsx | N24: KDE00122claim.cclaim.claim.ClaimNumberValidityClaims | O24: 99.999743 | Q24: Fail - Invalid Data | R24: Sprint40 | T24: PASS
A25: Claims | B25: Cannot be measured | C25: Cannot be measured | D25: Invalid Data | E25: KDE00122 | F25: เลขเรื่องสินไหมประกันชีวิตรายบุคคล | G25: Individual Claim Number | H25: claim | I25: cclaim | J25: excinsur | K25: orderno,sectioncode | L25: Validity | M25: DQ Measurement Result - Claims.xlsx | N25: KDE00122claim.cclaim.excinsur.ClaimNumberValidityClaims | O25: 99.993299 | Q25: Fail - Invalid Data | R25: Sprint40 | T25: PASS
A26: Claims | B26: Invalid Data | C26: Invalid Data | D26: Invalid Data | E26: KDE00125 | F26: เหตุผลที่ปฏิเสธการจ่ายสินไหม | G26: Reject reason | H26: group_life | I26: glife | J26: rejclaim | K26: reject_cause | L26: Completeness | M26: DQ Measurement Result - Claims.xlsx | N26: KDE00125group_life.glife.rejclaim.reject_causeCompletenessClaims | O26: 99.957348 | Q26: Fail - Invalid Data | R26: Sprint40 | T26: =VLOOKUP(N26,Sheet1!W:X,2,FALSE) -> PASS
A27: Claims | B27: Invalid Data | C27: Invalid Data | D27: Invalid Data | E27: KDE00133 | F27: ค่ารักษาพยาบาลตามใบเสร็จ | G27: Incurred amount | H27: group_life | I27: glife | J27: hclaimrcv | K27: amount | L27: Validity | M27: DQ Measurement Result - Claims.xlsx | N27: KDE00133group_life.glife.hclaimrcv.amountValidityClaims | O27: 99.999963 | Q27: Fail - Invalid Data | R27: Sprint40 | T27: =VLOOKUP(N27,Sheet1!W:X,2,FALSE) -> PASS
A28: Claims | B28: Cannot be measured | C28: Cannot be measured | D28: Invalid Data | E28: KDE00134 | F28: จำนวนเงินที่จ่ายสินไหม | G28: Claim Paid amount | H28: claim | I28: cclaim | J28: dth | K28: payLifeSum,payRiderSum | L28: Completeness | M28: DQ Measurement Result - Claims.xlsx | N28: KDE00134claim.cclaim.dth.ClaimPaidAmountCompletenessClaims | O28: 99.997295 | Q28: Fail - Invalid Data | R28: Sprint40 | T28: PASS
A29: Claims | B29: Cannot be measured | C29: Cannot be measured | D29: Invalid Data | E29: KDE00138 | F29: วันที่เกิดเหตุ | G29: occurred date | H29: claim | I29: cclaim | J29: iacm | K29: accidentdate | L29: Validity | M29: DQ Measurement Result - Claims.xlsx | N29: KDE00138claim.cclaim.iacm.accidentdateValidityClaims | O29: 99.991083 | Q29: Fail - Invalid Data | R29: Sprint40 | T29: =VLOOKUP(N29,Sheet1!W:X,2,FALSE) -> PASS
A30: Claims | B30: Cannot be measured | C30: Cannot be measured | D30: Invalid Data | E30: KDE00138 | F30: วันที่เกิดเหตุ | G30: occurred date | H30: mbl_db | I30: dbo | J30: after_eclaim | K30: admitdate | L30: Validity | M30: DQ Measurement Result - Claims.xlsx | N30: KDE00138mbl_db.dbo.after_eclaim.admitdateValidityClaims | O30: 99.962999 | Q30: Fail - Invalid Data | R30: Sprint40 | T30: =VLOOKUP(N30,Sheet1!W:X,2,FALSE) -> PASS
A31: Claims | B31: Invalid Data | C31: Invalid Data | D31: Invalid Data | E31: KDE00138 | F31: วันที่เกิดเหตุ | G31: occurred date | H31: claim | I31: cclaim | J31: mstwebclaim | K31: accidentdate | L31: Validity | M31: DQ Measurement Result - Claims.xlsx | N31: KDE00138claim.cclaim.mstwebclaim.accidentdateValidityClaims | O31: 99.954311 | Q31: Fail - Invalid Data | R31: Sprint40 | T31: =VLOOKUP(N31,Sheet1!W:X,2,FALSE) -> PASS
A32: Claims | B32: Invalid Data | C32: Invalid Data | D32: Invalid Data | E32: KDE00138 | F32: วันที่เกิดเหตุ | G32: occurred date | H32: claim | I32: cclaim | J32: oacm | K32: accidentdate | L32: Validity | M32: DQ Measurement Result - Claims.xlsx | N32: KDE00138claim.cclaim.oacm.accidentdateValidityClaims | O32: 99.998286 | Q32: Fail - Invalid Data | R32: Sprint40 | T32: =VLOOKUP(N32,Sheet1!W:X,2,FALSE) -> PASS
A33: Claims | B33: Cannot be measured | C33: Cannot be measured | D33: Invalid Data | E33: KDE00139 | F33: วันที่เข้ารับการรักษา | G33: Admission date | H33: claim | I33: cclaim | J33: mstwebclaim | K33: admitdate | L33: Completeness | M33: DQ Measurement Result - Claims.xlsx | N33: KDE00139claim.cclaim.mstwebclaim.admitdateCompletenessClaims | O33: 92.642859 | Q33: Fail - Invalid Data | R33: Sprint40 | T33: =VLOOKUP(N33,Sheet1!W:X,2,FALSE) -> PASS
A34: Claims | B34: Cannot be measured | C34: Cannot be measured | D34: Invalid Data | E34: KDE00139 | F34: วันที่เข้ารับการรักษา | G34: Admission date | H34: group_life | I34: glife | J34: hclaim | K34: st_healdate | L34: Completeness | M34: DQ Measurement Result - Claims.xlsx | N34: KDE00139group_life.glife.hclaim.st_healdateCompletenessClaims | O34: 99.999278 | Q34: Fail - Invalid Data | R34: Sprint40 | T34: =VLOOKUP(N34,Sheet1!W:X,2,FALSE) -> PASS
A35: Claims | B35: Cannot be measured | C35: Cannot be measured | D35: Invalid Data | E35: KDE00139 | F35: วันที่เข้ารับการรักษา | G35: Admission date | H35: claim | I35: cclaim | J35: mstwebclaim | K35: admitdate | L35: Validity | M35: DQ Measurement Result - Claims.xlsx | N35: KDE00139claim.cclaim.mstwebclaim.admitdateValidityClaims | O35: 99.999199 | Q35: Fail - Invalid Data | R35: Sprint40 | T35: =VLOOKUP(N35,Sheet1!W:X,2,FALSE) -> PASS
A36: Claims | B36: Invalid Data | C36: Invalid Data | D36: Invalid Data | E36: KDE00139 | F36: วันที่เข้ารับการรักษา | G36: Admission date | H36: group_life | I36: glife | J36: hclaim | K36: st_healdate | L36: Validity | M36: DQ Measurement Result - Claims.xlsx | N36: KDE00139group_life.glife.hclaim.st_healdateValidityClaims | O36: 99.999716 | Q36: Fail - Invalid Data | R36: Sprint40 | T36: =VLOOKUP(N36,Sheet1!W:X,2,FALSE) -> PASS
A37: Claims | B37: Invalid Data | C37: Invalid Data | D37: Invalid Data | E37: KDE00140 | F37: วันเดือนปีที่จ่ายเงินสินไหม | G37: Payment Date | H37: group_life | I37: glife | J37: claim | K37: paydate | L37: Completeness | M37: DQ Measurement Result - Claims.xlsx | N37: KDE00140group_life.glife.claim.paydateCompletenessClaims | O37: 99.871195 | Q37: Fail - Invalid Data | R37: Sprint40 | T37: =VLOOKUP(N37,Sheet1!W:X,2,FALSE) -> PASS
A38: Claims | B38: Invalid Data | C38: Invalid Data | D38: Invalid Data | E38: KDE00140 | F38: วันเดือนปีที่จ่ายเงินสินไหม | G38: Payment Date | H38: group_life | I38: glife | J38: hclaim | K38: paydate | L38: Completeness | M38: DQ Measurement Result - Claims.xlsx | N38: KDE00140group_life.glife.hclaim.paydateCompletenessClaims | O38: 99.999977 | Q38: Fail - Invalid Data | R38: Sprint40 | T38: =VLOOKUP(N38,Sheet1!W:X,2,FALSE) -> PASS
A39: Claims | B39: Invalid Data | C39: Invalid Data | D39: Invalid Data | E39: KDE00140 | F39: วันเดือนปีที่จ่ายเงินสินไหม | G39: Payment Date | H39: group_life | I39: glife | J39: medclaim | K39: paydate | L39: Completeness | M39: DQ Measurement Result - Claims.xlsx | N39: KDE00140group_life.glife.medclaim.paydateCompletenessClaims | O39: 99.977093 | Q39: Fail - Invalid Data | R39: Sprint40 | T39: =VLOOKUP(N39,Sheet1!W:X,2,FALSE) -> PASS
A40: Claims | B40: Invalid Data | C40: Invalid Data | D40: Invalid Data | E40: KDE00140 | F40: วันเดือนปีที่จ่ายเงินสินไหม | G40: Payment Date | H40: group_life | I40: glife | J40: hclaim | K40: paydate | L40: Validity | M40: DQ Measurement Result - Claims.xlsx | N40: KDE00140group_life.glife.hclaim.paydateValidityClaims | O40: 99.999571 | Q40: Fail - Invalid Data | R40: Sprint40 | T40: =VLOOKUP(N40,Sheet1!W:X,2,FALSE) -> PASS
... A44: Claims | B44: Invalid Data | C44: Invalid Data | D44: Invalid Data | E44: KDE00142 | F44: วันเดือนปีที่รับเอกสารเคลม | G44: Receive Document Date | H44: group_life | I44: glife | J44: medclaim | K44: recvdate | L44: Validity | M44: DQ Measurement Result - Claims.xlsx | N44: KDE00142group_life.glife.medclaim.recvdateValidityClaims | O44: 99.998555 | Q44: Fail - Invalid Data | R44: Sprint40 | T44: =VLOOKUP(N44,Sheet1!W:X,2,FALSE) -> PASS
A45: Claims | B45: Cannot be measured | C45: Cannot be measured | D45: Pass | E45: KDE00122 | F45: เลขเรื่องสินไหมประกันชีวิตรายบุคคล | G45: Individual Claim Number | H45: claim | I45: cclaim | J45: eclm | K45: orderno,sectioncode | L45: Validity | N45: KDE00122claim.cclaim.eclm.ClaimNumberValidityClaims | O45: 100 | Q45: Pass | R45: Sprint40 | T45: PASS | U45: Check data in source table dm_db.dbo.l_serv_master
A46: Claims | B46: Pass | C46: Pass | D46: Pass | E46: KDE00128 | F46: ช่องการเรียกร้องสินไหม | G46: channel of summit claim | H46: claim | I46: claimonline | J46: registeronline | K46: systemtype | L46: Completeness | N46: KDE00128claim.claimonline.registeronline.systemtypeCompletenessClaims | O46: 100 | Q46: Pass | R46: Sprint40 | T46: =VLOOKUP(N46,Sheet1!W:X,2,FALSE) -> Pass with Condition | U46: Check data in source table dm_db.dbo.tb_dmmast
A47: Claims | B47: Pass | C47: Pass | D47: Pass | E47: KDE00128 | F47: ช่องการเรียกร้องสินไหม | G47: channel of summit claim | H47: claim | I47: claimonline | J47: registeronline | K47: systemtype | L47: Integrity | N47: KDE00128claim.claimonline.registeronline.systemtypeIntegrityClaims | O47: 100 | Q47: Pass | R47: Sprint40 | T47: =VLOOKUP(N47,Sheet1!W:X,2,FALSE) -> PASS
A48: Claims | B48: Pass | C48: Pass | D48: Pass | E48: KDE00132 | F48: ประเภทผลประโยชน์การจ่ายสินไหม | G48: Benefit Type of paid | H48: group_life | I48: glife | J48: claimrcv | K48: claim_type | L48: Integrity | N48: KDE00132group_life.glife.claimrcv.claim_typeIntegrityClaims | O48: 100 | Q48: Pass | R48: Sprint40 | T48: =VLOOKUP(N48,Sheet1!W:X,2,FALSE) -> PASS
A49: Claims | B49: Pass | C49: Pass | D49: Pass | E49: KDE00132 | F49: ประเภทผลประโยชน์การจ่ายสินไหม | G49: Benefit Type of paid | H49: group_life | I49: glife | J49: hclaimrcv | K49: claim_type | L49: Integrity | N49: KDE00132group_life.glife.hclaimrcv.claim_typeIntegrityClaims | O49: 100 | Q49: Pass | R49: Sprint40 | T49: =VLOOKUP(N49,Sheet1!W:X,2,FALSE) -> PASS
A50: Claims | B50: Pass | C50: Pass | D50: Pass | E50: KDE00133 | F50: ค่ารักษาพยาบาลตามใบเสร็จ | G50: Incurred amount | H50: group_life | I50: glife | J50: hclaimrcv | K50: amount | L50: Completeness | N50: KDE00133group_life.glife.hclaimrcv.amountCompletenessClaims | O50: 100 | Q50: Pass | R50: Sprint40 | T50: =VLOOKUP(N50,Sheet1!W:X,2,FALSE) -> PASS
A51: Claims | B51: Cannot be measured | C51: Cannot be measured | D51: Pass | E51: KDE00134 | F51: จำนวนเงินที่จ่ายสินไหม | G51: Claim Paid amount | H51: policy | I51: mortgage | J51: cert | K51: amount1 | L51: Validity | N51: KDE00134policy.mortgage.cert.amount1ValidityClaims | O51: 100 | Q51: Pass | R51: Sprint40 | T51: =VLOOKUP(N51,Sheet1!W:X,2,FALSE) -> PASS
A52: Claims | B52: Cannot be measured | C52: Cannot be measured | D52: Pass | E52: KDE00138 | F52: วันที่เกิดเหตุ | G52: occurred date | H52: claim | I52: cclaim | J52: dth | K52: accidentdate | L52: Validity | N52: KDE00138claim.cclaim.dth.accidentdateValidityClaims | O52: 100 | Q52: Pass | R52: Sprint40 | T52: =VLOOKUP(N52,Sheet1!W:X,2,FALSE) -> PASS
A53: Claims | B53: Pass | C53: Pass | D53: Pass | E53: KDE00138 | F53: วันที่เกิดเหตุ | G53: occurred date | H53: claim | I53: cclaim | J53: dth | K53: accidentdate | L53: Completeness | N53: KDE00138claim.cclaim.dth.accidentdateCompletenessClaims | O53: 100 | Q53: Pass | R53: No Result @PROD | S53: m_AccidentOccurredDate_Completeness_DS68 | T53: =VLOOKUP(N53,Sheet1!W:X,2,FALSE) -> PASS
A54: Claims | B54: Pass | C54: Pass | D54: Pass | E54: KDE00138 | F54: วันที่เกิดเหตุ | G54: occurred date | H54: claim | I54: cclaim | J54: iacm | K54: accidentdate | L54: Completeness | N54: KDE00138claim.cclaim.iacm.accidentdateCompletenessClaims | O54: 100 | Q54: Pass | R54: Sprint40 | T54: =VLOOKUP(N54,Sheet1!W:X,2,FALSE) -> PASS
A55: Claims | B55: Pass | C55: Pass | D55: Pass | E55: KDE00138 | F55: วันที่เกิดเหตุ | G55: occurred date | H55: claim | I55: cclaim | J55: mstwebclaim | K55: accidentdate | L55: Completeness | N55: KDE00138claim.cclaim.mstwebclaim.accidentdateCompletenessClaims | O55: 100 | Q55: Pass | R55: Sprint40 | T55: =VLOOKUP(N55,Sheet1!W:X,2,FALSE) -> PASS
A56: Claims | B56: Pass | C56: Pass | D56: Pass | E56: KDE00138 | F56: วันที่เกิดเหตุ | G56: occurred date | H56: claim | I56: cclaim | J56: oacm | K56: accidentdate | L56: Completeness | N56: KDE00138claim.cclaim.oacm.accidentdateCompletenessClaims | O56: 100 | Q56: Pass | R56: Sprint40 | T56: =VLOOKUP(N56,Sheet1!W:X,2,FALSE) -> PASS
A57: Claims | B57: Pass | C57: Pass | D57: Pass | E57: KDE00138 | F57: วันที่เกิดเหตุ | G57: occurred date | H57: mbl_db | I57: dbo | J57: after_eclaim | K57: admitdate | L57: Completeness | N57: KDE00138mbl_db.dbo.after_eclaim.admitdateCompletenessClaims | O57: 100 | Q57: Pass | R57: Sprint40 | T57: =VLOOKUP(N57,Sheet1!W:X,2,FALSE) -> PASS
A58: Claims | B58: Pass | C58: Pass | D58: Pass | E58: KDE00140 | F58: วันเดือนปีที่จ่ายเงินสินไหม | G58: Payment Date | H58: group_life | I58: glife | J58: claim | K58: paydate | L58: Validity | N58: KDE00140group_life.glife.claim.paydateValidityClaims | O58: 100 | Q58: Pass | R58: Sprint40 | T58: =VLOOKUP(N58,Sheet1!W:X,2,FALSE) -> PASS
A59: Claims | B59: Pass | C59: Pass | D59: Pass | E59: KDE00141 | F59: วันที่อนุมัติสินไหม | G59: Claim Approved date | H59: claim | I59: claimbook | J59: claimpayment | K59: claimokdate | L59: Completeness | N59: KDE00141claim.claimbook.claimpayment.claimokdateCompletenessClaims | O59: 100 | Q59: Pass | R59: Sprint40 No Result @PROD | T59: =VLOOKUP(N59,Sheet1!W:X,2,FALSE) -> PASS
A60: Claims | B60: Pass | C60: Pass | D60: Pass | E60: KDE00141 | F60: วันที่อนุมัติสินไหม | G60: Claim Approved date | H60: claim | I60: claimbook | J60: claimpayment | K60: claimokdate | L60: Validity | N60: KDE00141claim.claimbook.claimpayment.claimokdateValidityClaims | O60: 100 | Q60: Pass | R60: Sprint40 No Result @PROD | T60: =VLOOKUP(N60,Sheet1!W:X,2,FALSE) -> PASS
A61: Claims | B61: Cannot be measured | C61: Cannot be measured | D61: Pass | E61: KDE00142 | F61: วันเดือนปีที่รับเอกสารเคลม | G61: Receive Document Date | H61: group_life | I61: glife | J61: claim | K61: recvdate | L61: Validity | N61: KDE00142group_life.glife.claim.recvdateValidityClaims | O61: 100 | Q61: Pass | R61: Sprint40 | T61: =VLOOKUP(N61,Sheet1!W:X,2,FALSE) -> PASS
A62: Claims | B62: Pass | C62: Pass | D62: Pass | E62: KDE00142 | F62: วันเดือนปีที่รับเอกสารเคลม | G62: Receive Document Date | H62: group_life | I62: glife | J62: claim | K62: recvdate | L62: Completeness | N62: KDE00142group_life.glife.claim.recvdateCompletenessClaims | O62: 100 | Q62: Pass | R62: Sprint40 | T62: =VLOOKUP(N62,Sheet1!W:X,2,FALSE) -> PASS
A63: Claims | B63: Pass | C63: Pass | D63: Pass | E63: KDE00142 | F63: วันเดือนปีที่รับเอกสารเคลม | G63: Receive Document Date | H63: group_life | I63: glife | J63: medclaim | K63: recvdate | L63: Completeness | N63: KDE00142group_life.glife.medclaim.recvdateCompletenessClaims | O63: 100 | Q63: Pass | R63: Sprint40 | T63: =VLOOKUP(N63,Sheet1!W:X,2,FALSE) -> PASS
A64: Claims | B64: Pass | C64: Pass | D64: Pass | E64: KDE00143 | F64: เลขที่รับเรื่องในการเรียกร้องสินไหมสำหรับลูกค้าประกันกลุ่ม | G64: Receive CLaim Number | H64: group_life | I64: glife | J64: claim | K64: recvno | L64: Completeness | N64: KDE00143group_life.glife.claim.recvnoCompletenessClaims | O64: 100 | Q64: Pass | R64: Sprint40 | T64: =VLOOKUP(N64,Sheet1!W:X,2,FALSE) -> PASS
A65: Claims | B65: Pass | C65: Pass | D65: Pass | E65: KDE00143 | F65: เลขที่รับเรื่องในการเรียกร้องสินไหมสำหรับลูกค้าประกันกลุ่ม | G65: Receive CLaim Number | H65: group_life | I65: glife | J65: hclaim | K65: recvno | L65: Completeness | N65: KDE00143group_life.glife.hclaim.recvnoCompletenessClaims | O65: 100 | Q65: Pass | R65: Sprint40 | T65: =VLOOKUP(N65,Sheet1!W:X,2,FALSE) -> PASS
... A75: Claims | B75: Pass | C75: Pass | D75: Pass | E75: KDE00434 | F75: สถานะการพิจารณา | G75: Claim status | H75: claim | I75: claimbook | J75: claimpayment | K75: remarkno | L75: Integrity | N75: KDE00434claim.claimbook.claimpayment.remarknoIntegrityClaims | O75: 100 | Q75: Pass | R75: Sprint40 | T75: =VLOOKUP(N75,Sheet1!W:X,2,FALSE) -> PASS
A76: Customer | B76: Cannot be measured | C76: Cannot be measured | D76: Cannot be measured | E76: KDE00001 | F76: หมายเลขโทรศัพท์มือถือของผู้เอาประกัน | G76: Policyholder Mobile Phone Number | H76: underwrite | I76: cunderwrite | J76: phone | K76: phoneno | L76: Validity | N76: KDE00001underwrite.cunderwrite.phone.phonenoValidityCustomer | Q76: No Data Found | R76: No Result @PROD | S76: m_MobilePhoneNumber_Validity_DS797 | T76: =VLOOKUP(N76,Sheet1!W:X,2,FALSE) -> PASS
A77: Customer | B77: Cannot be measured | C77: Cannot be measured | D77: Cannot be measured | E77: KDE00005 | F77: เลขที่บัตรประชาชนของผู้รับมอบสิทธิ | G77: Assignee Identity Number | H77: pos | I77: srvservice | J77: delegatemast | K77: referenceid | L77: Completeness | N77: KDE00005pos.srvservice.delegatemast.referenceidCompletenessCustomer | R77: Cannot be measured | T77: =VLOOKUP(N77,Sheet1!W:X,2,FALSE) -> FIXED
A78: Customer | B78: Cannot be measured | C78: Cannot be measured | D78: Cannot be measured | E78: KDE00005 | F78: เลขประจำตัวประชาชนของผู้ปกครอง คบ. | G78: KB's Identification Number | H78: tlprompt | I78: public | J78: kb | K78: identifyid | L78: Completeness | N78: KDE00005tlprompt.public.kb.identifyidCompletenessCustomer | R78: Cannot be measured | T78: =VLOOKUP(N78,Sheet1!W:X,2,FALSE) -> FIXED | U78: Incorrect IDQ Mapping Configured | V78: https://tli-edg.atlassian.net/browse/KDEI-551
A79: Customer | B79: Cannot be measured | C79: Cannot be measured | D79: Cannot be measured | E79: KDE00005 | F79: เลขประจำตัวประชาชนของผู้เอาประกันภัย | G79: Policyholder Identification Number | H79: claim | I79: cclaim | J79: eclaimform | K79: citizenid | L79: Completeness | N79: KDE00005claim.cclaim.eclaimform.citizenidCompletenessCustomer | R79: Cannot be measured | T79: =VLOOKUP(N79,Sheet1!W:X,2,FALSE) -> FIXED
A80: Customer | B80: Cannot be measured | C80: Cannot be measured | D80: Cannot be measured | E80: KDE00005 | F80: เลขประจำตัวประชาชนของผู้เอาประกันภัย | G80: Policyholder Identification Number | H80: common_db | I80: dbo | J80: tb_prospect | K80: citizen_id | L80: Completeness | N80: KDE00005common_db.dbo.tb_prospect.citizen_idCompletenessCustomer | R80: Cannot be measured | T80: =VLOOKUP(N80,Sheet1!W:X,2,FALSE) -> FIXED
A81: Customer | B81: Cannot be measured | C81: Cannot be measured | D81: Cannot be measured | E81: KDE00005 | F81: เลขประจำตัวประชาชนของผู้เอาประกันภัย | G81: Policyholder Identification Number | H81: customer | I81: party | J81: party | K81: govt_id | L81: Completeness | N81: KDE00005customer.party.party.govt_idCompletenessCustomer | R81: Cannot be measured | T81: =VLOOKUP(N81,Sheet1!W:X,2,FALSE) -> FIXED
A82: Customer | B82: Cannot be measured | C82: Cannot be measured | D82: Cannot be measured | E82: KDE00005 | F82: เลขประจำตัวประชาชนของผู้เอาประกันภัย | G82: Policyholder Identification Number | H82: dfl | I82: dfl | J82: mcaapplications | K82: identifyid | L82: Completeness | N82: KDE00005dfl.dfl.mcaapplications.identifyidCompletenessCustomer | R82: Cannot be measured | T82: =VLOOKUP(N82,Sheet1!W:X,2,FALSE) -> FIXED
A83: Customer | B83: Cannot be measured | C83: Cannot be measured | D83: Cannot be measured | E83: KDE00005 | F83: เลขประจำตัวประชาชนของผู้เอาประกันภัย | G83: Policyholder Identification Number | H83: group_life | I83: glife | J83: citizenid | K83: referenceid | L83: Completeness | N83: KDE00005group_life.glife.citizenid.referenceidCompletenessCustomer | R83: Cannot be measured | T83: =VLOOKUP(N83,Sheet1!W:X,2,FALSE) -> FIXED
A84: Customer | B84: Cannot be measured | C84: Cannot be measured | D84: Cannot be measured | E84: KDE00005 | F84: เลขประจำตัวประชาชนของผู้เอาประกันภัย | G84: Policyholder Identification Number | H84: policy | I84: mstperson | J84: person | K84: referenceid | L84: Completeness | N84: KDE00005policy.mstperson.person.referenceidCompletenessCustomer | R84: Cannot be measured | T84: =VLOOKUP(N84,Sheet1!W:X,2,FALSE) -> FIXED
A85: Customer | B85: Cannot be measured | C85: Cannot be measured | D85: Cannot be measured | E85: KDE00005 | F85: เลขประจำตัวประชาชนของผู้เอาประกันภัย | G85: Policyholder Identification Number | H85: policy | I85: universal | J85: partialwithdraw | K85: referenceid | L85: Completeness | N85: KDE00005policy.universal.partialwithdraw.referenceidCompletenessCustomer | R85: Cannot be measured | T85: =VLOOKUP(N85,Sheet1!W:X,2,FALSE) -> FIXED
A86: Customer | B86: Cannot be measured | C86: Cannot be measured | D86: Cannot be measured | E86: KDE00005 | F86: เลขประจำตัวประชาชนของผู้เอาประกันภัย | G86: Policyholder Identification Number | H86: pos | I86: srvservice | J86: dvtran | K86: referenceid | L86: Completeness | N86: KDE00005pos.srvservice.dvtran.referenceidCompletenessCustomer | R86: Cannot be measured | T86: =VLOOKUP(N86,Sheet1!W:X,2,FALSE) -> FIXED
A87: Customer | B87: Cannot be measured | C87: Cannot be measured | D87: Cannot be measured | E87: KDE00005 | F87: เลขประจำตัวประชาชนของผู้เอาประกันภัย | G87: Policyholder Identification Number | H87: tlprompt | I87: public | J87: mcaapplications | K87: identifyid | L87: Completeness | N87: KDE00005tlprompt.public.mcaapplications.identifyidCompletenessCustomer | R87: Cannot be measured | T87: =VLOOKUP(N87,Sheet1!W:X,2,FALSE) -> FIXED
A88: Customer | B88: Cannot be measured | C88: Cannot be measured | D88: Cannot be measured | E88: KDE00005 | F88: เลขประจำตัวประชาชนของผู้เอาประกันภัย | G88: Policyholder Identification Number | H88: underwrite | I88: cunderwrite | J88: appln | K88: idno | L88: Completeness | N88: KDE00005underwrite.cunderwrite.appln.idnoCompletenessCustomer | R88: Cannot be measured | T88: =VLOOKUP(N88,Sheet1!W:X,2,FALSE) -> FIXED
A89: Customer | B89: Cannot be measured | C89: Cannot be measured | D89: Cannot be measured | E89: KDE00005 | F89: เลขประจำตัวประชาชนของผู้เอาประกันภัย | G89: Policyholder Identification Number | H89: underwrite | I89: cunderwrite | J89: dmapplication | K89: idno | L89: Completeness | N89: KDE00005underwrite.cunderwrite.dmapplication.idnoCompletenessCustomer | R89: Cannot be measured | T89: =VLOOKUP(N89,Sheet1!W:X,2,FALSE) -> FIXED
A90: Customer | B90: Cannot be measured | C90: Cannot be measured | D90: Cannot be measured | E90: KDE00005 | F90: เลขที่บัตรประชาชนของผู้รับมอบสิทธิ | G90: Assignee Identity Number | H90: pos | I90: srvservice | J90: delegatemast | K90: referenceid | L90: Validity | N90: KDE00005pos.srvservice.delegatemast.referenceidValidityCustomer | R90: Cannot be measured | T90: =VLOOKUP(N90,Sheet1!W:X,2,FALSE) -> NOT PASS
... A104: Customer | B104: Cannot be measured | C104: Cannot be measured | D104: Cannot be measured | E104: KDE00005 | F104: เลขประจำตัวประชาชนของผู้เอาประกันภัย | G104: Policyholder Identification Number | H104: pos | I104: srvservice | J104: mttranpermit | K104: referenceid | L104: Validity | N104: KDE00005pos.srvservice.mttranpermit.referenceidValidityCustomer | R104: Cannot be measured | T104: =VLOOKUP(N104,Sheet1!W:X,2,FALSE) -> NOT PASS
A105: Customer | B105: Cannot be measured | C105: Cannot be measured | D105: Cannot be measured | E105: KDE00005 | F105: เลขประจำตัวประชาชนของผู้เอาประกันภัย | G105: Policyholder Identification Number | H105: pos | I105: srvservice | J105: pctran | K105: referenceid | L105: Validity | R105: Cannot be measured | T105: =VLOOKUP(N105,Sheet1!W:X,2,FALSE) -> #N/A
A106: Customer | B106: Cannot be measured | C106: Cannot be measured | D106: Cannot be measured | E106: KDE00005 | F106: เลขประจำตัวประชาชนของผู้เอาประกันภัย | G106: Policyholder Identification Number | H106: pos | I106: srvservice | J106: pstran | K106: referenceid | L106: Validity | N106: KDE00005pos.srvservice.pstran.referenceidValidityCustomer | R106: Cannot be measured | T106: =VLOOKUP(N106,Sheet1!W:X,2,FALSE) -> NOT PASS
A107: Customer | B107: Cannot be measured | C107: Cannot be measured | D107: Cannot be measured | E107: KDE00005 | F107: เลขประจำตัวประชาชนของผู้เอาประกันภัย | G107: Policyholder Identification Number | H107: pos | I107: srvservice | J107: srtrano | K107: referenceid | L107: Validity | N107: KDE00005pos.srvservice.srtrano.referenceidValidityCustomer | R107: Cannot be measured | T107: =VLOOKUP(N107,Sheet1!W:X,2,FALSE) -> NOT PASS
A108: Customer | B108: Cannot be measured | C108: Cannot be measured | D108: Cannot be measured | E108: KDE00005 | F108: เลขประจำตัวประชาชนของผู้เอาประกันภัย | G108: Policyholder Identification Number | H108: tlprompt | I108: public | J108: mcaapplications | K108: identifyid | L108: Validity | N108: KDE00005tlprompt.public.mcaapplications.identifyidValidityCustomer | R108: Cannot be measured | T108: =VLOOKUP(N108,Sheet1!W:X,2,FALSE) -> NOT PASS
A109: Customer | B109: Cannot be measured | C109: Cannot be measured | D109: Cannot be measured | E109: KDE00005 | F109: เลขประจำตัวประชาชนของผู้เอาประกันภัย | G109: Policyholder Identification Number | H109: underwrite | I109: cunderwrite | J109: appln | K109: idno | L109: Validity | N109: KDE00005underwrite.cunderwrite.appln.idnoValidityCustomer | R109: Cannot be measured | T109: =VLOOKUP(N109,Sheet1!W:X,2,FALSE) -> FIXED
A110: Customer | B110: Cannot be measured | C110: Cannot be measured | D110: Cannot be measured | E110: KDE00005 | F110: เลขประจำตัวประชาชนของผู้เอาประกันภัย | G110: Policyholder Identification Number | H110: underwrite | I110: cunderwrite | J110: dmapplication | K110: idno | L110: Validity | N110: KDE00005underwrite.cunderwrite.dmapplication.idnoValidityCustomer | R110: Cannot be measured | T110: =VLOOKUP(N110,Sheet1!W:X,2,FALSE) -> NOT PASS
A111: Customer | B111: Cannot be measured | C111: Cannot be measured | D111: Cannot be measured | E111: KDE00007 | F111: เลขประจำตัวผู้เสียภาษีอากร | G111: Taxpayer identification number | H111: group_life | I111: glife | J111: engcompany | K111: regisnumber | L111: Completeness | N111: KDE00007group_life.glife.engcompany.regisnumberCompletenessCustomer | R111: Cannot be measured | T111: =VLOOKUP(N111,Sheet1!W:X,2,FALSE) -> FIXED
A112: Customer | B112: Cannot be measured | C112: Cannot be measured | D112: Cannot be measured | E112: KDE00007 | F112: เลขประจำตัวผู้เสียภาษีอากร | G112: Taxpayer identification number | H112: tlprompt | I112: public | J112: payment | K112: personidtax | L112: Completeness | N112: KDE00007tlprompt.public.payment.personidtaxCompletenessCustomer | O112: 0.30683312 | Q112: Fail - Invalid Rules | T112: =VLOOKUP(N112,Sheet1!W:X,2,FALSE) -> PASS
A113: Customer | B113: Cannot be measured | C113: Cannot be measured | D113: Cannot be measured | E113: KDE00007 | F113: เลขประจำตัวผู้เสียภาษีอากร | G113: Taxpayer identification number | H113: group_life | I113: glife | J113: engcompany | K113: regisnumber | L113: Validity | N113: KDE00007group_life.glife.engcompany.regisnumberValidityCustomer | R113: Cannot be measured | T113: =VLOOKUP(N113,Sheet1!W:X,2,FALSE) -> FIXED
A114: Customer | B114: Cannot be measured | C114: Cannot be measured | D114: Cannot be measured | E114: KDE00007 | F114: เลขประจำตัวผู้เสียภาษีอากร | G114: Taxpayer identification number | H114: policy | I114: cbranch | J114: nbnewappfield | K114: taxid | L114: Validity | N114: KDE00007policy.cbranch.nbnewappfield.taxidValidityCustomer | R114: Cannot be measured | T114: =VLOOKUP(N114,Sheet1!W:X,2,FALSE) -> NOT PASS
A115: Customer | B115: Cannot be measured | C115: Cannot be measured | D115: Cannot be measured | E115: KDE00007 | F115: เลขประจำตัวผู้เสียภาษีอากร | G115: Taxpayer identification number | H115: pos | I115: newservice | J115: consent | K115: referenceid | L115: Validity | N115: KDE00007pos.newservice.consent.referenceidValidityCustomer | R115: Cannot be measured | T115: =VLOOKUP(N115,Sheet1!W:X,2,FALSE) -> NOT PASS
A116: Customer | B116: Cannot be measured | C116: Cannot be measured | D116: Cannot be measured | E116: KDE00007 | F116: เลขประจำตัวผู้เสียภาษีอากร | G116: Taxpayer identification number | H116: tlprompt | I116: public | J116: payment | K116: personidtax | L116: Validity | N116: KDE00007tlprompt.public.payment.personidtaxValidityCustomer | R116: Cannot be measured | T116: =VLOOKUP(N116,Sheet1!W:X,2,FALSE) -> FIXED
A117: Customer | B117: Cannot be measured | C117: Cannot be measured | D117: Cannot be measured | E117: KDE00008 | F117: เลขที่หนังสือเดินทางของผู้ขอเอาประกัน | G117: Policyholder Passport No. | H117: tlprompt | I117: public | J117: prospect | K117: passport | L117: Completeness | N117: KDE00008tlprompt.public.prospect.passportCompletenessCustomer | O117: 0.60288425 | Q117: Fail - Invalid Rules | T117: =VLOOKUP(N117,Sheet1!W:X,2,FALSE) -> PASS
A118: Customer | B118: Cannot be measured | C118: Cannot be measured | D118: Cannot be measured | E118: KDE00014 | F118: คำนำหน้าชื่อของผู้ขอเอาประกัน | G118: Applicant's Title | H118: policy | I118: mstperson | J118: name | K118: prename | L118: Integrity | N118: KDE00014policy.mstperson.name.prenameIntegrityCustomer | R118: Cannot be measured | T118: =VLOOKUP(N118,Sheet1!W:X,2,FALSE) -> NOT PASS
A119: Customer | B119: Cannot be measured | C119: Cannot be measured | D119: Cannot be measured | E119: KDE00016 | F119: ชื่อ-นามสกุล ของผู้เอาประกัน | G119: Policyholder Name-Surname | H119: dm_db | I119: dbo | J119: l_serv_master | K119: first_name,last_name | L119: Completeness | N119: KDE00016dm_db.dbo.l_serv_master.firstnameCompletenessCustomer | R119: No Result @PROD | S119: m_PersonName_Completeness_ENT904 | T119: =VLOOKUP(N119,Sheet1!W:X,2,FALSE) -> Pass with Condition
A120: Customer | B120: Cannot be measured | C120: Cannot be measured | D120: Cannot be measured | E120: KDE00016 | F120: ชื่อ-นามสกุล ของผู้เอาประกัน | G120: Policyholder Name-Surname | H120: dm_db | I120: dbo | J120: tb_dmmast | K120: firstname,lastname | L120: Completeness | N120: KDE00016dm_db.dbo.tb_dmmast.firstnameCompletenessCustomer | Q120: No Data Found | R120: No Result @PROD | S120: m_PersonName_Completeness_ENT1159 | T120: =VLOOKUP(N120,Sheet1!W:X,2,FALSE) -> Pass with Condition
A121: Customer | B121: Cannot be measured | C121: Cannot be measured | D121: Cannot be measured | E121: KDE00016 | F121: ชื่อ-นามสกุล ของผู้ขอเอาประกัน | G121: Applicant Name-Surname | H121: customer | I121: common_refund | J121: customers_refund | K121: firstname,lastname | L121: Validity | N121: KDE00016customer.common_refund.customers_refund.PersonNameValidityCustomer | T121: =VLOOKUP(N121,Sheet1!W:X,2,FALSE) -> FIXED
A122: Customer | B122: Cannot be measured | C122: Cannot be measured | D122: Cannot be measured | E122: KDE00016 | F122: ชื่อ-นามสกุล ของผู้ขอเอาประกัน | G122: Applicant Name-Surname | H122: customer | I122: party | J122: person | K122: fname_th,lname_th | L122: Validity | N122: KDE00016customer.party.person.fname_thValidityCustomer | T122: =VLOOKUP(N122,Sheet1!W:X,2,FALSE) -> NOT PASS
A123: Customer | B123: Cannot be measured | C123: Cannot be measured | D123: Cannot be measured | E123: KDE00016 | F123: ชื่อ-นามสกุล ของผู้ขอเอาประกัน | G123: Applicant Name-Surname | H123: dfl | I123: dfl | J123: mcaapplications | K123: name,lastname | L123: Validity | N123: KDE00016dfl.dfl.mcaapplications.PersonNameValidityCustomer | T123: =VLOOKUP(N123,Sheet1!W:X,2,FALSE) -> NOT PASS
A124: Customer | B124: Cannot be measured | C124: Cannot be measured | D124: Cannot be measured | E124: KDE00016 | F124: ชื่อ-นามสกุล ของผู้ขอเอาประกัน | G124: Applicant Name-Surname | H124: finance_acc | I124: accountbranch | J124: paymentmst | K124: firstname,lastname | L124: Validity | N124: KDE00016finance_acc.accountbranch.paymentmst.PersonNameValidityCustomer | T124: =VLOOKUP(N124,Sheet1!W:X,2,FALSE) -> FIXED
A125: Customer | B125: Cannot be measured | C125: Cannot be measured | D125: Cannot be measured | E125: KDE00016 | F125: ชื่อ-นามสกุล ของผู้ขอเอาประกัน | G125: Applicant Name-Surname | H125: group_life | I125: glife | J125: g | K125: fname,lname | L125: Validity | N125: KDE00016group_life.glife.g.PersonNameValidityCustomer | T125: =VLOOKUP(N125,Sheet1!W:X,2,FALSE) -> NOT PASS
...

Sheet Sheet7
A1: Cannot be measured | B1: KDE00001
C2: Invalid Data | D2: KDE00002
C3: Invalid Data | D3: KDE00003
C4: Invalid Data | D4: KDE00004
A5: Cannot be measured | B5: KDE00005
A6: Cannot be measured | B6: KDE00007
A7: Cannot be measured | B7: KDE00008
E8: Pass | F8: KDE00009
C9: Invalid Data | D9: KDE00010
C10: Invalid Data | D10: KDE00011
A11: Cannot be measured | B11: KDE00014
A12: Cannot be measured | B12: KDE00016
C13: Invalid Data | D13: KDE00018
A14: Cannot be measured | B14: KDE00025
C15: Invalid Data | D15: KDE00026
C16: Invalid Data | D16: KDE00027
C17: Invalid Data | D17: KDE00092
A18: Cannot be measured | B18: KDE00093
C19: Invalid Data | D19: KDE00098
E20: Pass | F20: KDE00099
A21: Cannot be measured | B21: KDE00104
A22: Cannot be measured | B22: KDE00121
A23: Cannot be measured | B23: KDE00163
A24: Cannot be measured | B24: KDE00409
A25: Cannot be measured | B25: KDE00724 | E25: Pass | F25: KDE00105
A26: Cannot be measured | B26: KDE00725 | E26: Pass | F26: KDE00111
A27: Cannot be measured | B27: KDE00727 | E27: Pass | F27: KDE00119
A28: Cannot be measured | B28: KDE00731 | E28: Pass | F28: KDE00120
A29: Cannot be measured | B29: KDE00734 | E29: Pass | F29: KDE00124
A30: Cannot be measured | B30: KDE00802
C31: Invalid Data | D31: KDE00408 | E31: Pass | F31: KDE00406
E32: Pass | F32: KDE00407
C33: Invalid Data | D33: KDE00410 | E33: Pass | F33: KDE00408
C34: Invalid Data | D34: KDE00413 | E34: Pass | F34: KDE00413
C35: Invalid Data | D35: KDE00723 | E35: Pass | F35: KDE00495
E36: Pass | F36: KDE00723
E37: Pass | F37: KDE00725
E38: Pass | F38: KDE00727
E39: Pass | F39: KDE00731

Sheet Temp
A1: Data Domain | B1: Status May | C1: Status March | D1: KDE | E1: Key Data Element (Thai) | F1: Key Data Element (English) | G1: Src Database | H1: Src Schema | I1: Src Table | J1: Src Column | K1: Business DQ Rules | L1: Prod_ProfilingResult | M1: key | N1: ValidPercentage as of 20260511 | O1: Prod_ThresholdStatus May | P1: Status | Q1: Jobname | R1: Status Test
A2: Customer | B2: Cannot be measured | C2: Cannot be measured | D2: KDE00001 | E2: หมายเลขโทรศัพท์มือถือของผู้เอาประกัน | F2: Policyholder Mobile Phone Number | G2: underwrite | H2: cunderwrite | I2: phone | J2: phoneno | K2: Validity | M2: KDE00001underwrite.cunderwrite.phone.phonenoValidityCustomer | O2: No Data Found | P2: No Result @PROD | Q2: m_MobilePhoneNumber_Validity_DS797 | R2: =VLOOKUP(M2,Sheet1!W:X,2,FALSE) -> PASS
A3: Customer | B3: Invalid Data | C3: Invalid Data | D3: KDE00001 | E3: หมายเลขโทรศัพท์มือถือของผู้เอาประกัน | F3: Policyholder Mobile Phone Number | G3: customer | H3: contact | I3: phone | J3: phone_number | K3: Completeness | L3: Contact EDM | M3: KDE00001customer.contact.phone.phone_numberCompletenessCustomer | N3: 99.999865 | O3: Fail - Invalid Data | R3: =VLOOKUP(M3,Sheet1!W:X,2,FALSE) -> PASS
A4: Customer | B4: Invalid Data | C4: Invalid Data | D4: KDE00001 | E4: หมายเลขโทรศัพท์มือถือของผู้เอาประกัน | F4: Policyholder Mobile Phone Number | G4: policy | H4: cbranch | I4: nbtelephone | J4: phoneno_m | K4: Completeness | L4: Contact EDM | M4: KDE00001policy.cbranch.nbtelephone.phoneno_mCompletenessCustomer | N4: 99.864205 | O4: Fail - Invalid Data | R4: =VLOOKUP(M4,Sheet1!W:X,2,FALSE) -> PASS
A5: Customer | B5: Invalid Data | C5: Invalid Data | D5: KDE00001 | E5: หมายเลขโทรศัพท์มือถือของผู้เอาประกัน | F5: Policyholder Mobile Phone Number | G5: claim | H5: cclaim | I5: tempreceipt | J5: phoneno | K5: Validity | L5: Contact EDM | M5: KDE00001claim.cclaim.tempreceipt.phonenoValidityCustomer | N5: 99.575071 | O5: Fail - Invalid Data | R5: =VLOOKUP(M5,Sheet1!W:X,2,FALSE) -> PASS
A6: Customer | B6: Invalid Data | C6: Invalid Data | D6: KDE00001 | E6: หมายเลขโทรศัพท์มือถือของผู้เอาประกัน | F6: Policyholder Mobile Phone Number | G6: customer | H6: contact | I6: phone | J6: phone_number | K6: Validity | L6: Contact EDM | M6: KDE00001customer.contact.phone.phone_numberValidityCustomer | N6: 84.664858 | O6: Fail - Invalid Data | R6: =VLOOKUP(M6,Sheet1!W:X,2,FALSE) -> Pass with Condition
A7: Customer | B7: Invalid Data | C7: Invalid Data | D7: KDE00001 | E7: หมายเลขโทรศัพท์มือถือของผู้เอาประกัน | F7: Policyholder Mobile Phone Number | G7: customer | H7: customer_account | I7: account | J7: mobile_no | K7: Validity | L7: Contact EDM | M7: KDE00001customer.customer_account.account.mobile_noValidityCustomer | N7: 99.999769 | O7: Fail - Invalid Data | R7: =VLOOKUP(M7,Sheet1!W:X,2,FALSE) -> Pass with Condition
A8: Customer | B8: Invalid Data | C8: Invalid Data | D8: KDE00001 | E8: หมายเลขโทรศัพท์มือถือของผู้เอาประกัน | F8: Policyholder Mobile Phone Number | G8: dfl | H8: dfl | I8: mcaapplications | J8: mobileno | K8: Validity | L8: Contact EDM | M8: KDE00001dfl.dfl.mcaapplications.mobilenoValidityCustomer | N8: 99.887396 | O8: Fail - Invalid Data | R8: =VLOOKUP(M8,Sheet1!W:X,2,FALSE) -> Pass with Condition
A9: Customer | B9: Invalid Data | C9: Invalid Data | D9: KDE00001 | E9: หมายเลขโทรศัพท์มือถือของผู้เอาประกัน | F9: Policyholder Mobile Phone Number | G9: group_life | H9: glife | I9: mobilephone | J9: mobilephone | K9: Validity | L9: Contact EDM | M9: KDE00001group_life.glife.mobilephone.mobilephoneValidityCustomer | N9: 99.916699 | O9: Fail - Invalid Data | R9: =VLOOKUP(M9,Sheet1!W:X,2,FALSE) -> PASS
A10: Customer | B10: Invalid Data | C10: Invalid Data | D10: KDE00001 | E10: หมายเลขโทรศัพท์มือถือของผู้เอาประกัน | F10: Policyholder Mobile Phone Number | G10: policy | H10: cbranch | I10: nbtelephone | J10: phoneno_m | K10: Validity | L10: Contact EDM | M10: KDE00001policy.cbranch.nbtelephone.phoneno_mValidityCustomer | N10: 99.650302 | O10: Fail - Invalid Data | R10: =VLOOKUP(M10,Sheet1!W:X,2,FALSE) -> PASS
A11: Customer | B11: Invalid Data | C11: Invalid Data | D11: KDE00001 | E11: หมายเลขโทรศัพท์มือถือของผู้เอาประกัน | F11: Policyholder Mobile Phone Number | G11: tlprompt | H11: public | I11: mcaapplications | J11: telno | K11: Validity | L11: Contact EDM | M11: KDE00001tlprompt.public.mcaapplications.telnoValidityCustomer | N11: 99.785672 | O11: Fail - Invalid Data | R11: =VLOOKUP(M11,Sheet1!W:X,2,FALSE) -> Pass with Condition
A12: Customer | B12: Invalid Data | C12: Invalid Data | D12: KDE00001 | E12: หมายเลขโทรศัพท์มือถือของผู้เอาประกัน | F12: Policyholder Mobile Phone Number | G12: underwrite | H12: cunderwrite | I12: dmmaster | J12: mobilephone | K12: Validity | L12: Contact EDM | M12: KDE00001underwrite.cunderwrite.dmmaster.mobilephoneValidityCustomer | N12: 99.931368 | O12: Fail - Invalid Data | R12: =VLOOKUP(M12,Sheet1!W:X,2,FALSE) -> PASS
A13: Customer | B13: Pass | C13: Pass | D13: KDE00001 | E13: หมายเลขโทรศัพท์มือถือของผู้เอาประกัน | F13: Policyholder Mobile Phone Number | G13: dfl | H13: dfl | I13: mcaapplications | J13: mobileno | K13: Completeness | M13: KDE00001dfl.dfl.mcaapplications.mobilenoCompletenessCustomer | N13: 100 | O13: Pass | R13: =VLOOKUP(M13,Sheet1!W:X,2,FALSE) -> PASS
A14: Customer | B14: Invalid Data | C14: Cannot be measured | D14: KDE00002 | E14: หมายเลขโทรศัพท์สถานทีทำงานของผู้เอาประกัน | F14: Policyholder Work address_Phone No | G14: tlprompt | H14: public | I14: address | J14: telno | K14: Validity | L14: Contact EDM | M14: KDE00002tlprompt.public.address.mobilenoValidityCustomer | N14: 99.896829 | O14: Fail - Invalid Data | R14: =VLOOKUP(M14,Sheet1!W:X,2,FALSE) -> PASS
A15: Customer | B15: Invalid Data | C15: Cannot be measured | D15: KDE00002 | E15: หมายเลขโทรศัพท์สถานทีทำงานของผู้เอาประกัน | F15: Policyholder Work address_Phone No | G15: tlprompt | H15: public | I15: address | J15: mobileno | K15: Validity | L15: Contact EDM | M15: KDE00002tlprompt.public.address.mobilenoValidityCustomer | N15: 99.896829 | O15: Fail - Invalid Data | R15: =VLOOKUP(M15,Sheet1!W:X,2,FALSE) -> PASS
A16: Customer | B16: Invalid Data | C16: Invalid Data | D16: KDE00002 | E16: หมายเลขโทรศัพท์สถานทีทำงานของผู้เอาประกัน | F16: Policyholder Work address_Phone No | G16: dfl | H16: dfl | I16: address | J16: mobileno | K16: Completeness | L16: Contact EDM | M16: KDE00002dfl.dfl.address.mobilenoCompletenessCustomer | N16: 99.978813 | O16: Fail - Invalid Data | R16: =VLOOKUP(M16,Sheet1!W:X,2,FALSE) -> PASS
A17: Customer | B17: Invalid Data | C17: Invalid Data | D17: KDE00002 | E17: หมายเลขโทรศัพท์สถานทีทำงานของผู้เอาประกัน | F17: Policyholder Work address_Phone No | G17: dfl | H17: dfl | I17: address | J17: mobileno | K17: Validity | L17: Contact EDM | M17: KDE00002dfl.dfl.address.mobilenoValidityCustomer | N17: 99.439123 | O17: Fail - Invalid Data | R17: =VLOOKUP(M17,Sheet1!W:X,2,FALSE) -> PASS
A18: Customer | B18: Invalid Data | C18: Invalid Data | D18: KDE00003 | E18: หมายเลขโทรศัพท์บ้านของผู้ขอเอาประกันภัย | F18: Policyholder Home Phone Number | G18: policy | H18: cbranch | I18: nbtelephone | J18: phoneno_h | K18: Completeness | L18: Contact EDM | M18: KDE00003policy.cbranch.nbtelephone.phoneno_hCompletenessCustomer | N18: 99.504138 | O18: Fail - Invalid Data | R18: =VLOOKUP(M18,Sheet1!W:X,2,FALSE) -> PASS
A19: Customer | B19: Invalid Data | C19: Invalid Data | D19: KDE00003 | E19: หมายเลขโทรศัพท์บ้านของผู้ขอเอาประกันภัย | F19: Policyholder Home Phone Number | G19: policy | H19: cbranch | I19: nbtelephone | J19: phoneno_h | K19: Validity | L19: Contact EDM | M19: KDE00003policy.cbranch.nbtelephone.phoneno_hValidityCustomer | N19: 79.907913 | O19: Fail - Invalid Data | R19: =VLOOKUP(M19,Sheet1!W:X,2,FALSE) -> PASS
A20: Customer | B20: Invalid Data | C20: Invalid Data | D20: KDE00004 | E20: เพศของผู้ขอเอาประกันภัย | F20: Policyholder Gender | G20: group_life | H20: glife | I20: g | J20: sex | K20: Completeness | L20: Contact EDM | M20: KDE00004group_life.glife.g.sexCompletenessCustomer | N20: 99.267112 | O20: Fail - Invalid Data | R20: =VLOOKUP(M20,Sheet1!W:X,2,FALSE) -> Pass with Condition
A21: Customer | B21: Invalid Data | C21: Invalid Data | D21: KDE00004 | E21: เพศของผู้ขอเอาประกันภัย | F21: Policyholder Gender | G21: policy | H21: mstperson | I21: person | J21: sex | K21: Completeness | L21: Contact EDM | M21: KDE00004policy.mstperson.person.sexCompletenessCustomer | N21: 99.999819 | O21: Fail - Invalid Data | R21: =VLOOKUP(M21,Sheet1!W:X,2,FALSE) -> PASS
A22: Customer | B22: Invalid Data | C22: Invalid Data | D22: KDE00004 | E22: เพศของผู้ขอเอาประกันภัย | F22: Policyholder Gender | G22: group_life | H22: glife | I22: g | J22: sex | K22: Integrity | L22: Contact EDM | M22: KDE00004group_life.glife.g.sexIntegrityCustomer | N22: 99.998159 | O22: Fail - Invalid Data | R22: =VLOOKUP(M22,Sheet1!W:X,2,FALSE) -> PASS
A23: Customer | B23: Invalid Data | C23: Invalid Data | D23: KDE00004 | E23: เพศของผู้ขอเอาประกันภัย | F23: Policyholder Gender | G23: policy | H23: mstperson | I23: person | J23: sex | K23: Integrity | L23: Contact EDM | M23: KDE00004policy.mstperson.person.sexIntegrityCustomer | N23: 99.999899 | O23: Fail - Invalid Data | R23: =VLOOKUP(M23,Sheet1!W:X,2,FALSE) -> PASS
A24: Customer | B24: Pass | C24: Pass | D24: KDE00004 | E24: เพศของผู้ขอเอาประกันภัย | F24: Policyholder Gender | G24: dfl | H24: dfl | I24: mcaapplications | J24: gender | K24: Completeness | M24: KDE00004dfl.dfl.mcaapplications.genderCompletenessCustomer | N24: 100 | O24: Pass | P24: No Result @PROD | Q24: m_PersonGenderCode_Logic_DS164 | R24: =VLOOKUP(M24,Sheet1!W:X,2,FALSE) -> Pass with Condition
A25: Customer | B25: Pass | C25: Pass | D25: KDE00004 | E25: เพศของผู้ขอเอาประกันภัย | F25: Policyholder Gender | G25: edw_month_end | H25: edw_month_end | I25: indfile | J25: sex | K25: Completeness | M25: KDE00004edw_month_end.edw_month_end.indfile.sexCompletenessCustomer | N25: 100 | O25: Pass | R25: =VLOOKUP(M25,Sheet1!W:X,2,FALSE) -> Pass with Condition
A26: Customer | B26: Pass | C26: Pass | D26: KDE00004 | E26: เพศของผู้ขอเอาประกันภัย | F26: Policyholder Gender | G26: edw_month_end | H26: edw_month_end | I26: ordfile | J26: sex | K26: Completeness | M26: KDE00004edw_month_end.edw_month_end.ordfile.sexCompletenessCustomer | N26: 100 | O26: Pass | R26: =VLOOKUP(M26,Sheet1!W:X,2,FALSE) -> Pass with Condition
A27: Customer | B27: Pass | C27: Pass | D27: KDE00004 | E27: เพศของผู้ขอเอาประกันภัย | F27: Policyholder Gender | G27: edw_month_end | H27: edw_month_end | I27: whlfile | J27: sex | K27: Completeness | M27: KDE00004edw_month_end.edw_month_end.whlfile.sexCompletenessCustomer | N27: 100 | O27: Pass | R27: =VLOOKUP(M27,Sheet1!W:X,2,FALSE) -> Pass with Condition
A28: Customer | B28: Pass | C28: Pass | D28: KDE00004 | E28: เพศของผู้ขอเอาประกันภัย | F28: Policyholder Gender | G28: policy | H28: cbranch | I28: nbinsured | J28: sex | K28: Completeness | M28: KDE00004policy.cbranch.nbinsured.sexCompletenessCustomer | N28: 100 | O28: Pass | R28: =VLOOKUP(M28,Sheet1!W:X,2,FALSE) -> Pass with Condition
A29: Customer | B29: Pass | C29: Pass | D29: KDE00004 | E29: เพศของผู้ขอเอาประกันภัย | F29: Policyholder Gender | G29: tlprompt | H29: public | I29: mcaapplications | J29: gender | K29: Completeness | M29: KDE00004tlprompt.public.mcaapplications.genderCompletenessCustomer | N29: 100 | O29: Pass | R29: =VLOOKUP(M29,Sheet1!W:X,2,FALSE) -> Pass with Condition
A30: Customer | B30: Pass | C30: Pass | D30: KDE00004 | E30: เพศของผู้ขอเอาประกันภัย | F30: Policyholder Gender | G30: underwrite | H30: cunderwrite | I30: appln | J30: sex | K30: Completeness | M30: KDE00004underwrite.cunderwrite.appln.sexCompletenessCustomer | N30: 100 | O30: Pass | R30: =VLOOKUP(M30,Sheet1!W:X,2,FALSE) -> Pass with Condition
A31: Customer | B31: Pass | C31: Pass | D31: KDE00004 | E31: เพศของผู้ขอเอาประกันภัย | F31: Policyholder Gender | G31: underwrite | H31: cunderwrite | I31: dmapplication | J31: sex | K31: Completeness | M31: KDE00004underwrite.cunderwrite.dmapplication.sexCompletenessCustomer | N31: 100 | O31: Pass | R31: =VLOOKUP(M31,Sheet1!W:X,2,FALSE) -> Pass with Condition
A32: Customer | B32: Pass | C32: Pass | D32: KDE00004 | E32: เพศของผู้ขอเอาประกันภัย | F32: Policyholder Gender | G32: dfl | H32: dfl | I32: mcaapplications | J32: gender | K32: Integrity | M32: KDE00004dfl.dfl.mcaapplications.genderIntegrityCustomer | N32: 100 | O32: Pass | R32: =VLOOKUP(M32,Sheet1!W:X,2,FALSE) -> Pass with Condition
A33: Customer | B33: Pass | C33: Pass | D33: KDE00004 | E33: เพศของผู้ขอเอาประกันภัย | F33: Policyholder Gender | G33: policy | H33: cbranch | I33: nbinsured | J33: sex | K33: Integrity | M33: KDE00004policy.cbranch.nbinsured.sexIntegrityCustomer | N33: 100 | O33: Pass | R33: =VLOOKUP(M33,Sheet1!W:X,2,FALSE) -> PASS
A34: Customer | B34: Pass | C34: Pass | D34: KDE00004 | E34: เพศของผู้ขอเอาประกันภัย | F34: Policyholder Gender | G34: tlprompt | H34: public | I34: mcaapplications | J34: gender | K34: Integrity | M34: KDE00004tlprompt.public.mcaapplications.genderIntegrityCustomer | N34: 100 | O34: Pass | R34: =VLOOKUP(M34,Sheet1!W:X,2,FALSE) -> PASS
A35: Customer | B35: Pass | C35: Pass | D35: KDE00004 | E35: เพศของผู้ขอเอาประกันภัย | F35: Policyholder Gender | G35: underwrite | H35: cunderwrite | I35: appln | J35: sex | K35: Integrity | M35: KDE00004underwrite.cunderwrite.appln.sexIntegrityCustomer | N35: 100 | O35: Pass | R35: =VLOOKUP(M35,Sheet1!W:X,2,FALSE) -> PASS
A36: Customer | B36: Pass | C36: Pass | D36: KDE00004 | E36: เพศของผู้ขอเอาประกันภัย | F36: Policyholder Gender | G36: underwrite | H36: cunderwrite | I36: dmapplication | J36: sex | K36: Integrity | M36: KDE00004underwrite.cunderwrite.dmapplication.sexIntegrityCustomer | N36: 100 | O36: Pass | R36: =VLOOKUP(M36,Sheet1!W:X,2,FALSE) -> PASS
A37: Customer | B37: Cannot be measured | C37: Cannot be measured | D37: KDE00005 | E37: เลขที่บัตรประชาชนของผู้รับมอบสิทธิ | F37: Assignee Identity Number | G37: pos | H37: srvservice | I37: delegatemast | J37: referenceid | K37: Completeness | M37: KDE00005pos.srvservice.delegatemast.referenceidCompletenessCustomer | P37: Cannot be measured | R37: =VLOOKUP(M37,Sheet1!W:X,2,FALSE) -> FIXED
A38: Customer | B38: Cannot be measured | C38: Cannot be measured | D38: KDE00005 | E38: เลขประจำตัวประชาชนของผู้ปกครอง คบ. | F38: KB's Identification Number | G38: tlprompt | H38: public | I38: kb | J38: identifyid | K38: Completeness | M38: KDE00005tlprompt.public.kb.identifyidCompletenessCustomer | P38: Cannot be measured | R38: =VLOOKUP(M38,Sheet1!W:X,2,FALSE) -> FIXED
A39: Customer | B39: Cannot be measured | C39: Cannot be measured | D39: KDE00005 | E39: เลขประจำตัวประชาชนของผู้เอาประกันภัย | F39: Policyholder Identification Number | G39: claim | H39: cclaim | I39: eclaimform | J39: citizenid | K39: Completeness | M39: KDE00005claim.cclaim.eclaimform.citizenidCompletenessCustomer | P39: Cannot be measured | R39: =VLOOKUP(M39,Sheet1!W:X,2,FALSE) -> FIXED
A40: Customer | B40: Cannot be measured | C40: Cannot be measured | D40: KDE00005 | E40: เลขประจำตัวประชาชนของผู้เอาประกันภัย | F40: Policyholder Identification Number | G40: common_db | H40: dbo | I40: tb_prospect | J40: citizen_id | K40: Completeness | M40: KDE00005common_db.dbo.tb_prospect.citizen_idCompletenessCustomer | P40: Cannot be measured | R40: =VLOOKUP(M40,Sheet1!W:X,2,FALSE) -> FIXED
A41: Customer | B41: Cannot be measured | C41: Cannot be measured | D41: KDE00005 | E41: เลขประจำตัวประชาชนของผู้เอาประกันภัย | F41: Policyholder Identification Number | G41: customer | H41: party | I41: party | J41: govt_id | K41: Completeness | M41: KDE00005customer.party.party.govt_idCompletenessCustomer | P41: Cannot be measured | R41: =VLOOKUP(M41,Sheet1!W:X,2,FALSE) -> FIXED
A42: Customer | B42: Cannot be measured | C42: Cannot be measured | D42: KDE00005 | E42: เลขประจำตัวประชาชนของผู้เอาประกันภัย | F42: Policyholder Identification Number | G42: dfl | H42: dfl | I42: mcaapplications | J42: identifyid | K42: Completeness | M42: KDE00005dfl.dfl.mcaapplications.identifyidCompletenessCustomer | P42: Cannot be measured | R42: =VLOOKUP(M42,Sheet1!W:X,2,FALSE) -> FIXED
A43: Customer | B43: Cannot be measured | C43: Cannot be measured | D43: KDE00005 | E43: เลขประจำตัวประชาชนของผู้เอาประกันภัย | F43: Policyholder Identification Number | G43: group_life | H43: glife | I43: citizenid | J43: referenceid | K43: Completeness | M43: KDE00005group_life.glife.citizenid.referenceidCompletenessCustomer | P43: Cannot be measured | R43: =VLOOKUP(M43,Sheet1!W:X,2,FALSE) -> FIXED
A44: Customer | B44: Cannot be measured | C44: Cannot be measured | D44: KDE00005 | E44: เลขประจำตัวประชาชนของผู้เอาประกันภัย | F44: Policyholder Identification Number | G44: policy | H44: mstperson | I44: person | J44: referenceid | K44: Completeness | M44: KDE00005policy.mstperson.person.referenceidCompletenessCustomer | P44: Cannot be measured | R44: =VLOOKUP(M44,Sheet1!W:X,2,FALSE) -> FIXED
A45: Customer | B45: Cannot be measured | C45: Cannot be measured | D45: KDE00005 | E45: เลขประจำตัวประชาชนของผู้เอาประกันภัย | F45: Policyholder Identification Number | G45: policy | H45: universal | I45: partialwithdraw | J45: referenceid | K45: Completeness | M45: KDE00005policy.universal.partialwithdraw.referenceidCompletenessCustomer | P45: Cannot be measured | R45: =VLOOKUP(M45,Sheet1!W:X,2,FALSE) -> FIXED
A46: Customer | B46: Cannot be measured | C46: Cannot be measured | D46: KDE00005 | E46: เลขประจำตัวประชาชนของผู้เอาประกันภัย | F46: Policyholder Identification Number | G46: pos | H46: srvservice | I46: dvtran | J46: referenceid | K46: Completeness | M46: KDE00005pos.srvservice.dvtran.referenceidCompletenessCustomer | P46: Cannot be measured | R46: =VLOOKUP(M46,Sheet1!W:X,2,FALSE) -> FIXED
A47: Customer | B47: Cannot be measured | C47: Cannot be measured | D47: KDE00005 | E47: เลขประจำตัวประชาชนของผู้เอาประกันภัย | F47: Policyholder Identification Number | G47: tlprompt | H47: public | I47: mcaapplications | J47: identifyid | K47: Completeness | M47: KDE00005tlprompt.public.mcaapplications.identifyidCompletenessCustomer | P47: Cannot be measured | R47: =VLOOKUP(M47,Sheet1!W:X,2,FALSE) -> FIXED
A48: Customer | B48: Cannot be measured | C48: Cannot be measured | D48: KDE00005 | E48: เลขประจำตัวประชาชนของผู้เอาประกันภัย | F48: Policyholder Identification Number | G48: underwrite | H48: cunderwrite | I48: appln | J48: idno | K48: Completeness | M48: KDE00005underwrite.cunderwrite.appln.idnoCompletenessCustomer | P48: Cannot be measured | R48: =VLOOKUP(M48,Sheet1!W:X,2,FALSE) -> FIXED
... A71: Customer | B71: Cannot be measured | C71: Cannot be measured | D71: KDE00007 | E71: เลขประจำตัวผู้เสียภาษีอากร | F71: Taxpayer identification number | G71: group_life | H71: glife | I71: engcompany | J71: regisnumber | K71: Completeness | M71: KDE00007group_life.glife.engcompany.regisnumberCompletenessCustomer | P71: Cannot be measured | R71: =VLOOKUP(M71,Sheet1!W:X,2,FALSE) -> FIXED
A72: Customer | B72: Cannot be measured | C72: Cannot be measured | D72: KDE00007 | E72: เลขประจำตัวผู้เสียภาษีอากร | F72: Taxpayer identification number | G72: tlprompt | H72: public | I72: payment | J72: personidtax | K72: Completeness | M72: KDE00007tlprompt.public.payment.personidtaxCompletenessCustomer | N72: 0.30818099 | O72: Fail - Invalid Rules | R72: =VLOOKUP(M72,Sheet1!W:X,2,FALSE) -> PASS
A73: Customer | B73: Cannot be measured | C73: Cannot be measured | D73: KDE00007 | E73: เลขประจำตัวผู้เสียภาษีอากร | F73: Taxpayer identification number | G73: group_life | H73: glife | I73: engcompany | J73: regisnumber | K73: Validity | M73: KDE00007group_life.glife.engcompany.regisnumberValidityCustomer | P73: Cannot be measured | R73: =VLOOKUP(M73,Sheet1!W:X,2,FALSE) -> FIXED
A74: Customer | B74: Cannot be measured | C74: Cannot be measured | D74: KDE00007 | E74: เลขประจำตัวผู้เสียภาษีอากร | F74: Taxpayer identification number | G74: policy | H74: cbranch | I74: nbnewappfield | J74: taxid | K74: Validity | M74: KDE00007policy.cbranch.nbnewappfield.taxidValidityCustomer | P74: Cannot be measured | R74: =VLOOKUP(M74,Sheet1!W:X,2,FALSE) -> NOT PASS
A75: Customer | B75: Cannot be measured | C75: Cannot be measured | D75: KDE00007 | E75: เลขประจำตัวผู้เสียภาษีอากร | F75: Taxpayer identification number | G75: pos | H75: newservice | I75: consent | J75: referenceid | K75: Validity | M75: KDE00007pos.newservice.consent.referenceidValidityCustomer | P75: Cannot be measured | R75: =VLOOKUP(M75,Sheet1!W:X,2,FALSE) -> NOT PASS
A76: Customer | B76: Cannot be measured | C76: Cannot be measured | D76: KDE00007 | E76: เลขประจำตัวผู้เสียภาษีอากร | F76: Taxpayer identification number | G76: tlprompt | H76: public | I76: payment | J76: personidtax | K76: Validity | M76: KDE00007tlprompt.public.payment.personidtaxValidityCustomer | P76: Cannot be measured | R76: =VLOOKUP(M76,Sheet1!W:X,2,FALSE) -> FIXED
A77: Customer | B77: Pass | C77: Pass | D77: KDE00007 | E77: เลขประจำตัวผู้เสียภาษีอากร | F77: Taxpayer identification number | G77: pos | H77: newservice | I77: consent | J77: referenceid | K77: Completeness | M77: KDE00007pos.newservice.consent.referenceidCompletenessCustomer | N77: 100 | O77: Pass | R77: =VLOOKUP(M77,Sheet1!W:X,2,FALSE) -> PASS
A78: Customer | B78: Pass | C78: Cannot be measured | D78: KDE00008 | E78: เลขที่หนังสือเดินทางของผู้ขอเอาประกัน | F78: Policyholder Passport No. | G78: group_life | H78: glife | I78: passportid | J78: passportid | K78: Completeness | M78: KDE00008group_life.glife.passportid.passportidCompletenessCustomer | N78: 100 | O78: Pass | R78: =VLOOKUP(M78,Sheet1!W:X,2,FALSE) -> PASS
A79: Customer | B79: Cannot be measured | C79: Cannot be measured | D79: KDE00008 | E79: เลขที่หนังสือเดินทางของผู้ขอเอาประกัน | F79: Policyholder Passport No. | G79: tlprompt | H79: public | I79: prospect | J79: passport | K79: Completeness | M79: KDE00008tlprompt.public.prospect.passportCompletenessCustomer | N79: 0.59179662 | O79: Fail - Invalid Rules | R79: =VLOOKUP(M79,Sheet1!W:X,2,FALSE) -> PASS
A80: Customer | B80: Pass | C80: Pass | D80: KDE00009 | E80: ประเภทเอกสารแสดงตัวบุคคล | F80: Type of identity document | G80: dfl | H80: dfl | I80: mcaapplications | J80: identifytype | K80: Completeness | M80: KDE00009dfl.dfl.mcaapplications.identifytypeCompletenessCustomer | N80: 100 | O80: Pass | R80: =VLOOKUP(M80,Sheet1!W:X,2,FALSE) -> Pass with Condition
A81: Customer | B81: Pass | C81: Pass | D81: KDE00009 | E81: ประเภทเอกสารแสดงตัวบุคคล | F81: Type of identity document | G81: tlprompt | H81: public | I81: mcaapplications | J81: identifytype | K81: Completeness | M81: KDE00009tlprompt.public.mcaapplications.identifytypeCompletenessCustomer | N81: 100 | O81: Pass | R81: =VLOOKUP(M81,Sheet1!W:X,2,FALSE) -> Pass with Condition
A82: Customer | B82: Pass | C82: Pass | D82: KDE00009 | E82: ประเภทเอกสารแสดงตัวบุคคล | F82: Type of identity document | G82: underwrite | H82: cunderwrite | I82: appln | J82: cardtype | K82: Completeness | M82: KDE00009underwrite.cunderwrite.appln.cardtypeCompletenessCustomer | N82: 100 | O82: Pass | R82: =VLOOKUP(M82,Sheet1!W:X,2,FALSE) -> Pass with Condition
A83: Customer | B83: Invalid Data | C83: Invalid Data | D83: KDE00010 | E83: หมายเลขโทรศัพท์มือถือผู้ปกครอง/ผู้ชำระเบี้ย | F83: Parent/Payer's Mobile Phone Number | G83: dm_db | H83: dbo | I83: l_payment | J83: phone_no | K83: Validity | L83: Contact EDM | M83: KDE00010dm_db.dbo.l_payment.phone_noValidityCustomer | N83: 79.070305 | O83: Fail - Invalid Data | R83: =VLOOKUP(M83,Sheet1!W:X,2,FALSE) -> PASS
A84: Customer | B84: Invalid Data | C84: Invalid Data | D84: KDE00011 | E84: ความสัมพันธ์ของผู้รับประโยชน์ | F84: Relationship of Beneficiary | G84: policy | H84: cbranch | I84: nbbeneficiary | J84: relationshipcode | K84: Completeness | L84: Contact EDM | M84: KDE00011policy.cbranch.nbbeneficiary.relationshipcodeCompletenessCustomer | N84: 99.999962 | O84: Fail - Invalid Data | R84: =VLOOKUP(M84,Sheet1!W:X,2,FALSE) -> PASS
A85: Customer | B85: Invalid Data | C85: Invalid Data | D85: KDE00011 | E85: ความสัมพันธ์ของผู้รับประโยชน์ | F85: Relationship of Beneficiary | G85: policy | H85: mstperson | I85: beneficiary | J85: relationshipcode | K85: Integrity | L85: Contact EDM | M85: KDE00011policy.mstperson.beneficiary.relationshipcodeIntegrityCustomer | N85: 99.971309 | O85: Fail - Invalid Data | R85: =VLOOKUP(M85,Sheet1!W:X,2,FALSE) -> PASS
A86: Customer | B86: Pass | C86: Pass | D86: KDE00011 | E86: ความสัมพันธ์ของผู้รับประโยชน์ | F86: Relationship of Beneficiary | G86: policy | H86: mstperson | I86: beneficiary | J86: relationshipcode | K86: Completeness | M86: KDE00011policy.mstperson.beneficiary.relationshipcodeCompletenessCustomer | N86: 100 | O86: Pass | R86: =VLOOKUP(M86,Sheet1!W:X,2,FALSE) -> PASS
A87: Customer | B87: Invalid Data | C87: Pass | D87: KDE00011 | E87: ความสัมพันธ์ของผู้รับประโยชน์ | F87: Relationship of Beneficiary | G87: policy | H87: cbranch | I87: nbbeneficiary | J87: relationshipcode | K87: Integrity | L87: Contact EDM | M87: KDE00011policy.cbranch.nbbeneficiary.relationshipcodeIntegrityCustomer | N87: 99.93671 | O87: Fail - Invalid Data | R87: =VLOOKUP(M87,Sheet1!W:X,2,FALSE) -> PASS
A88: Customer | B88: Cannot be measured | C88: Cannot be measured | D88: KDE00014 | E88: คำนำหน้าชื่อของผู้ขอเอาประกัน | F88: Applicant's Title | G88: policy | H88: mstperson | I88: name | J88: prename | K88: Integrity | M88: KDE00014policy.mstperson.name.prenameIntegrityCustomer | P88: Cannot be measured | R88: =VLOOKUP(M88,Sheet1!W:X,2,FALSE) -> NOT PASS
A89: Customer | B89: Invalid Data | C89: Invalid Data | D89: KDE00014 | E89: คำนำหน้าชื่อของผู้ขอเอาประกัน | F89: Applicant's Title | G89: customer | H89: common_refund | I89: customers_refund | J89: prename | K89: Integrity | L89: Contact EDM | M89: KDE00014customer.common_refund.customers_refund.prenameIntegrityCustomer | N89: 99.998945 | O89: Fail - Invalid Data | R89: =VLOOKUP(M89,Sheet1!W:X,2,FALSE) -> PASS
A90: Customer | B90: Invalid Data | C90: Cannot be measured | D90: KDE00016 | E90: ชื่อ-นามสกุล ของผู้ขอเอาประกัน | F90: Applicant Name-Surname | G90: group_life | H90: glife | I90: g | J90: fname,lname | K90: Completeness | L90: Contact EDM | M90: KDE00016group_life.glife.g.PersonNameCompletenessCustomer | N90: 99.947261 | O90: Fail - Invalid Data | R90: =VLOOKUP(M90,Sheet1!W:X,2,FALSE) -> PASS
A91: Customer | B91: Cannot be measured | C91: Cannot be measured | D91: KDE00016 | E91: ชื่อ-นามสกุล ของผู้เอาประกัน | F91: Policyholder Name-Surname | G91: dm_db | H91: dbo | I91: l_serv_master | J91: first_name,last_name | K91: Completeness | M91: KDE00016dm_db.dbo.l_serv_master.firstnameCompletenessCustomer | O91: No Data Found | P91: No Result @PROD | Q91: m_PersonName_Completeness_ENT904 | R91: =VLOOKUP(M91,Sheet1!W:X,2,FALSE) -> Pass with Condition
A92: Customer | B92: Cannot be measured | C92: Cannot be measured | D92: KDE00016 | E92: ชื่อ-นามสกุล ของผู้เอาประกัน | F92: Policyholder Name-Surname | G92: dm_db | H92: dbo | I92: tb_dmmast | J92: firstname,lastname | K92: Completeness | M92: KDE00016dm_db.dbo.tb_dmmast.firstnameCompletenessCustomer | O92: No Data Found | P92: No Result @PROD | Q92: m_PersonName_Completeness_ENT1159 | R92: =VLOOKUP(M92,Sheet1!W:X,2,FALSE) -> Pass with Condition
A93: Customer | B93: Pass | C93: Cannot be measured | D93: KDE00016 | E93: ชื่อ-นามสกุล ของผู้เอาประกัน | F93: Policyholder Name-Surname | G93: underwrite | H93: cunderwrite | I93: dmapplication | J93: firstname,lastname | K93: Completeness | M93: KDE00016underwrite.cunderwrite.dmapplication.CustomerNameCompletenessCustomer | N93: 100 | O93: Pass | R93: =VLOOKUP(M93,Sheet1!W:X,2,FALSE) -> Pass with Condition
A94: Customer | B94: Cannot be measured | C94: Cannot be measured | D94: KDE00016 | E94: ชื่อ-นามสกุล ของผู้ขอเอาประกัน | F94: Applicant Name-Surname | G94: customer | H94: common_refund | I94: customers_refund | J94: firstname,lastname | K94: Validity | M94: KDE00016customer.common_refund.customers_refund.PersonNameValidityCustomer | R94: =VLOOKUP(M94,Sheet1!W:X,2,FALSE) -> FIXED
A95: Customer | B95: Cannot be measured | C95: Cannot be measured | D95: KDE00016 | E95: ชื่อ-นามสกุล ของผู้ขอเอาประกัน | F95: Applicant Name-Surname | G95: customer | H95: party | I95: person | J95: fname_th,lname_th | K95: Validity | M95: KDE00016customer.party.person.fname_thValidityCustomer | R95: =VLOOKUP(M95,Sheet1!W:X,2,FALSE) -> NOT PASS
A96: Customer | B96: Cannot be measured | C96: Cannot be measured | D96: KDE00016 | E96: ชื่อ-นามสกุล ของผู้ขอเอาประกัน | F96: Applicant Name-Surname | G96: dfl | H96: dfl | I96: mcaapplications | J96: name,lastname | K96: Validity | M96: KDE00016dfl.dfl.mcaapplications.PersonNameValidityCustomer | R96: =VLOOKUP(M96,Sheet1!W:X,2,FALSE) -> NOT PASS
A97: Customer | B97: Cannot be measured | C97: Cannot be measured | D97: KDE00016 | E97: ชื่อ-นามสกุล ของผู้ขอเอาประกัน | F97: Applicant Name-Surname | G97: finance_acc | H97: accountbranch | I97: paymentmst | J97: firstname,lastname | K97: Validity | M97: KDE00016finance_acc.accountbranch.paymentmst.PersonNameValidityCustomer | R97: =VLOOKUP(M97,Sheet1!W:X,2,FALSE) -> FIXED
A98: Customer | B98: Cannot be measured | C98: Cannot be measured | D98: KDE00016 | E98: ชื่อ-นามสกุล ของผู้ขอเอาประกัน | F98: Applicant Name-Surname | G98: group_life | H98: glife | I98: g | J98: fname,lname | K98: Validity | M98: KDE00016group_life.glife.g.PersonNameValidityCustomer | R98: =VLOOKUP(M98,Sheet1!W:X,2,FALSE) -> NOT PASS
A99: Customer | B99: Cannot be measured | C99: Cannot be measured | D99: KDE00016 | E99: ชื่อ-นามสกุล ของผู้ขอเอาประกัน | F99: Applicant Name-Surname | G99: policy | H99: mstperson | I99: name | J99: firstname,lastname | K99: Validity | M99: KDE00016policy.mstperson.name.PersonNameValidityCustomer | R99: =VLOOKUP(M99,Sheet1!W:X,2,FALSE) -> FIXED
A100: Customer | B100: Cannot be measured | C100: Cannot be measured | D100: KDE00016 | E100: ชื่อ-นามสกุล ของผู้ขอเอาประกัน | F100: Applicant Name-Surname | G100: tlprompt | H100: public | I100: mcaapplications | J100: name,lastname | K100: Validity | M100: KDE00016tlprompt.public.mcaapplications.PersonNameValidityCustomer | R100: =VLOOKUP(M100,Sheet1!W:X,2,FALSE) -> FIXED
A101: Customer | B101: Cannot be measured | C101: Cannot be measured | D101: KDE00016 | E101: ชื่อ-นามสกุล ของผู้ขอเอาประกัน | F101: Applicant Name-Surname | G101: underwrite | H101: cunderwrite | I101: appln | J101: firstname,lastname | K101: Validity | M101: KDE00016underwrite.cunderwrite.appln.PersonNameValidityCustomer | R101: =VLOOKUP(M101,Sheet1!W:X,2,FALSE) -> FIXED
A102: Customer | B102: Cannot be measured | C102: Cannot be measured | D102: KDE00016 | E102: ชื่อ-นามสกุล ของผู้เอาประกัน | F102: Policyholder Name-Surname | G102: claim | H102: cclaim | I102: namindi | J102: firstname,lastname | K102: Validity | M102: KDE00016claim.cclaim.namindi.PersonNameValidityCustomer | R102: =VLOOKUP(M102,Sheet1!W:X,2,FALSE) -> FIXED
A103: Customer | B103: Cannot be measured | C103: Cannot be measured | D103: KDE00016 | E103: ชื่อ-นามสกุล ของผู้เอาประกัน | F103: Policyholder Name-Surname | G103: claim | H103: cclaim | I103: namordo | J103: firstname,lastname | K103: Validity | M103: KDE00016claim.cclaim.namordo.PersonNameValidityCustomer | R103: =VLOOKUP(M103,Sheet1!W:X,2,FALSE) -> FIXED
A104: Customer | B104: Cannot be measured | C104: Cannot be measured | D104: KDE00016 | E104: ชื่อ-นามสกุล ของผู้เอาประกัน | F104: Policyholder Name-Surname | G104: claim | H104: claimback | I104: extendage | J104: firstname,lastname | K104: Validity | M104: KDE00016claim.claimback.extendage.PersonNameValidityCustomer | R104: =VLOOKUP(M104,Sheet1!W:X,2,FALSE) -> FIXED
A105: Customer | B105: Cannot be measured | C105: Cannot be measured | D105: KDE00016 | E105: ชื่อ-นามสกุล ของผู้เอาประกัน | F105: Policyholder Name-Surname | G105: dm_db | H105: dbo | I105: l_serv_master | J105: first_name,last_name | K105: Validity | M105: KDE00016dm_db.dbo.l_serv_master.PersonNameValidityCustomer | P105: Cannot be measured | R105: =VLOOKUP(M105,Sheet1!W:X,2,FALSE) -> FIXED
A106: Customer | B106: Cannot be measured | C106: Cannot be measured | D106: KDE00016 | E106: ชื่อ-นามสกุล ของผู้เอาประกัน | F106: Policyholder Name-Surname | G106: dm_db | H106: dbo | I106: tb_dmmast | J106: firstname,lastname | K106: Validity | M106: KDE00016dm_db.dbo.tb_dmmast.PersonNameValidityCustomer | P106: Cannot be measured | R106: =VLOOKUP(M106,Sheet1!W:X,2,FALSE) -> FIXED
A107: Customer | B107: Cannot be measured | C107: Cannot be measured | D107: KDE00016 | E107: ชื่อ-นามสกุล ของผู้เอาประกัน | F107: Policyholder Name-Surname | G107: underwrite | H107: cunderwrite | I107: dmapplication | J107: firstname,lastname | K107: Validity | M107: KDE00016underwrite.cunderwrite.dmapplication.PersonNameValidityCustomer | R107: =VLOOKUP(M107,Sheet1!W:X,2,FALSE) -> FIXED
A108: Customer | B108: Cannot be measured | C108: Cannot be measured | D108: KDE00016 | E108: ชื่อ-นามสกุล ของผู้มอบอำนาจ | F108: Authorized Person Name-Surname | G108: group_life | H108: glife | I108: policy_peopleref | J108: tfirstname,tlastname | K108: Validity | M108: KDE00016group_life.glife.policy_peopleref.PersonNameValidityCustomer | R108: =VLOOKUP(M108,Sheet1!W:X,2,FALSE) -> FIXED
A109: Customer | B109: Cannot be measured | C109: Cannot be measured | D109: KDE00016 | E109: ชื่อ-นามสกุล ของผู้มอบอำนาจ | F109: Authorized Person Name-Surname | G109: group_life | H109: glife | I109: policy_peopleref | J109: tfirstname,tlastname | K109: Completeness | M109: KDE00016group_life.glife.policy_peopleref.CustomerNameCompletenessCustomer | N109: 45.75091 | O109: Fail - Further Investigation | R109: =VLOOKUP(M109,Sheet1!W:X,2,FALSE) -> Pass with Condition
A110: Customer | B110: Cannot be measured | C110: Cannot be measured | D110: KDE00016 | E110: ชื่อ-นามสกุล ของผู้เอาประกัน | F110: Policyholder Name-Surname | G110: claim | H110: cclaim | I110: eclaimform | J110: firstname,lastname | K110: Validity | M110: KDE00016claim.cclaim.eclaimform.PersonNameValidityCustomer | R110: =VLOOKUP(M110,Sheet1!W:X,2,FALSE) -> FIXED
A111: Customer | B111: Cannot be measured | C111: Cannot be measured | D111: KDE00016 | E111: ชื่อ-นามสกุล ของผู้เอาประกัน | F111: Policyholder Name-Surname | G111: underwrite | H111: cunderwrite | I111: name | J111: firstname,lastname | K111: Completeness | M111: KDE00016underwrite.cunderwrite.name.firstnameCompletenessCustomer | P111: Cannot be measured | R111: =VLOOKUP(M111,Sheet1!W:X,2,FALSE) -> NOT PASS
A112: Customer | B112: Cannot be measured | C112: Cannot be measured | D112: KDE00016 | E112: ชื่อ-นามสกุล ของผู้เอาประกัน | F112: Policyholder Name-Surname | G112: underwrite | H112: cunderwrite | I112: name | J112: firstname,lastname | K112: Validity | M112: KDE00016underwrite.cunderwrite.name.PersonNameValidityCustomer | P112: Cannot be measured | R112: =VLOOKUP(M112,Sheet1!W:X,2,FALSE) -> NOT PASS
A113: Customer | B113: Invalid Data | C113: Invalid Data | D113: KDE00016 | E113: ชื่อ-นามสกุล ของผู้ขอเอาประกัน | F113: Applicant Name-Surname | G113: customer | H113: party | I113: person | J113: fname_th,lname_th | K113: Completeness | L113: Contact EDM | M113: KDE00016customer.party.person.CustomerNameCompletenessCustomer | N113: 99.92959 | O113: Fail - Invalid Data | R113: =VLOOKUP(M113,Sheet1!W:X,2,FALSE) -> Pass with Condition
A114: Customer | B114: Invalid Data | C114: Invalid Data | D114: KDE00016 | E114: ชื่อ-นามสกุล ของผู้ขอเอาประกัน | F114: Applicant Name-Surname | G114: dfl | H114: dfl | I114: mcaapplications | J114: name,lastname | K114: Completeness | L114: Contact EDM | M114: KDE00016dfl.dfl.mcaapplications.ApplicantNameCompletenessCustomer | N114: 99.997552 | O114: Fail - Invalid Data | R114: =VLOOKUP(M114,Sheet1!W:X,2,FALSE) -> Pass with Condition
A115: Customer | B115: Invalid Data | C115: Invalid Data | D115: KDE00016 | E115: ชื่อ-นามสกุล ของผู้ขอเอาประกัน | F115: Applicant Name-Surname | G115: finance_acc | H115: accountbranch | I115: paymentmst | J115: firstname,lastname | K115: Completeness | L115: Contact EDM | M115: KDE00016finance_acc.accountbranch.paymentmst.CustomerNameCompletenessCustomer | N115: 99.633752 | O115: Fail - Invalid Data | R115: =VLOOKUP(M115,Sheet1!W:X,2,FALSE) -> Pass with Condition
A116: Customer | B116: Invalid Data | C116: Invalid Data | D116: KDE00016 | E116: ชื่อ-นามสกุล ของผู้ขอเอาประกัน | F116: Applicant Name-Surname | G116: policy | H116: mstperson | I116: name | J116: firstname,lastname | K116: Completeness | L116: Contact EDM | M116: KDE00016policy.mstperson.name.firstnameCompletenessCustomer | N116: 99.918602 | O116: Fail - Invalid Data | R116: =VLOOKUP(M116,Sheet1!W:X,2,FALSE) -> Pass with Condition
A117: Customer | B117: Invalid Data | C117: Invalid Data | D117: KDE00016 | E117: ชื่อ-นามสกุล ของผู้ขอเอาประกัน | F117: Applicant Name-Surname | G117: underwrite | H117: cunderwrite | I117: appln | J117: firstname,lastname | K117: Completeness | L117: Contact EDM | M117: KDE00016underwrite.cunderwrite.appln.CustomerNameCompletenessCustomer | N117: 99.871592 | O117: Fail - Invalid Data | R117: =VLOOKUP(M117,Sheet1!W:X,2,FALSE) -> Pass with Condition
A118: Customer | B118: Invalid Data | C118: Invalid Data | D118: KDE00016 | E118: ชื่อ-นามสกุล ของผู้เอาประกัน | F118: Policyholder Name-Surname | G118: claim | H118: cclaim | I118: namordo | J118: firstname,lastname | K118: Completeness | L118: Contact EDM | M118: KDE00016claim.cclaim.namordo.CustomerNameCompletenessCustomer | N118: 99.971371 | O118: Fail - Invalid Data | R118: =VLOOKUP(M118,Sheet1!W:X,2,FALSE) -> Pass with Condition
A119: Customer | B119: Pass | C119: Invalid Data | D119: KDE00016 | E119: ชื่อ-นามสกุล ของผู้เอาประกัน | F119: Policyholder Name-Surname | G119: claim | H119: claimback | I119: extendage | J119: firstname,lastname | K119: Completeness | M119: KDE00016claim.claimback.extendage.CustomerNameCompletenessCustomer | N119: 100 | O119: Pass | R119: =VLOOKUP(M119,Sheet1!W:X,2,FALSE) -> Pass with Condition
A120: Customer | B120: Pass | C120: Pass | D120: KDE00016 | E120: ชื่อ-นามสกุล ของผู้ขอเอาประกัน | F120: Applicant Name-Surname | G120: customer | H120: common_refund | I120: customers_refund | J120: firstname,lastname | K120: Completeness | M120: KDE00016customer.common_refund.customers_refund.ApplicantNameCompletenessCustomer | N120: 100 | O120: Pass | R120: =VLOOKUP(M120,Sheet1!W:X,2,FALSE) -> Pass with Condition
A121: Customer | B121: Pass | C121: Pass | D121: KDE00016 | E121: ชื่อ-นามสกุล ของผู้ขอเอาประกัน | F121: Applicant Name-Surname | G121: tlprompt | H121: public | I121: mcaapplications | J121: name,lastname | K121: Completeness | M121: KDE00016tlprompt.public.mcaapplications.CustomerNameCompletenessCustomer | N121: 100 | O121: Pass | R121: =VLOOKUP(M121,Sheet1!W:X,2,FALSE) -> Pass with Condition
A122: Customer | B122: Pass | C122: Pass | D122: KDE00016 | E122: ชื่อ-นามสกุล ของผู้เอาประกัน | F122: Policyholder Name-Surname | G122: claim | H122: cclaim | I122: namindi | J122: firstname,lastname | K122: Completeness | M122: KDE00016claim.cclaim.namindi.CustomerNameCompletenessCustomer | N122: 100 | O122: Pass | R122: =VLOOKUP(M122,Sheet1!W:X,2,FALSE) -> Pass with Condition
...

Sheet Sheet2
A1: KDE00001
A2: KDE00002 | I2: Total KDE | J2: 191 | N2: Status May | O2: Count of KDE | P2: countIF
A3: KDE00003 | I3: Remaining KDE | J3: 76 | N3: Cannot be measured | O3: 215 | P3: 75
A4: KDE00004 | I4: Completed | J4: =J2-J3 -> 115 | N4: Invalid Data | O4: 163 | P4: 75
A5: KDE00005 | N5: Pass | O5: 491 | P5: 137
A6: KDE00007 | N6: (blank) | O6: 1 | P6: 1
A7: KDE00008 | O7: =SUM(O3:O6) -> 870 | P7: =SUM(P3:P6) -> 288
A8: KDE00009
A9: KDE00010
A10: KDE00011 | H10: KDE 142 KDEs
A11: KDE00014
A12: KDE00016
A13: KDE00018
A14: KDE00025
A15: KDE00026
A16: KDE00027
A17: KDE00030
A18: KDE00040
A19: KDE00045
A20: KDE00046
A21: KDE00054
A22: KDE00058
... A190: KDE00867

Sheet result
A1: MeasurementID | B1: key | C1: ElementName | D1: DataField | E1: KDENumber | F1: DataDomain | G1: Dimension | H1: TestedRows | I1: AnomalyRows | J1: ValidRows | K1: ValidPercentage | L1: Threshold | M1: ThresholdStatus | N1: Jobname | O1: UpdatedbyUser | P1: LastUpdated
A2: 00DD5D67-0516-4B6F-8F6A-37B4E30AA566 | B2: KDE00358policy.cbranch.nbrider.statusIntegrityInsurance/Policy | C2: RiderStatusCode | D2: policy.cbranch.nbrider.status | E2: KDE00358 | F2: Insurance/Policy | G2: Integrity | H2: 40386720 | I2: 0 | J2: 40386720 | K2: 100 | L2: 100 | M2: Pass | N2: m_RiderStatusCode_Integrity_DS540 | O2: LDAP_TLI_EDW\sarinyarat | P2: 46153.588
A3: 0118BD48-711B-49BD-9C9E-BA5C0C0624DA | B3: KDE00063policy.cbranch.tmpover.srngnoValidityInsurance/Policy | C3: PremiumPaymentSubmissionNumber | D3: policy.cbranch.tmpover.srngno | E3: KDE00063 | F3: Insurance/Policy | G3: Validity | H3: 13081579 | I3: 0 | J3: 13081579 | K3: 100 | L3: 100 | M3: Pass | N3: m_PremiumPaymentSubmissionNumber_Validity_DS380 | O3: LDAP_TLI_EDW\sarinyarat | P3: 46153.579
A4: 012186E3-7F95-4E0B-AE74-F864C566DE73 | B4: KDE00003policy.cbranch.nbtelephone.phoneno_hCompletenessCustomer | C4: HomePhoneNumber | D4: policy.cbranch.nbtelephone.phoneno | E4: KDE00003 | F4: Customer | G4: Completeness | H4: 196224 | I4: 973 | J4: 195251 | K4: 99.504138 | L4: 100 | M4: Fail | N4: m_HomePhoneNumber_Completeness_DS1185 | O4: LDAP_TLI_EDW\sarinyarat | P4: 46153.584
A5: 0141FBB1-267D-4B9A-A09E-9D3F7931F3FF | B5: KDE00244policy.mstpolicy.indmast.policynoCompletenessInsurance/Policy | C5: PolicyNumber | D5: policy.mstpolicy.indmast.policyno | E5: KDE00244 | F5: Insurance/Policy | G5: Completeness | H5: 154371 | I5: 0 | J5: 154371 | K5: 100 | L5: 100 | M5: Pass | N5: m_PolicyNumber_Completeness_DS462 | O5: LDAP_TLI_EDW\sarinyarat | P5: 46153.587
A6: 01E7BC02-E336-48CC-B07D-646F0F9B48B9 | B6: KDE00252policy.cbranch.dsubmit.rpnoCompletenessInsurance/Policy | C6: PremiumReceiptNumber | D6: policy.cbranch.dsubmit.rpno | E6: KDE00252 | F6: Insurance/Policy | G6: Completeness | H6: 19645616 | I6: 0 | J6: 19645616 | K6: 100 | L6: 100 | M6: Pass | N6: m_PremiumReceiptNumber_Completeness_DS485 | O6: Native\Administrator | P6: 46153.565
A7: 02F0C1A0-16CF-4699-AA64-F7B599FA7A5F | B7: KDE00346group_life.glife.claim.pay_methodCompletenessFinance | C7: PaymentMethodCode | D7: group_life.glife.claim.pay_method | E7: KDE00346 | F7: Finance | G7: Completeness | H7: 32128 | I7: 0 | J7: 32128 | K7: 100 | L7: 100 | M7: Pass | N7: m_PaymentMethodCode_Completeness_DS335 | O7: LDAP_TLI_EDW\sarinyarat | P7: 46153.578
A8: 030A7A04-A50D-4953-91C8-1ADA01355040 | B8: KDE00445sales.sales.person.emailValiditySales | C8: EmailAddress | D8: sales.sales.person.email | E8: KDE00445 | F8: Sales | G8: Validity | H8: 43187 | I8: 2 | J8: 43185 | K8: 99.995369 | L8: 100 | M8: Fail | N8: m_EmailAddress_Validity_DS685 | O8: LDAP_TLI_EDW\sarinyarat | P8: 46153.584
A9: 0346E2FD-DAFF-4ACA-AA1D-305D978B62A5 | B9: KDE00155sales.sales.person.salesidCompletenessSales | C9: AgentIDNumber | D9: sales.sales.person.salesid | E9: KDE00155 | F9: Sales | G9: Completeness | H9: 45644 | I9: 0 | J9: 45644 | K9: 100 | L9: 100 | M9: Pass | N9: m_AgentIDNumber_Completeness_DS678 | O9: Native\Administrator | P9: 46153.561
A10: 03A7D880-6A40-4FDC-A137-48E602C96AF2 | B10: KDE00160sales.sales.person.personidCompletenessSales | C10: AgentIDNumber | D10: sales.sales.person.personid | E10: KDE00160 | F10: Sales | G10: Completeness | H10: 45644 | I10: 0 | J10: 45644 | K10: 100 | L10: 100 | M10: Pass | N10: m_AgentIDNumber_Completeness_DS681 | O10: Native\Administrator | P10: 46153.561
A11: 03AC8E04-27A6-42C7-8937-D07F95CFA31F | B11: KDE00727underwrite.cunderwrite.bnf.bnftypeCompletenessCustomer | C11: PersonTypeCode | D11: underwrite.cunderwrite.bnf.bnftype | E11: KDE00727 | F11: Customer | G11: Completeness | H11: 580930 | I11: 0 | J11: 580930 | K11: 100 | L11: 100 | M11: Pass | N11: m_PersonTypeCode_Completeness_DS896 | O11: LDAP_TLI_EDW\sarinyarat | P11: 46153.584
A12: 03B3007E-6074-47B8-AC7B-B6D8508F0F34 | B12: KDE00171policy.mstpolicy.indmast.effectivedateCompletenessInsurance/Policy | C12: PolicyEffectiveDate | D12: policy.mstpolicy.indmast.effectivedate | E12: KDE00171 | F12: Insurance/Policy | G12: Completeness | H12: 154371 | I12: 0 | J12: 154371 | K12: 100 | L12: 100 | M12: Pass | N12: m_PolicyEffectiveDate_Completeness_DS411 | O12: LDAP_TLI_EDW\sarinyarat | P12: 46153.587
A13: 03EA2486-71EF-4077-91FB-38E4F808F444 | B13: KDE00001customer.contact.phone.phone_numberCompletenessCustomer | C13: MobilePhoneNumber | D13: customer.contact.phone.phone_number | E13: KDE00001 | F13: Customer | G13: Completeness | H13: 6683747 | I13: 9 | J13: 6683738 | K13: 99.999865 | L13: 100 | M13: Fail | N13: m_MobilePhoneNumber_Completeness_DS147 | O13: LDAP_TLI_EDW\sarinyarat | P13: 46153.59
